Workbook

Sheet Instructivo
A1: CONTROL DE STOCK SEMANAL — COMO USAR ESTE LIBRO
A2: Candela Cafe & Patisserie · Prueba de 1 semana · 6 areas de produccion, 159 insumos, 141 productos
A3: Leer esta hoja antes de imprimir nada. Toma 5 minutos y evita una semana perdida.
B5: QUE RESPONDE ESTE LIBRO
B6: Cuanto insumo hay, cuanto se consumio de verdad en la semana, y si ese consumo se explica con lo que se elaboro. Lo que no se explica queda a la vista, separado en cuatro causas posibles: mal uso del insumo (rinde menos de lo que deberia), consumo del personal sin registrar, insumo que desaparece, y producto que se quema o se tira.
B7: ANTES DE ARRANCAR (el domingo previo, 1 hora)
B8: • 1. Hoja CONFIG: poner la fecha del lunes de arranque y el nombre del jefe de cada area. Todas las fechas del libro se completan solas.
B9: • 2. Hoja INSUMOS: revisar UNIDAD BASE y CONTENIDO POR BULTO de los 159 insumos. Los puse inferidos del nombre (ej. "Harina 000 x25kg" -> 25 kg por bulto) pero hay que confirmarlos contra el envase real. Si esto esta mal, todo el analisis sale mal.
B10: • 3. Hoja INSUMOS, columna CRITICO: vienen 62 marcados como SI (los caros y los de mayor riesgo). Esos son los unicos que se cuentan todos los dias. Sumar o quitar los que hagan falta.
B11: • 4. Imprimir: la planilla 1 (una por area, usando el filtro de AREA), la planilla 2, la planilla 3 (una por area) y la planilla 4 de cada area.
B12: DURANTE LA SEMANA
B13: • LUNES TEMPRANO, antes de producir — PLANILLA 1 (Inventario inicial): cada jefe de area cuenta TODOS sus insumos. Bultos cerrados + lo que hay suelto del envase abierto. La planilla calcula el total.
B14: • TODOS LOS DIAS, cuando entra mercaderia — PLANILLA 2 (Ingresos): quien recibe anota area, insumo, cantidad y numero de remito. En el momento, no despues. Un ingreso no anotado aparece al final como un faltante que no existe.
B15: • TODOS LOS DIAS, al cierre de la jornada — PLANILLA 3 (Conteo diario): cada jefe cuenta solo sus insumos criticos (unos 10). Son 5 minutos.
B16: • TODOS LOS DIAS, mientras se produce — PLANILLA 4 (Produccion diaria): el jefe de area anota lo ELABORADO y lo DESCARTADO de cada producto. Una planilla por area, ya con los productos del catalogo impresos.
... B29: COMO INTERPRETAR CADA SENAL
B30: SENAL EN LA PLANILLA | D30: LO QUE PROBABLEMENTE SIGNIFICA | F30: QUE HACER
B31: Consumo real muy por encima del de Fudo, parejo toda la semana | D31: La receta rinde menos de lo que dice la ficha tecnica, o se desperdicia en el proceso | F31: Pesar una produccion completa y recalcular la ficha
B32: Consumo real alto pero concentrado en 1 o 2 dias | D32: Un evento puntual: una tanda perdida, un derrame, o un retiro no registrado | F32: Cruzar con la planilla 5 y con quien estuvo de turno ese dia
B33: Consumo negativo (el stock final es mayor al posible) | D33: Entro mercaderia que nadie anoto en la planilla 2 | F33: Buscar el remito y reforzar el registro de ingresos
B34: Diferencia sin explicar positiva y grande en un producto | D34: Salio producto sin venderse ni registrarse: consumo del personal o faltante | F34: Comparar con Fudo consumos internos y con el sobrante en exhibicion
B35: Descarte declarado muy por debajo de lo que se ve en el piso | D35: No se esta anotando lo que se tira | F35: Insistir en la planilla 5: sin motivo cargado, todo se lee como faltante
B36: Lo recibido no coincide con la factura | D36: Se factura mas de lo que entra, o se recibe sin controlar | F36: Reclamar al proveedor y pesar en la recepcion
B37: LIMITES DE ESTE METODO (para no sacar conclusiones de mas)
B38: NO se lleva stock de producto terminado. La diferencia del analisis B incluye lo que quedo en exhibicion al cierre del domingo. Lea la tendencia y los casos grandes, no el numero exacto de cada producto.
B39: Una sola semana no distingue una causa estable de una casualidad. Sirve para senalar donde mirar, no para acusar a nadie.
B40: La calidad del resultado depende del conteo. Si el inventario inicial se hace "a ojo", el libro devuelve numeros prolijos y falsos.
B41: Cocina San Luis no tiene productos en el catalogo de la app: su planilla 4 viene en blanco para escribirlos a mano.
B42: REGLA DE ORO
B43: Solo se escribe en las celdas AMARILLAS. Todo lo que esta en negro o en verde es formula: si se pisa, se rompe el analisis.

Sheet Config
A1: CONFIGURACION DE LA SEMANA DE CONTROL
A2: Candela Cafe & Patisserie · Complete SOLO las celdas amarillas. Todo el libro se actualiza solo.
A3: Esta hoja alimenta las fechas y los desplegables del resto de las planillas.
A5: 1 · SEMANA DE CONTROL
A6: Fecha de inicio (lunes) | C6: Escriba la fecha del lunes en que arranca el control.
A7: Fecha de cierre (domingo) | B7: =IF($B$6="","",$B$6+6) | C7: Se calcula solo.
A9: DIA | B9: FECHA | C9: OBSERVACIONES DEL DIA
A10: Lunes | B10: =IF($B$6="","",$B$6+0)
A11: Martes | B11: =IF($B$6="","",$B$6+1)
A12: Miercoles | B12: =IF($B$6="","",$B$6+2)
A13: Jueves | B13: =IF($B$6="","",$B$6+3)
A14: Viernes | B14: =IF($B$6="","",$B$6+4)
A15: Sabado | B15: =IF($B$6="","",$B$6+5)
A16: Domingo | B16: =IF($B$6="","",$B$6+6)
A18: 2 · RESPONSABLES POR AREA
A19: AREA | B19: DONDE SE ELABORA | C19: JEFE DE AREA (nombre) | D19: FIRMA / ACLARACION
A20: Panadería | B20: Central
A21: Pastelería | B21: Central
A22: Especialidades | B22: Central
A23: Facturería | B23: Central
A24: Sandwiches | B24: Central
A25: Cocina San Luis | B25: Local San Luis
A27: 3 · MOTIVOS DE DESCARTE (desplegable en la hoja "5 Descartes")
A28: Quemado / mal cocido
A29: Mal armado / defectuoso
A30: Vencido / pasado
A31: Caido / roto
A32: Sobrante no vendido
A33: Prueba / degustacion
A34: Consumo del personal
A35: Devolucion de local
A36: Otro
A38: 4 · LEYENDA DE COLORES Y TIPOS DE LETRA
A39: Celda amarilla, letra azul | B39: La completa una persona a mano. Es el unico lugar donde hay que escribir.
A40: Letra negra, fondo blanco | B40: Formula. NO tocar: se calcula sola.
A41: Letra verde | B41: Trae el dato de otra hoja del libro. NO tocar.
A42: Fondo rojo claro | B42: Alerta: el desvio supera el limite tolerado. Hay que investigar.
A43: Fondo verde claro | B43: Dentro de lo esperado.
A45: 5 · LIMITES DE TOLERANCIA (para las alertas del Tablero)
A46: Desvio maximo tolerado en insumos (%) | B46: 0.05 | C46: Diferencia entre consumo real y consumo teorico/Fudo.
A47: Descarte maximo tolerado en productos (%) | B47: 0.03 | C47: Sobre el total elaborado de cada producto.
A48: Diferencia maxima tolerada sin explicar (%) | B48: 0.02 | C48: Elaborado menos vendido, consumos y descartes.

Sheet Insumos
A1: MAESTRO DE INSUMOS DE PRODUCCION
A2: Traido del catalogo real de la app de Pedidos de Produccion (159 insumos, 6 areas).
A3: REVISAR ANTES DE ARRANCAR: la unidad y el contenido por bulto fueron inferidos del nombre. Corrija lo que no coincida con el envase real.
A4: AREA | B4: INSUMO | C4: CATEGORIA | D4: PROVEEDOR | E4: UNIDAD BASE | F4: CONTENIDO POR BULTO | G4: CRITICO (conteo diario) | H4: COSTO POR UNIDAD $ | I4: CLAVE (no tocar)
A5: Panadería | B5: Aceite de girasol | E5: L | F5: 5 | G5: NO | I5: =$A5&" | "&$B5
A6: Panadería | B6: Aceite de oliva | E6: L | F6: 5 | G6: NO | I6: =$A6&" | "&$B6
A7: Panadería | B7: Aditivo | E7: kg | F7: 1 | G7: NO | I7: =$A7&" | "&$B7
A8: Panadería | B8: Avena | E8: kg | F8: 1 | G8: NO | I8: =$A8&" | "&$B8
A9: Panadería | B9: Azucar | E9: kg | F9: 1 | G9: SI | I9: =$A9&" | "&$B9
A10: Panadería | B10: Azucar impalpable | E10: kg | F10: 1 | G10: NO | I10: =$A10&" | "&$B10
A11: Panadería | B11: Berlina | E11: kg | F11: 1 | G11: NO | I11: =$A11&" | "&$B11
A12: Panadería | B12: Bicarbonato de amonio | E12: kg | F12: 1 | G12: NO | I12: =$A12&" | "&$B12
A13: Panadería | B13: Bicarbonato de sodio | E13: kg | F13: 1 | G13: NO | I13: =$A13&" | "&$B13
A14: Panadería | B14: Canela en polvo | E14: kg | F14: 1 | G14: NO | I14: =$A14&" | "&$B14
A15: Panadería | B15: Fecula | E15: kg | F15: 1 | G15: NO | I15: =$A15&" | "&$B15
A16: Panadería | B16: Grasa | E16: kg | F16: 1 | G16: SI | I16: =$A16&" | "&$B16
... A42: Panadería | B42: Albahaca | E42: kg | F42: 1 | G42: NO | I42: =$A42&" | "&$B42
A43: Panadería | B43: Tomates cherry | D43: Verdulería | E43: kg | F43: 1 | G43: NO | I43: =$A43&" | "&$B43
A44: Panadería | B44: Cebolla morada | D44: Verdulería | E44: kg | F44: 1 | G44: NO | I44: =$A44&" | "&$B44
A45: Panadería | B45: Albahaca hidropónica | D45: Verdulería | E45: kg | F45: 1 | G45: NO | I45: =$A45&" | "&$B45
A46: Panadería | B46: Rúcula | D46: Verdulería | E46: kg | F46: 1 | G46: NO | I46: =$A46&" | "&$B46
A47: Pastelería | B47: Almendras | E47: kg | F47: 1 | G47: SI | I47: =$A47&" | "&$B47
A48: Pastelería | B48: Arandanos congelados | E48: kg | F48: 1 | G48: SI | I48: =$A48&" | "&$B48
A49: Pastelería | B49: Azucar | E49: kg | F49: 1 | G49: SI | I49: =$A49&" | "&$B49
A50: Pastelería | B50: Azucar impalpable | E50: kg | F50: 1 | G50: NO | I50: =$A50&" | "&$B50
A51: Pastelería | B51: Baño alpino | E51: kg | F51: 1 | G51: SI | I51: =$A51&" | "&$B51
A52: Pastelería | B52: Baño lodiser semiamargo | E52: kg | F52: 1 | G52: SI | I52: =$A52&" | "&$B52
A53: Pastelería | B53: Cacao | E53: kg | F53: 1 | G53: NO | I53: =$A53&" | "&$B53
A54: Pastelería | B54: Chocolate chip | E54: kg | F54: 1 | G54: SI | I54: =$A54&" | "&$B54
A55: Pastelería | B55: Chocolate gotas | E55: kg | F55: 1 | G55: SI | I55: =$A55&" | "&$B55
A56: Pastelería | B56: Chocolate moldeo | E56: kg | F56: 1 | G56: SI | I56: =$A56&" | "&$B56
A57: Pastelería | B57: Coco rallado | E57: kg | F57: 1 | G57: NO | I57: =$A57&" | "&$B57
A58: Pastelería | B58: Confites mini | E58: kg | F58: 1 | G58: NO | I58: =$A58&" | "&$B58
... A84: Pastelería | B84: Variegato Maracuya | E84: L | F84: 1 | G84: NO | I84: =$A84&" | "&$B84
A85: Pastelería | B85: Frutilla | D85: Verdulería | E85: kg | F85: 1 | G85: NO | I85: =$A85&" | "&$B85
A86: Pastelería | B86: Arándanos | D86: Verdulería | E86: kg | F86: 1 | G86: NO | I86: =$A86&" | "&$B86
A87: Pastelería | B87: Limón | D87: Verdulería | E87: kg | F87: 1 | G87: NO | I87: =$A87&" | "&$B87
A88: Pastelería | B88: Durazno | D88: Verdulería | E88: kg | F88: 1 | G88: NO | I88: =$A88&" | "&$B88
A89: Pastelería | B89: Kiwi | D89: Verdulería | E89: kg | F89: 1 | G89: NO | I89: =$A89&" | "&$B89
A90: Pastelería | B90: Ananá | D90: Verdulería | E90: kg | F90: 1 | G90: NO | I90: =$A90&" | "&$B90
A91: Especialidades | B91: Almidón de maiz | E91: kg | F91: 1 | G91: NO | I91: =$A91&" | "&$B91
A92: Especialidades | B92: Azucar | E92: kg | F92: 1 | G92: SI | I92: =$A92&" | "&$B92
A93: Especialidades | B93: Dulce de leche repostero | E93: kg | F93: 1 | G93: SI | I93: =$A93&" | "&$B93
A94: Especialidades | B94: Esencia de vainilla | E94: L | F94: 1 | G94: NO | I94: =$A94&" | "&$B94
A95: Especialidades | B95: Fecula | E95: kg | F95: 1 | G95: NO | I95: =$A95&" | "&$B95
A96: Especialidades | B96: Grasa | E96: kg | F96: 1 | G96: SI | I96: =$A96&" | "&$B96
A97: Especialidades | B97: Huevos | E97: u | F97: 30 | G97: SI | I97: =$A97&" | "&$B97
A98: Especialidades | B98: Jamon cocido | E98: kg | F98: 1 | G98: SI | I98: =$A98&" | "&$B98
A99: Especialidades | B99: Leche entera | E99: L | F99: 1 | G99: SI | I99: =$A99&" | "&$B99
A100: Especialidades | B100: Manteca | E100: kg | F100: 1 | G100: SI | I100: =$A100&" | "&$B100
A101: Especialidades | B101: Mayonesa | E101: kg | F101: 1 | G101: NO | I101: =$A101&" | "&$B101
A102: Especialidades | B102: Nueces | E102: kg | F102: 1 | G102: SI | I102: =$A102&" | "&$B102
... A110: Especialidades | B110: Tomates cherrys | E110: kg | F110: 1 | G110: NO | I110: =$A110&" | "&$B110
A111: Especialidades | B111: Naranja | D111: Verdulería | E111: kg | F111: 1 | G111: NO | I111: =$A111&" | "&$B111
A112: Especialidades | B112: Limón | D112: Verdulería | E112: kg | F112: 1 | G112: NO | I112: =$A112&" | "&$B112
A113: Especialidades | B113: Durazno | D113: Verdulería | E113: kg | F113: 1 | G113: NO | I113: =$A113&" | "&$B113
A114: Facturería | B114: Azucar | E114: kg | F114: 1 | G114: SI | I114: =$A114&" | "&$B114
A115: Facturería | B115: Berlina | E115: kg | F115: 1 | G115: NO | I115: =$A115&" | "&$B115
A116: Facturería | B116: Cacao | E116: kg | F116: 1 | G116: NO | I116: =$A116&" | "&$B116
A117: Facturería | B117: Crema de leche | E117: L | F117: 1 | G117: SI | I117: =$A117&" | "&$B117
A118: Facturería | B118: Crema Vegetal | E118: L | F118: 1 | G118: SI | I118: =$A118&" | "&$B118
A119: Facturería | B119: Dulce de leche repostero | E119: kg | F119: 1 | G119: SI | I119: =$A119&" | "&$B119
A120: Facturería | B120: Dulce de membrillo | E120: kg | F120: 1 | G120: NO | I120: =$A120&" | "&$B120
A121: Facturería | B121: Esencia de vainilla | E121: L | F121: 1 | G121: NO | I121: =$A121&" | "&$B121
A122: Facturería | B122: Grasa | E122: kg | F122: 1 | G122: SI | I122: =$A122&" | "&$B122
A123: Facturería | B123: Huevos | E123: u | F123: 30 | G123: SI | I123: =$A123&" | "&$B123
A124: Facturería | B124: Leche entera | E124: L | F124: 1 | G124: SI | I124: =$A124&" | "&$B124
A125: Facturería | B125: Levadura | E125: kg | F125: 1 | G125: SI | I125: =$A125&" | "&$B125
... A129: Facturería | B129: Sal | E129: kg | F129: 1 | G129: NO | I129: =$A129&" | "&$B129
A130: Sandwiches | B130: Rúcula hidropónica | D130: Verdulería | E130: kg | F130: 1 | G130: NO | I130: =$A130&" | "&$B130
A131: Sandwiches | B131: Lechuga hidropónica | D131: Verdulería | E131: kg | F131: 1 | G131: NO | I131: =$A131&" | "&$B131
A132: Sandwiches | B132: Tomates | D132: Verdulería | E132: kg | F132: 1 | G132: NO | I132: =$A132&" | "&$B132
A133: Sandwiches | B133: Tomates cherry | D133: Verdulería | E133: kg | F133: 1 | G133: NO | I133: =$A133&" | "&$B133
A134: Sandwiches | B134: Albahaca hidropónica | D134: Verdulería | E134: kg | F134: 1 | G134: NO | I134: =$A134&" | "&$B134
A135: Cocina San Luis | B135: Detergente | C135: Limpieza | E135: L | F135: 5 | G135: NO | I135: =$A135&" | "&$B135
A136: Cocina San Luis | B136: Lavandina | C136: Limpieza | E136: L | F136: 5 | G136: NO | I136: =$A136&" | "&$B136
A137: Cocina San Luis | B137: Queso de máquina barra | C137: Fiambres y Lácteos | E137: kg | F137: 1 | G137: SI | I137: =$A137&" | "&$B137
A138: Cocina San Luis | B138: Queso cheddar fetas | C138: Fiambres y Lácteos | E138: kg | F138: 1 | G138: SI | I138: =$A138&" | "&$B138
A139: Cocina San Luis | B139: Queso roquefort | C139: Fiambres y Lácteos | E139: kg | F139: 1 | G139: SI | I139: =$A139&" | "&$B139
A140: Cocina San Luis | B140: Queso parmesano rallo | C140: Fiambres y Lácteos | E140: kg | F140: 1 | G140: SI | I140: =$A140&" | "&$B140
A141: Cocina San Luis | B141: Queso crema s/sabor | C141: Fiambres y Lácteos | E141: kg | F141: 1 | G141: NO | I141: =$A141&" | "&$B141
A142: Cocina San Luis | B142: Jamón cocido paladini | C142: Fiambres y Lácteos | E142: kg | F142: 1 | G142: SI | I142: =$A142&" | "&$B142
A143: Cocina San Luis | B143: Salame milán | C143: Fiambres y Lácteos | E143: kg | F143: 1 | G143: SI | I143: =$A143&" | "&$B143
A144: Cocina San Luis | B144: Lomo ahumado feteado | C144: Fiambres y Lácteos | E144: kg | F144: 1 | G144: SI | I144: =$A144&" | "&$B144
A145: Cocina San Luis | B145: Panceta ahumada feteada | C145: Fiambres y Lácteos | E145: kg | F145: 1 | G145: SI | I145: =$A145&" | "&$B145
A146: Cocina San Luis | B146: Salchicha viena f/larga | C146: Fiambres y Lácteos | E146: kg | F146: 1 | G146: NO | I146: =$A146&" | "&$B146
... A148: Cocina San Luis | B148: Crema de leche | C148: Fiambres y Lácteos | E148: L | F148: 1 | G148: SI | I148: =$A148&" | "&$B148
A149: Cocina San Luis | B149: Pomelo | C149: Verdulería | D149: Verdulería | E149: kg | F149: 1 | G149: NO | I149: =$A149&" | "&$B149
A150: Cocina San Luis | B150: Naranja | C150: Verdulería | D150: Verdulería | E150: kg | F150: 1 | G150: NO | I150: =$A150&" | "&$B150
A151: Cocina San Luis | B151: Limón | C151: Verdulería | D151: Verdulería | E151: kg | F151: 1 | G151: NO | I151: =$A151&" | "&$B151
A152: Cocina San Luis | B152: Lechuga crespa | C152: Verdulería | D152: Verdulería | E152: kg | F152: 1 | G152: NO | I152: =$A152&" | "&$B152
A153: Cocina San Luis | B153: Tomate x kg | C153: Verdulería | D153: Verdulería | E153: kg | F153: 1 | G153: NO | I153: =$A153&" | "&$B153
A154: Cocina San Luis | B154: Tomate Cherry x kg | C154: Verdulería | D154: Verdulería | E154: kg | F154: 1 | G154: NO | I154: =$A154&" | "&$B154
A155: Cocina San Luis | B155: Rúcula | C155: Verdulería | D155: Verdulería | E155: kg | F155: 1 | G155: NO | I155: =$A155&" | "&$B155
A156: Cocina San Luis | B156: Ciruela x kg | C156: Verdulería | D156: Verdulería | E156: kg | F156: 1 | G156: NO | I156: =$A156&" | "&$B156
A157: Cocina San Luis | B157: Kiwi x kg | C157: Verdulería | D157: Verdulería | E157: kg | F157: 1 | G157: NO | I157: =$A157&" | "&$B157
A158: Cocina San Luis | B158: Banana x unidad | C158: Verdulería | D158: Verdulería | E158: u | F158: 1 | G158: NO | I158: =$A158&" | "&$B158
A159: Cocina San Luis | B159: Palta x kg | C159: Verdulería | D159: Verdulería | E159: kg | F159: 1 | G159: SI | I159: =$A159&" | "&$B159
A160: Cocina San Luis | B160: Frutilla x kg | C160: Verdulería | D160: Verdulería | E160: kg | F160: 1 | G160: SI | I160: =$A160&" | "&$B160
... A163: Cocina San Luis | B163: Jengibre x unidad | C163: Verdulería | D163: Verdulería | E163: u | F163: 1 | G163: NO | I163: =$A163&" | "&$B163
...

Sheet Productos
A1: MAESTRO DE PRODUCTOS ELABORADOS
A2: Traido del catalogo real de la app (141 productos).
A3: Cocina San Luis no tiene productos en el catalogo: se cargan a mano en su planilla de produccion.
A4: AREA | B4: PRODUCTO | C4: UNIDAD | D4: DONDE SE ELABORA | E4: CLAVE (no tocar)
A5: Panadería | B5: Bagel | C5: u | D5: Central | E5: =$A5&" | "&$B5
A6: Panadería | B6: Bizcochos | C6: kg | D6: Central | E6: =$A6&" | "&$B6
A7: Panadería | B7: Bizcochos de margarina | C7: kg | D7: Central | E7: =$A7&" | "&$B7
A8: Panadería | B8: Bizcochos redondos | C8: kg | D8: Central | E8: =$A8&" | "&$B8
A9: Panadería | B9: Bollitos B/N | C9: u | D9: Central | E9: =$A9&" | "&$B9
A10: Panadería | B10: Bollos grandes | C10: u | D10: Central | E10: =$A10&" | "&$B10
A11: Panadería | B11: Caseras | C11: u | D11: Central | E11: =$A11&" | "&$B11
A12: Panadería | B12: Caseritas | C12: u | D12: Central | E12: =$A12&" | "&$B12
A13: Panadería | B13: Chatas | C13: kg | D13: Central | E13: =$A13&" | "&$B13
A14: Panadería | B14: Cremona | C14: u | D14: Central | E14: =$A14&" | "&$B14
A15: Panadería | B15: Focaccia | C15: u | D15: Central | E15: =$A15&" | "&$B15
A16: Panadería | B16: Libritos | C16: u | D16: Central | E16: =$A16&" | "&$B16
... A145: Sandwiches | B145: Miga de cantimpalo y queso | C145: u | D145: Central | E145: =$A145&" | "&$B145

Sheet 1 Inv Inicial
A1: PLANILLA 1 · INVENTARIO INICIAL DE INSUMOS
A2: Se cuenta el LUNES antes de arrancar a producir. Una hoja por area: filtre por AREA e imprima.
A3: COMO CONTAR: bultos cerrados + lo que hay suelto del abierto. Ejemplo: 3 bolsas de 25 kg + 8,5 kg sueltos -> Bultos = 3, Parcial = 8,5, TOTAL = 83,5 kg (lo calcula la planilla).
A4: AREA | B4: INSUMO | C4: UNID. | D4: CONTENIDO POR BULTO | E4: BULTOS CERRADOS | F4: PARCIAL (suelto) | G4: TOTAL (calculado) | H4: CONTO (iniciales) | I4: OBSERVACIONES
A5: =Insumos!$A5 | B5: =Insumos!$B5 | C5: =Insumos!$E5 | D5: =Insumos!$F5 | G5: =IFERROR($E5*$D5,0)+IFERROR($F5,0)
A6: =Insumos!$A6 | B6: =Insumos!$B6 | C6: =Insumos!$E6 | D6: =Insumos!$F6 | G6: =IFERROR($E6*$D6,0)+IFERROR($F6,0)
A7: =Insumos!$A7 | B7: =Insumos!$B7 | C7: =Insumos!$E7 | D7: =Insumos!$F7 | G7: =IFERROR($E7*$D7,0)+IFERROR($F7,0)
A8: =Insumos!$A8 | B8: =Insumos!$B8 | C8: =Insumos!$E8 | D8: =Insumos!$F8 | G8: =IFERROR($E8*$D8,0)+IFERROR($F8,0)
A9: =Insumos!$A9 | B9: =Insumos!$B9 | C9: =Insumos!$E9 | D9: =Insumos!$F9 | G9: =IFERROR($E9*$D9,0)+IFERROR($F9,0)
A10: =Insumos!$A10 | B10: =Insumos!$B10 | C10: =Insumos!$E10 | D10: =Insumos!$F10 | G10: =IFERROR($E10*$D10,0)+IFERROR($F10,0)
A11: =Insumos!$A11 | B11: =Insumos!$B11 | C11: =Insumos!$E11 | D11: =Insumos!$F11 | G11: =IFERROR($E11*$D11,0)+IFERROR($F11,0)
A12: =Insumos!$A12 | B12: =Insumos!$B12 | C12: =Insumos!$E12 | D12: =Insumos!$F12 | G12: =IFERROR($E12*$D12,0)+IFERROR($F12,0)
A13: =Insumos!$A13 | B13: =Insumos!$B13 | C13: =Insumos!$E13 | D13: =Insumos!$F13 | G13: =IFERROR($E13*$D13,0)+IFERROR($F13,0)
A14: =Insumos!$A14 | B14: =Insumos!$B14 | C14: =Insumos!$E14 | D14: =Insumos!$F14 | G14: =IFERROR($E14*$D14,0)+IFERROR($F14,0)
A15: =Insumos!$A15 | B15: =Insumos!$B15 | C15: =Insumos!$E15 | D15: =Insumos!$F15 | G15: =IFERROR($E15*$D15,0)+IFERROR($F15,0)
A16: =Insumos!$A16 | B16: =Insumos!$B16 | C16: =Insumos!$E16 | D16: =Insumos!$F16 | G16: =IFERROR($E16*$D16,0)+IFERROR($F16,0)
... A163: =Insumos!$A163 | B163: =Insumos!$B163 | C163: =Insumos!$E163 | D163: =Insumos!$F163 | G163: =IFERROR($E163*$D163,0)+IFERROR($F163,0)

Sheet 2 Ingresos
A1: PLANILLA 2 · INGRESOS DE MERCADERIA DE LA SEMANA
A2: Se anota CADA VEZ que entra mercaderia a un area, en el momento en que entra. Sin esto no se puede calcular el consumo.
A3: La fila 5 es un EJEMPLO: borrela antes de empezar. Cargue desde la fila 6.
A4: FECHA | B4: AREA | C4: INSUMO | D4: PROVEEDOR | E4: N° REMITO / FACTURA | F4: BULTOS | G4: CONTENIDO POR BULTO | H4: PARCIAL | I4: TOTAL (calculado) | J4: RECIBIO (iniciales) | K4: CONTROL AUTOMATICO
A5: =IF(Config!$B$6="","",Config!$B$6) | B5: Panaderia | C5: Harina 000 x25kg | D5: Molino XX | E5: R-0001234 | F5: 4 | G5: =IFERROR(INDEX(Insumos!$F$5:$F$163,MATCH($B5&" | "&$C5,Insumos!$I$5:$I$163,0)),"") | H5: 12.5 | I5: =IFERROR($F5*$G5,0)+IFERROR($H5,0) | J5: JP | K5: EJEMPLO - borrar esta fila
G6: =IFERROR(INDEX(Insumos!$F$5:$F$163,MATCH($B6&" | "&$C6,Insumos!$I$5:$I$163,0)),"") | I6: =IFERROR($F6*$G6,0)+IFERROR($H6,0) | K6: =IF($C6="","",IF(COUNTIF(Insumos!$I$5:$I$163,$B6&" | "&$C6)=0,"REVISAR: area+insumo no existe en el maestro","OK"))
G7: =IFERROR(INDEX(Insumos!$F$5:$F$163,MATCH($B7&" | "&$C7,Insumos!$I$5:$I$163,0)),"") | I7: =IFERROR($F7*$G7,0)+IFERROR($H7,0) | K7: =IF($C7="","",IF(COUNTIF(Insumos!$I$5:$I$163,$B7&" | "&$C7)=0,"REVISAR: area+insumo no existe en el maestro","OK"))
G8: =IFERROR(INDEX(Insumos!$F$5:$F$163,MATCH($B8&" | "&$C8,Insumos!$I$5:$I$163,0)),"") | I8: =IFERROR($F8*$G8,0)+IFERROR($H8,0) | K8: =IF($C8="","",IF(COUNTIF(Insumos!$I$5:$I$163,$B8&" | "&$C8)=0,"REVISAR: area+insumo no existe en el maestro","OK"))
G9: =IFERROR(INDEX(Insumos!$F$5:$F$163,MATCH($B9&" | "&$C9,Insumos!$I$5:$I$163,0)),"") | I9: =IFERROR($F9*$G9,0)+IFERROR($H9,0) | K9: =IF($C9="","",IF(COUNTIF(Insumos!$I$5:$I$163,$B9&" | "&$C9)=0,"REVISAR: area+insumo no existe en el maestro","OK"))
G10: =IFERROR(INDEX(Insumos!$F$5:$F$163,MATCH($B10&" | "&$C10,Insumos!$I$5:$I$163,0)),"") | I10: =IFERROR($F10*$G10,0)+IFERROR($H10,0) | K10: =IF($C10="","",IF(COUNTIF(Insumos!$I$5:$I$163,$B10&" | "&$C10)=0,"REVISAR: area+insumo no existe en el maestro","OK"))
G11: =IFERROR(INDEX(Insumos!$F$5:$F$163,MATCH($B11&" | "&$C11,Insumos!$I$5:$I$163,0)),"") | I11: =IFERROR($F11*$G11,0)+IFERROR($H11,0) | K11: =IF($C11="","",IF(COUNTIF(Insumos!$I$5:$I$163,$B11&" | "&$C11)=0,"REVISAR: area+insumo no existe en el maestro","OK"))
G12: =IFERROR(INDEX(Insumos!$F$5:$F$163,MATCH($B12&" | "&$C12,Insumos!$I$5:$I$163,0)),"") | I12: =IFERROR($F12*$G12,0)+IFERROR($H12,0) | K12: =IF($C12="","",IF(COUNTIF(Insumos!$I$5:$I$163,$B12&" | "&$C12)=0,"REVISAR: area+insumo no existe en el maestro","OK"))
G13: =IFERROR(INDEX(Insumos!$F$5:$F$163,MATCH($B13&" | "&$C13,Insumos!$I$5:$I$163,0)),"") | I13: =IFERROR($F13*$G13,0)+IFERROR($H13,0) | K13: =IF($C13="","",IF(COUNTIF(Insumos!$I$5:$I$163,$B13&" | "&$C13)=0,"REVISAR: area+insumo no existe en el maestro","OK"))
G14: =IFERROR(INDEX(Insumos!$F$5:$F$163,MATCH($B14&" | "&$C14,Insumos!$I$5:$I$163,0)),"") | I14: =IFERROR($F14*$G14,0)+IFERROR($H14,0) | K14: =IF($C14="","",IF(COUNTIF(Insumos!$I$5:$I$163,$B14&" | "&$C14)=0,"REVISAR: area+insumo no existe en el maestro","OK"))
G15: =IFERROR(INDEX(Insumos!$F$5:$F$163,MATCH($B15&" | "&$C15,Insumos!$I$5:$I$163,0)),"") | I15: =IFERROR($F15*$G15,0)+IFERROR($H15,0) | K15: =IF($C15="","",IF(COUNTIF(Insumos!$I$5:$I$163,$B15&" | "&$C15)=0,"REVISAR: area+insumo no existe en el maestro","OK"))
G16: =IFERROR(INDEX(Insumos!$F$5:$F$163,MATCH($B16&" | "&$C16,Insumos!$I$5:$I$163,0)),"") | I16: =IFERROR($F16*$G16,0)+IFERROR($H16,0) | K16: =IF($C16="","",IF(COUNTIF(Insumos!$I$5:$I$163,$B16&" | "&$C16)=0,"REVISAR: area+insumo no existe en el maestro","OK"))
G17: =IFERROR(INDEX(Insumos!$F$5:$F$163,MATCH($B17&" | "&$C17,Insumos!$I$5:$I$163,0)),"") | I17: =IFERROR($F17*$G17,0)+IFERROR($H17,0) | K17: =IF($C17="","",IF(COUNTIF(Insumos!$I$5:$I$163,$B17&" | "&$C17)=0,"REVISAR: area+insumo no existe en el maestro","OK"))
... G255: =IFERROR(INDEX(Insumos!$F$5:$F$163,MATCH($B255&" | "&$C255,Insumos!$I$5:$I$163,0)),"") | I255: =IFERROR($F255*$G255,0)+IFERROR($H255,0) | K255: =IF($C255="","",IF(COUNTIF(Insumos!$I$5:$I$163,$B255&" | "&$C255)=0,"REVISAR: area+insumo no existe en el maestro","OK"))

Sheet 3 Conteo Diario
A1: PLANILLA 3 · CONTEO DIARIO DE INSUMOS CRITICOS
A2: Cada jefe de area cuenta SOLO sus insumos criticos, al cierre de su jornada. 62 insumos en total (unos 10 por area).
A3: Filtre por AREA e imprima una hoja por area. Mismo criterio que el inventario: bultos cerrados + suelto.
A4: AREA | B4: INSUMO | C4: UNID. | D4: CONTENIDO POR BULTO | E4: =IF(Config!$B$10="","LUNES",UPPER("LUN")&" "&TEXT(Config!$B$10,"dd/mm")) | G4: =IF(Config!$B$11="","MARTES",UPPER("MAR")&" "&TEXT(Config!$B$11,"dd/mm")) | I4: =IF(Config!$B$12="","MIERCOLES",UPPER("MIE")&" "&TEXT(Config!$B$12,"dd/mm")) | K4: =IF(Config!$B$13="","JUEVES",UPPER("JUE")&" "&TEXT(Config!$B$13,"dd/mm")) | M4: =IF(Config!$B$14="","VIERNES",UPPER("VIE")&" "&TEXT(Config!$B$14,"dd/mm")) | O4: =IF(Config!$B$15="","SABADO",UPPER("SAB")&" "&TEXT(Config!$B$15,"dd/mm")) | Q4: =IF(Config!$B$16="","DOMINGO",UPPER("DOM")&" "&TEXT(Config!$B$16,"dd/mm")) | S4: TOTAL LUN | T4: TOTAL MAR | U4: TOTAL MIE | V4: TOTAL JUE | W4: TOTAL VIE | X4: TOTAL SAB | Y4: TOTAL DOM
E5: Bultos | F5: Parcial | G5: Bultos | H5: Parcial | I5: Bultos | J5: Parcial | K5: Bultos | L5: Parcial | M5: Bultos | N5: Parcial | O5: Bultos | P5: Parcial | Q5: Bultos | R5: Parcial
A6: =Insumos!$A9 | B6: =Insumos!$B9 | C6: =Insumos!$E9 | D6: =Insumos!$F9 | S6: =IF(AND(E6="",F6=""),"",IFERROR(E6*$D6,0)+IFERROR(F6,0)) | T6: =IF(AND(G6="",H6=""),"",IFERROR(G6*$D6,0)+IFERROR(H6,0)) | U6: =IF(AND(I6="",J6=""),"",IFERROR(I6*$D6,0)+IFERROR(J6,0)) | V6: =IF(AND(K6="",L6=""),"",IFERROR(K6*$D6,0)+IFERROR(L6,0)) | W6: =IF(AND(M6="",N6=""),"",IFERROR(M6*$D6,0)+IFERROR(N6,0)) | X6: =IF(AND(O6="",P6=""),"",IFERROR(O6*$D6,0)+IFERROR(P6,0)) | Y6: =IF(AND(Q6="",R6=""),"",IFERROR(Q6*$D6,0)+IFERROR(R6,0))
A7: =Insumos!$A16 | B7: =Insumos!$B16 | C7: =Insumos!$E16 | D7: =Insumos!$F16 | S7: =IF(AND(E7="",F7=""),"",IFERROR(E7*$D7,0)+IFERROR(F7,0)) | T7: =IF(AND(G7="",H7=""),"",IFERROR(G7*$D7,0)+IFERROR(H7,0)) | U7: =IF(AND(I7="",J7=""),"",IFERROR(I7*$D7,0)+IFERROR(J7,0)) | V7: =IF(AND(K7="",L7=""),"",IFERROR(K7*$D7,0)+IFERROR(L7,0)) | W7: =IF(AND(M7="",N7=""),"",IFERROR(M7*$D7,0)+IFERROR(N7,0)) | X7: =IF(AND(O7="",P7=""),"",IFERROR(O7*$D7,0)+IFERROR(P7,0)) | Y7: =IF(AND(Q7="",R7=""),"",IFERROR(Q7*$D7,0)+IFERROR(R7,0))
A8: =Insumos!$A17 | B8: =Insumos!$B17 | C8: =Insumos!$E17 | D8: =Insumos!$F17 | S8: =IF(AND(E8="",F8=""),"",IFERROR(E8*$D8,0)+IFERROR(F8,0)) | T8: =IF(AND(G8="",H8=""),"",IFERROR(G8*$D8,0)+IFERROR(H8,0)) | U8: =IF(AND(I8="",J8=""),"",IFERROR(I8*$D8,0)+IFERROR(J8,0)) | V8: =IF(AND(K8="",L8=""),"",IFERROR(K8*$D8,0)+IFERROR(L8,0)) | W8: =IF(AND(M8="",N8=""),"",IFERROR(M8*$D8,0)+IFERROR(N8,0)) | X8: =IF(AND(O8="",P8=""),"",IFERROR(O8*$D8,0)+IFERROR(P8,0)) | Y8: =IF(AND(Q8="",R8=""),"",IFERROR(Q8*$D8,0)+IFERROR(R8,0))
A9: =Insumos!$A18 | B9: =Insumos!$B18 | C9: =Insumos!$E18 | D9: =Insumos!$F18 | S9: =IF(AND(E9="",F9=""),"",IFERROR(E9*$D9,0)+IFERROR(F9,0)) | T9: =IF(AND(G9="",H9=""),"",IFERROR(G9*$D9,0)+IFERROR(H9,0)) | U9: =IF(AND(I9="",J9=""),"",IFERROR(I9*$D9,0)+IFERROR(J9,0)) | V9: =IF(AND(K9="",L9=""),"",IFERROR(K9*$D9,0)+IFERROR(L9,0)) | W9: =IF(AND(M9="",N9=""),"",IFERROR(M9*$D9,0)+IFERROR(N9,0)) | X9: =IF(AND(O9="",P9=""),"",IFERROR(O9*$D9,0)+IFERROR(P9,0)) | Y9: =IF(AND(Q9="",R9=""),"",IFERROR(Q9*$D9,0)+IFERROR(R9,0))
A10: =Insumos!$A19 | B10: =Insumos!$B19 | C10: =Insumos!$E19 | D10: =Insumos!$F19 | S10: =IF(AND(E10="",F10=""),"",IFERROR(E10*$D10,0)+IFERROR(F10,0)) | T10: =IF(AND(G10="",H10=""),"",IFERROR(G10*$D10,0)+IFERROR(H10,0)) | U10: =IF(AND(I10="",J10=""),"",IFERROR(I10*$D10,0)+IFERROR(J10,0)) | V10: =IF(AND(K10="",L10=""),"",IFERROR(K10*$D10,0)+IFERROR(L10,0)) | W10: =IF(AND(M10="",N10=""),"",IFERROR(M10*$D10,0)+IFERROR(N10,0)) | X10: =IF(AND(O10="",P10=""),"",IFERROR(O10*$D10,0)+IFERROR(P10,0)) | Y10: =IF(AND(Q10="",R10=""),"",IFERROR(Q10*$D10,0)+IFERROR(R10,0))
A11: =Insumos!$A20 | B11: =Insumos!$B20 | C11: =Insumos!$E20 | D11: =Insumos!$F20 | S11: =IF(AND(E11="",F11=""),"",IFERROR(E11*$D11,0)+IFERROR(F11,0)) | T11: =IF(AND(G11="",H11=""),"",IFERROR(G11*$D11,0)+IFERROR(H11,0)) | U11: =IF(AND(I11="",J11=""),"",IFERROR(I11*$D11,0)+IFERROR(J11,0)) | V11: =IF(AND(K11="",L11=""),"",IFERROR(K11*$D11,0)+IFERROR(L11,0)) | W11: =IF(AND(M11="",N11=""),"",IFERROR(M11*$D11,0)+IFERROR(N11,0)) | X11: =IF(AND(O11="",P11=""),"",IFERROR(O11*$D11,0)+IFERROR(P11,0)) | Y11: =IF(AND(Q11="",R11=""),"",IFERROR(Q11*$D11,0)+IFERROR(R11,0))
A12: =Insumos!$A21 | B12: =Insumos!$B21 | C12: =Insumos!$E21 | D12: =Insumos!$F21 | S12: =IF(AND(E12="",F12=""),"",IFERROR(E12*$D12,0)+IFERROR(F12,0)) | T12: =IF(AND(G12="",H12=""),"",IFERROR(G12*$D12,0)+IFERROR(H12,0)) | U12: =IF(AND(I12="",J12=""),"",IFERROR(I12*$D12,0)+IFERROR(J12,0)) | V12: =IF(AND(K12="",L12=""),"",IFERROR(K12*$D12,0)+IFERROR(L12,0)) | W12: =IF(AND(M12="",N12=""),"",IFERROR(M12*$D12,0)+IFERROR(N12,0)) | X12: =IF(AND(O12="",P12=""),"",IFERROR(O12*$D12,0)+IFERROR(P12,0)) | Y12: =IF(AND(Q12="",R12=""),"",IFERROR(Q12*$D12,0)+IFERROR(R12,0))
A13: =Insumos!$A22 | B13: =Insumos!$B22 | C13: =Insumos!$E22 | D13: =Insumos!$F22 | S13: =IF(AND(E13="",F13=""),"",IFERROR(E13*$D13,0)+IFERROR(F13,0)) | T13: =IF(AND(G13="",H13=""),"",IFERROR(G13*$D13,0)+IFERROR(H13,0)) | U13: =IF(AND(I13="",J13=""),"",IFERROR(I13*$D13,0)+IFERROR(J13,0)) | V13: =IF(AND(K13="",L13=""),"",IFERROR(K13*$D13,0)+IFERROR(L13,0)) | W13: =IF(AND(M13="",N13=""),"",IFERROR(M13*$D13,0)+IFERROR(N13,0)) | X13: =IF(AND(O13="",P13=""),"",IFERROR(O13*$D13,0)+IFERROR(P13,0)) | Y13: =IF(AND(Q13="",R13=""),"",IFERROR(Q13*$D13,0)+IFERROR(R13,0))
A14: =Insumos!$A47 | B14: =Insumos!$B47 | C14: =Insumos!$E47 | D14: =Insumos!$F47 | S14: =IF(AND(E14="",F14=""),"",IFERROR(E14*$D14,0)+IFERROR(F14,0)) | T14: =IF(AND(G14="",H14=""),"",IFERROR(G14*$D14,0)+IFERROR(H14,0)) | U14: =IF(AND(I14="",J14=""),"",IFERROR(I14*$D14,0)+IFERROR(J14,0)) | V14: =IF(AND(K14="",L14=""),"",IFERROR(K14*$D14,0)+IFERROR(L14,0)) | W14: =IF(AND(M14="",N14=""),"",IFERROR(M14*$D14,0)+IFERROR(N14,0)) | X14: =IF(AND(O14="",P14=""),"",IFERROR(O14*$D14,0)+IFERROR(P14,0)) | Y14: =IF(AND(Q14="",R14=""),"",IFERROR(Q14*$D14,0)+IFERROR(R14,0))
A15: =Insumos!$A48 | B15: =Insumos!$B48 | C15: =Insumos!$E48 | D15: =Insumos!$F48 | S15: =IF(AND(E15="",F15=""),"",IFERROR(E15*$D15,0)+IFERROR(F15,0)) | T15: =IF(AND(G15="",H15=""),"",IFERROR(G15*$D15,0)+IFERROR(H15,0)) | U15: =IF(AND(I15="",J15=""),"",IFERROR(I15*$D15,0)+IFERROR(J15,0)) | V15: =IF(AND(K15="",L15=""),"",IFERROR(K15*$D15,0)+IFERROR(L15,0)) | W15: =IF(AND(M15="",N15=""),"",IFERROR(M15*$D15,0)+IFERROR(N15,0)) | X15: =IF(AND(O15="",P15=""),"",IFERROR(O15*$D15,0)+IFERROR(P15,0)) | Y15: =IF(AND(Q15="",R15=""),"",IFERROR(Q15*$D15,0)+IFERROR(R15,0))
A16: =Insumos!$A49 | B16: =Insumos!$B49 | C16: =Insumos!$E49 | D16: =Insumos!$F49 | S16: =IF(AND(E16="",F16=""),"",IFERROR(E16*$D16,0)+IFERROR(F16,0)) | T16: =IF(AND(G16="",H16=""),"",IFERROR(G16*$D16,0)+IFERROR(H16,0)) | U16: =IF(AND(I16="",J16=""),"",IFERROR(I16*$D16,0)+IFERROR(J16,0)) | V16: =IF(AND(K16="",L16=""),"",IFERROR(K16*$D16,0)+IFERROR(L16,0)) | W16: =IF(AND(M16="",N16=""),"",IFERROR(M16*$D16,0)+IFERROR(N16,0)) | X16: =IF(AND(O16="",P16=""),"",IFERROR(O16*$D16,0)+IFERROR(P16,0)) | Y16: =IF(AND(Q16="",R16=""),"",IFERROR(Q16*$D16,0)+IFERROR(R16,0))
A17: =Insumos!$A51 | B17: =Insumos!$B51 | C17: =Insumos!$E51 | D17: =Insumos!$F51 | S17: =IF(AND(E17="",F17=""),"",IFERROR(E17*$D17,0)+IFERROR(F17,0)) | T17: =IF(AND(G17="",H17=""),"",IFERROR(G17*$D17,0)+IFERROR(H17,0)) | U17: =IF(AND(I17="",J17=""),"",IFERROR(I17*$D17,0)+IFERROR(J17,0)) | V17: =IF(AND(K17="",L17=""),"",IFERROR(K17*$D17,0)+IFERROR(L17,0)) | W17: =IF(AND(M17="",N17=""),"",IFERROR(M17*$D17,0)+IFERROR(N17,0)) | X17: =IF(AND(O17="",P17=""),"",IFERROR(O17*$D17,0)+IFERROR(P17,0)) | Y17: =IF(AND(Q17="",R17=""),"",IFERROR(Q17*$D17,0)+IFERROR(R17,0))
A18: =Insumos!$A52 | B18: =Insumos!$B52 | C18: =Insumos!$E52 | D18: =Insumos!$F52 | S18: =IF(AND(E18="",F18=""),"",IFERROR(E18*$D18,0)+IFERROR(F18,0)) | T18: =IF(AND(G18="",H18=""),"",IFERROR(G18*$D18,0)+IFERROR(H18,0)) | U18: =IF(AND(I18="",J18=""),"",IFERROR(I18*$D18,0)+IFERROR(J18,0)) | V18: =IF(AND(K18="",L18=""),"",IFERROR(K18*$D18,0)+IFERROR(L18,0)) | W18: =IF(AND(M18="",N18=""),"",IFERROR(M18*$D18,0)+IFERROR(N18,0)) | X18: =IF(AND(O18="",P18=""),"",IFERROR(O18*$D18,0)+IFERROR(P18,0)) | Y18: =IF(AND(Q18="",R18=""),"",IFERROR(Q18*$D18,0)+IFERROR(R18,0))
A19: =Insumos!$A54 | B19: =Insumos!$B54 | C19: =Insumos!$E54 | D19: =Insumos!$F54 | S19: =IF(AND(E19="",F19=""),"",IFERROR(E19*$D19,0)+IFERROR(F19,0)) | T19: =IF(AND(G19="",H19=""),"",IFERROR(G19*$D19,0)+IFERROR(H19,0)) | U19: =IF(AND(I19="",J19=""),"",IFERROR(I19*$D19,0)+IFERROR(J19,0)) | V19: =IF(AND(K19="",L19=""),"",IFERROR(K19*$D19,0)+IFERROR(L19,0)) | W19: =IF(AND(M19="",N19=""),"",IFERROR(M19*$D19,0)+IFERROR(N19,0)) | X19: =IF(AND(O19="",P19=""),"",IFERROR(O19*$D19,0)+IFERROR(P19,0)) | Y19: =IF(AND(Q19="",R19=""),"",IFERROR(Q19*$D19,0)+IFERROR(R19,0))
A20: =Insumos!$A55 | B20: =Insumos!$B55 | C20: =Insumos!$E55 | D20: =Insumos!$F55 | S20: =IF(AND(E20="",F20=""),"",IFERROR(E20*$D20,0)+IFERROR(F20,0)) | T20: =IF(AND(G20="",H20=""),"",IFERROR(G20*$D20,0)+IFERROR(H20,0)) | U20: =IF(AND(I20="",J20=""),"",IFERROR(I20*$D20,0)+IFERROR(J20,0)) | V20: =IF(AND(K20="",L20=""),"",IFERROR(K20*$D20,0)+IFERROR(L20,0)) | W20: =IF(AND(M20="",N20=""),"",IFERROR(M20*$D20,0)+IFERROR(N20,0)) | X20: =IF(AND(O20="",P20=""),"",IFERROR(O20*$D20,0)+IFERROR(P20,0)) | Y20: =IF(AND(Q20="",R20=""),"",IFERROR(Q20*$D20,0)+IFERROR(R20,0))
A21: =Insumos!$A56 | B21: =Insumos!$B56 | C21: =Insumos!$E56 | D21: =Insumos!$F56 | S21: =IF(AND(E21="",F21=""),"",IFERROR(E21*$D21,0)+IFERROR(F21,0)) | T21: =IF(AND(G21="",H21=""),"",IFERROR(G21*$D21,0)+IFERROR(H21,0)) | U21: =IF(AND(I21="",J21=""),"",IFERROR(I21*$D21,0)+IFERROR(J21,0)) | V21: =IF(AND(K21="",L21=""),"",IFERROR(K21*$D21,0)+IFERROR(L21,0)) | W21: =IF(AND(M21="",N21=""),"",IFERROR(M21*$D21,0)+IFERROR(N21,0)) | X21: =IF(AND(O21="",P21=""),"",IFERROR(O21*$D21,0)+IFERROR(P21,0)) | Y21: =IF(AND(Q21="",R21=""),"",IFERROR(Q21*$D21,0)+IFERROR(R21,0))
A22: =Insumos!$A59 | B22: =Insumos!$B59 | C22: =Insumos!$E59 | D22: =Insumos!$F59 | S22: =IF(AND(E22="",F22=""),"",IFERROR(E22*$D22,0)+IFERROR(F22,0)) | T22: =IF(AND(G22="",H22=""),"",IFERROR(G22*$D22,0)+IFERROR(H22,0)) | U22: =IF(AND(I22="",J22=""),"",IFERROR(I22*$D22,0)+IFERROR(J22,0)) | V22: =IF(AND(K22="",L22=""),"",IFERROR(K22*$D22,0)+IFERROR(L22,0)) | W22: =IF(AND(M22="",N22=""),"",IFERROR(M22*$D22,0)+IFERROR(N22,0)) | X22: =IF(AND(O22="",P22=""),"",IFERROR(O22*$D22,0)+IFERROR(P22,0)) | Y22: =IF(AND(Q22="",R22=""),"",IFERROR(Q22*$D22,0)+IFERROR(R22,0))
A23: =Insumos!$A60 | B23: =Insumos!$B60 | C23: =Insumos!$E60 | D23: =Insumos!$F60 | S23: =IF(AND(E23="",F23=""),"",IFERROR(E23*$D23,0)+IFERROR(F23,0)) | T23: =IF(AND(G23="",H23=""),"",IFERROR(G23*$D23,0)+IFERROR(H23,0)) | U23: =IF(AND(I23="",J23=""),"",IFERROR(I23*$D23,0)+IFERROR(J23,0)) | V23: =IF(AND(K23="",L23=""),"",IFERROR(K23*$D23,0)+IFERROR(L23,0)) | W23: =IF(AND(M23="",N23=""),"",IFERROR(M23*$D23,0)+IFERROR(N23,0)) | X23: =IF(AND(O23="",P23=""),"",IFERROR(O23*$D23,0)+IFERROR(P23,0)) | Y23: =IF(AND(Q23="",R23=""),"",IFERROR(Q23*$D23,0)+IFERROR(R23,0))
A24: =Insumos!$A62 | B24: =Insumos!$B62 | C24: =Insumos!$E62 | D24: =Insumos!$F62 | S24: =IF(AND(E24="",F24=""),"",IFERROR(E24*$D24,0)+IFERROR(F24,0)) | T24: =IF(AND(G24="",H24=""),"",IFERROR(G24*$D24,0)+IFERROR(H24,0)) | U24: =IF(AND(I24="",J24=""),"",IFERROR(I24*$D24,0)+IFERROR(J24,0)) | V24: =IF(AND(K24="",L24=""),"",IFERROR(K24*$D24,0)+IFERROR(L24,0)) | W24: =IF(AND(M24="",N24=""),"",IFERROR(M24*$D24,0)+IFERROR(N24,0)) | X24: =IF(AND(O24="",P24=""),"",IFERROR(O24*$D24,0)+IFERROR(P24,0)) | Y24: =IF(AND(Q24="",R24=""),"",IFERROR(Q24*$D24,0)+IFERROR(R24,0))
A25: =Insumos!$A69 | B25: =Insumos!$B69 | C25: =Insumos!$E69 | D25: =Insumos!$F69 | S25: =IF(AND(E25="",F25=""),"",IFERROR(E25*$D25,0)+IFERROR(F25,0)) | T25: =IF(AND(G25="",H25=""),"",IFERROR(G25*$D25,0)+IFERROR(H25,0)) | U25: =IF(AND(I25="",J25=""),"",IFERROR(I25*$D25,0)+IFERROR(J25,0)) | V25: =IF(AND(K25="",L25=""),"",IFERROR(K25*$D25,0)+IFERROR(L25,0)) | W25: =IF(AND(M25="",N25=""),"",IFERROR(M25*$D25,0)+IFERROR(N25,0)) | X25: =IF(AND(O25="",P25=""),"",IFERROR(O25*$D25,0)+IFERROR(P25,0)) | Y25: =IF(AND(Q25="",R25=""),"",IFERROR(Q25*$D25,0)+IFERROR(R25,0))
A26: =Insumos!$A72 | B26: =Insumos!$B72 | C26: =Insumos!$E72 | D26: =Insumos!$F72 | S26: =IF(AND(E26="",F26=""),"",IFERROR(E26*$D26,0)+IFERROR(F26,0)) | T26: =IF(AND(G26="",H26=""),"",IFERROR(G26*$D26,0)+IFERROR(H26,0)) | U26: =IF(AND(I26="",J26=""),"",IFERROR(I26*$D26,0)+IFERROR(J26,0)) | V26: =IF(AND(K26="",L26=""),"",IFERROR(K26*$D26,0)+IFERROR(L26,0)) | W26: =IF(AND(M26="",N26=""),"",IFERROR(M26*$D26,0)+IFERROR(N26,0)) | X26: =IF(AND(O26="",P26=""),"",IFERROR(O26*$D26,0)+IFERROR(P26,0)) | Y26: =IF(AND(Q26="",R26=""),"",IFERROR(Q26*$D26,0)+IFERROR(R26,0))
A27: =Insumos!$A73 | B27: =Insumos!$B73 | C27: =Insumos!$E73 | D27: =Insumos!$F73 | S27: =IF(AND(E27="",F27=""),"",IFERROR(E27*$D27,0)+IFERROR(F27,0)) | T27: =IF(AND(G27="",H27=""),"",IFERROR(G27*$D27,0)+IFERROR(H27,0)) | U27: =IF(AND(I27="",J27=""),"",IFERROR(I27*$D27,0)+IFERROR(J27,0)) | V27: =IF(AND(K27="",L27=""),"",IFERROR(K27*$D27,0)+IFERROR(L27,0)) | W27: =IF(AND(M27="",N27=""),"",IFERROR(M27*$D27,0)+IFERROR(N27,0)) | X27: =IF(AND(O27="",P27=""),"",IFERROR(O27*$D27,0)+IFERROR(P27,0)) | Y27: =IF(AND(Q27="",R27=""),"",IFERROR(Q27*$D27,0)+IFERROR(R27,0))
A28: =Insumos!$A74 | B28: =Insumos!$B74 | C28: =Insumos!$E74 | D28: =Insumos!$F74 | S28: =IF(AND(E28="",F28=""),"",IFERROR(E28*$D28,0)+IFERROR(F28,0)) | T28: =IF(AND(G28="",H28=""),"",IFERROR(G28*$D28,0)+IFERROR(H28,0)) | U28: =IF(AND(I28="",J28=""),"",IFERROR(I28*$D28,0)+IFERROR(J28,0)) | V28: =IF(AND(K28="",L28=""),"",IFERROR(K28*$D28,0)+IFERROR(L28,0)) | W28: =IF(AND(M28="",N28=""),"",IFERROR(M28*$D28,0)+IFERROR(N28,0)) | X28: =IF(AND(O28="",P28=""),"",IFERROR(O28*$D28,0)+IFERROR(P28,0)) | Y28: =IF(AND(Q28="",R28=""),"",IFERROR(Q28*$D28,0)+IFERROR(R28,0))
A29: =Insumos!$A78 | B29: =Insumos!$B78 | C29: =Insumos!$E78 | D29: =Insumos!$F78 | S29: =IF(AND(E29="",F29=""),"",IFERROR(E29*$D29,0)+IFERROR(F29,0)) | T29: =IF(AND(G29="",H29=""),"",IFERROR(G29*$D29,0)+IFERROR(H29,0)) | U29: =IF(AND(I29="",J29=""),"",IFERROR(I29*$D29,0)+IFERROR(J29,0)) | V29: =IF(AND(K29="",L29=""),"",IFERROR(K29*$D29,0)+IFERROR(L29,0)) | W29: =IF(AND(M29="",N29=""),"",IFERROR(M29*$D29,0)+IFERROR(N29,0)) | X29: =IF(AND(O29="",P29=""),"",IFERROR(O29*$D29,0)+IFERROR(P29,0)) | Y29: =IF(AND(Q29="",R29=""),"",IFERROR(Q29*$D29,0)+IFERROR(R29,0))
A30: =Insumos!$A79 | B30: =Insumos!$B79 | C30: =Insumos!$E79 | D30: =Insumos!$F79 | S30: =IF(AND(E30="",F30=""),"",IFERROR(E30*$D30,0)+IFERROR(F30,0)) | T30: =IF(AND(G30="",H30=""),"",IFERROR(G30*$D30,0)+IFERROR(H30,0)) | U30: =IF(AND(I30="",J30=""),"",IFERROR(I30*$D30,0)+IFERROR(J30,0)) | V30: =IF(AND(K30="",L30=""),"",IFERROR(K30*$D30,0)+IFERROR(L30,0)) | W30: =IF(AND(M30="",N30=""),"",IFERROR(M30*$D30,0)+IFERROR(N30,0)) | X30: =IF(AND(O30="",P30=""),"",IFERROR(O30*$D30,0)+IFERROR(P30,0)) | Y30: =IF(AND(Q30="",R30=""),"",IFERROR(Q30*$D30,0)+IFERROR(R30,0))
A31: =Insumos!$A80 | B31: =Insumos!$B80 | C31: =Insumos!$E80 | D31: =Insumos!$F80 | S31: =IF(AND(E31="",F31=""),"",IFERROR(E31*$D31,0)+IFERROR(F31,0)) | T31: =IF(AND(G31="",H31=""),"",IFERROR(G31*$D31,0)+IFERROR(H31,0)) | U31: =IF(AND(I31="",J31=""),"",IFERROR(I31*$D31,0)+IFERROR(J31,0)) | V31: =IF(AND(K31="",L31=""),"",IFERROR(K31*$D31,0)+IFERROR(L31,0)) | W31: =IF(AND(M31="",N31=""),"",IFERROR(M31*$D31,0)+IFERROR(N31,0)) | X31: =IF(AND(O31="",P31=""),"",IFERROR(O31*$D31,0)+IFERROR(P31,0)) | Y31: =IF(AND(Q31="",R31=""),"",IFERROR(Q31*$D31,0)+IFERROR(R31,0))
A32: =Insumos!$A81 | B32: =Insumos!$B81 | C32: =Insumos!$E81 | D32: =Insumos!$F81 | S32: =IF(AND(E32="",F32=""),"",IFERROR(E32*$D32,0)+IFERROR(F32,0)) | T32: =IF(AND(G32="",H32=""),"",IFERROR(G32*$D32,0)+IFERROR(H32,0)) | U32: =IF(AND(I32="",J32=""),"",IFERROR(I32*$D32,0)+IFERROR(J32,0)) | V32: =IF(AND(K32="",L32=""),"",IFERROR(K32*$D32,0)+IFERROR(L32,0)) | W32: =IF(AND(M32="",N32=""),"",IFERROR(M32*$D32,0)+IFERROR(N32,0)) | X32: =IF(AND(O32="",P32=""),"",IFERROR(O32*$D32,0)+IFERROR(P32,0)) | Y32: =IF(AND(Q32="",R32=""),"",IFERROR(Q32*$D32,0)+IFERROR(R32,0))
A33: =Insumos!$A92 | B33: =Insumos!$B92 | C33: =Insumos!$E92 | D33: =Insumos!$F92 | S33: =IF(AND(E33="",F33=""),"",IFERROR(E33*$D33,0)+IFERROR(F33,0)) | T33: =IF(AND(G33="",H33=""),"",IFERROR(G33*$D33,0)+IFERROR(H33,0)) | U33: =IF(AND(I33="",J33=""),"",IFERROR(I33*$D33,0)+IFERROR(J33,0)) | V33: =IF(AND(K33="",L33=""),"",IFERROR(K33*$D33,0)+IFERROR(L33,0)) | W33: =IF(AND(M33="",N33=""),"",IFERROR(M33*$D33,0)+IFERROR(N33,0)) | X33: =IF(AND(O33="",P33=""),"",IFERROR(O33*$D33,0)+IFERROR(P33,0)) | Y33: =IF(AND(Q33="",R33=""),"",IFERROR(Q33*$D33,0)+IFERROR(R33,0))
A34: =Insumos!$A93 | B34: =Insumos!$B93 | C34: =Insumos!$E93 | D34: =Insumos!$F93 | S34: =IF(AND(E34="",F34=""),"",IFERROR(E34*$D34,0)+IFERROR(F34,0)) | T34: =IF(AND(G34="",H34=""),"",IFERROR(G34*$D34,0)+IFERROR(H34,0)) | U34: =IF(AND(I34="",J34=""),"",IFERROR(I34*$D34,0)+IFERROR(J34,0)) | V34: =IF(AND(K34="",L34=""),"",IFERROR(K34*$D34,0)+IFERROR(L34,0)) | W34: =IF(AND(M34="",N34=""),"",IFERROR(M34*$D34,0)+IFERROR(N34,0)) | X34: =IF(AND(O34="",P34=""),"",IFERROR(O34*$D34,0)+IFERROR(P34,0)) | Y34: =IF(AND(Q34="",R34=""),"",IFERROR(Q34*$D34,0)+IFERROR(R34,0))
A35: =Insumos!$A96 | B35: =Insumos!$B96 | C35: =Insumos!$E96 | D35: =Insumos!$F96 | S35: =IF(AND(E35="",F35=""),"",IFERROR(E35*$D35,0)+IFERROR(F35,0)) | T35: =IF(AND(G35="",H35=""),"",IFERROR(G35*$D35,0)+IFERROR(H35,0)) | U35: =IF(AND(I35="",J35=""),"",IFERROR(I35*$D35,0)+IFERROR(J35,0)) | V35: =IF(AND(K35="",L35=""),"",IFERROR(K35*$D35,0)+IFERROR(L35,0)) | W35: =IF(AND(M35="",N35=""),"",IFERROR(M35*$D35,0)+IFERROR(N35,0)) | X35: =IF(AND(O35="",P35=""),"",IFERROR(O35*$D35,0)+IFERROR(P35,0)) | Y35: =IF(AND(Q35="",R35=""),"",IFERROR(Q35*$D35,0)+IFERROR(R35,0))
A36: =Insumos!$A97 | B36: =Insumos!$B97 | C36: =Insumos!$E97 | D36: =Insumos!$F97 | S36: =IF(AND(E36="",F36=""),"",IFERROR(E36*$D36,0)+IFERROR(F36,0)) | T36: =IF(AND(G36="",H36=""),"",IFERROR(G36*$D36,0)+IFERROR(H36,0)) | U36: =IF(AND(I36="",J36=""),"",IFERROR(I36*$D36,0)+IFERROR(J36,0)) | V36: =IF(AND(K36="",L36=""),"",IFERROR(K36*$D36,0)+IFERROR(L36,0)) | W36: =IF(AND(M36="",N36=""),"",IFERROR(M36*$D36,0)+IFERROR(N36,0)) | X36: =IF(AND(O36="",P36=""),"",IFERROR(O36*$D36,0)+IFERROR(P36,0)) | Y36: =IF(AND(Q36="",R36=""),"",IFERROR(Q36*$D36,0)+IFERROR(R36,0))
A37: =Insumos!$A98 | B37: =Insumos!$B98 | C37: =Insumos!$E98 | D37: =Insumos!$F98 | S37: =IF(AND(E37="",F37=""),"",IFERROR(E37*$D37,0)+IFERROR(F37,0)) | T37: =IF(AND(G37="",H37=""),"",IFERROR(G37*$D37,0)+IFERROR(H37,0)) | U37: =IF(AND(I37="",J37=""),"",IFERROR(I37*$D37,0)+IFERROR(J37,0)) | V37: =IF(AND(K37="",L37=""),"",IFERROR(K37*$D37,0)+IFERROR(L37,0)) | W37: =IF(AND(M37="",N37=""),"",IFERROR(M37*$D37,0)+IFERROR(N37,0)) | X37: =IF(AND(O37="",P37=""),"",IFERROR(O37*$D37,0)+IFERROR(P37,0)) | Y37: =IF(AND(Q37="",R37=""),"",IFERROR(Q37*$D37,0)+IFERROR(R37,0))
A38: =Insumos!$A99 | B38: =Insumos!$B99 | C38: =Insumos!$E99 | D38: =Insumos!$F99 | S38: =IF(AND(E38="",F38=""),"",IFERROR(E38*$D38,0)+IFERROR(F38,0)) | T38: =IF(AND(G38="",H38=""),"",IFERROR(G38*$D38,0)+IFERROR(H38,0)) | U38: =IF(AND(I38="",J38=""),"",IFERROR(I38*$D38,0)+IFERROR(J38,0)) | V38: =IF(AND(K38="",L38=""),"",IFERROR(K38*$D38,0)+IFERROR(L38,0)) | W38: =IF(AND(M38="",N38=""),"",IFERROR(M38*$D38,0)+IFERROR(N38,0)) | X38: =IF(AND(O38="",P38=""),"",IFERROR(O38*$D38,0)+IFERROR(P38,0)) | Y38: =IF(AND(Q38="",R38=""),"",IFERROR(Q38*$D38,0)+IFERROR(R38,0))
A39: =Insumos!$A100 | B39: =Insumos!$B100 | C39: =Insumos!$E100 | D39: =Insumos!$F100 | S39: =IF(AND(E39="",F39=""),"",IFERROR(E39*$D39,0)+IFERROR(F39,0)) | T39: =IF(AND(G39="",H39=""),"",IFERROR(G39*$D39,0)+IFERROR(H39,0)) | U39: =IF(AND(I39="",J39=""),"",IFERROR(I39*$D39,0)+IFERROR(J39,0)) | V39: =IF(AND(K39="",L39=""),"",IFERROR(K39*$D39,0)+IFERROR(L39,0)) | W39: =IF(AND(M39="",N39=""),"",IFERROR(M39*$D39,0)+IFERROR(N39,0)) | X39: =IF(AND(O39="",P39=""),"",IFERROR(O39*$D39,0)+IFERROR(P39,0)) | Y39: =IF(AND(Q39="",R39=""),"",IFERROR(Q39*$D39,0)+IFERROR(R39,0))
A40: =Insumos!$A102 | B40: =Insumos!$B102 | C40: =Insumos!$E102 | D40: =Insumos!$F102 | S40: =IF(AND(E40="",F40=""),"",IFERROR(E40*$D40,0)+IFERROR(F40,0)) | T40: =IF(AND(G40="",H40=""),"",IFERROR(G40*$D40,0)+IFERROR(H40,0)) | U40: =IF(AND(I40="",J40=""),"",IFERROR(I40*$D40,0)+IFERROR(J40,0)) | V40: =IF(AND(K40="",L40=""),"",IFERROR(K40*$D40,0)+IFERROR(L40,0)) | W40: =IF(AND(M40="",N40=""),"",IFERROR(M40*$D40,0)+IFERROR(N40,0)) | X40: =IF(AND(O40="",P40=""),"",IFERROR(O40*$D40,0)+IFERROR(P40,0)) | Y40: =IF(AND(Q40="",R40=""),"",IFERROR(Q40*$D40,0)+IFERROR(R40,0))
A41: =Insumos!$A104 | B41: =Insumos!$B104 | C41: =Insumos!$E104 | D41: =Insumos!$F104 | S41: =IF(AND(E41="",F41=""),"",IFERROR(E41*$D41,0)+IFERROR(F41,0)) | T41: =IF(AND(G41="",H41=""),"",IFERROR(G41*$D41,0)+IFERROR(H41,0)) | U41: =IF(AND(I41="",J41=""),"",IFERROR(I41*$D41,0)+IFERROR(J41,0)) | V41: =IF(AND(K41="",L41=""),"",IFERROR(K41*$D41,0)+IFERROR(L41,0)) | W41: =IF(AND(M41="",N41=""),"",IFERROR(M41*$D41,0)+IFERROR(N41,0)) | X41: =IF(AND(O41="",P41=""),"",IFERROR(O41*$D41,0)+IFERROR(P41,0)) | Y41: =IF(AND(Q41="",R41=""),"",IFERROR(Q41*$D41,0)+IFERROR(R41,0))
A42: =Insumos!$A105 | B42: =Insumos!$B105 | C42: =Insumos!$E105 | D42: =Insumos!$F105 | S42: =IF(AND(E42="",F42=""),"",IFERROR(E42*$D42,0)+IFERROR(F42,0)) | T42: =IF(AND(G42="",H42=""),"",IFERROR(G42*$D42,0)+IFERROR(H42,0)) | U42: =IF(AND(I42="",J42=""),"",IFERROR(I42*$D42,0)+IFERROR(J42,0)) | V42: =IF(AND(K42="",L42=""),"",IFERROR(K42*$D42,0)+IFERROR(L42,0)) | W42: =IF(AND(M42="",N42=""),"",IFERROR(M42*$D42,0)+IFERROR(N42,0)) | X42: =IF(AND(O42="",P42=""),"",IFERROR(O42*$D42,0)+IFERROR(P42,0)) | Y42: =IF(AND(Q42="",R42=""),"",IFERROR(Q42*$D42,0)+IFERROR(R42,0))
A43: =Insumos!$A106 | B43: =Insumos!$B106 | C43: =Insumos!$E106 | D43: =Insumos!$F106 | S43: =IF(AND(E43="",F43=""),"",IFERROR(E43*$D43,0)+IFERROR(F43,0)) | T43: =IF(AND(G43="",H43=""),"",IFERROR(G43*$D43,0)+IFERROR(H43,0)) | U43: =IF(AND(I43="",J43=""),"",IFERROR(I43*$D43,0)+IFERROR(J43,0)) | V43: =IF(AND(K43="",L43=""),"",IFERROR(K43*$D43,0)+IFERROR(L43,0)) | W43: =IF(AND(M43="",N43=""),"",IFERROR(M43*$D43,0)+IFERROR(N43,0)) | X43: =IF(AND(O43="",P43=""),"",IFERROR(O43*$D43,0)+IFERROR(P43,0)) | Y43: =IF(AND(Q43="",R43=""),"",IFERROR(Q43*$D43,0)+IFERROR(R43,0))
A44: =Insumos!$A107 | B44: =Insumos!$B107 | C44: =Insumos!$E107 | D44: =Insumos!$F107 | S44: =IF(AND(E44="",F44=""),"",IFERROR(E44*$D44,0)+IFERROR(F44,0)) | T44: =IF(AND(G44="",H44=""),"",IFERROR(G44*$D44,0)+IFERROR(H44,0)) | U44: =IF(AND(I44="",J44=""),"",IFERROR(I44*$D44,0)+IFERROR(J44,0)) | V44: =IF(AND(K44="",L44=""),"",IFERROR(K44*$D44,0)+IFERROR(L44,0)) | W44: =IF(AND(M44="",N44=""),"",IFERROR(M44*$D44,0)+IFERROR(N44,0)) | X44: =IF(AND(O44="",P44=""),"",IFERROR(O44*$D44,0)+IFERROR(P44,0)) | Y44: =IF(AND(Q44="",R44=""),"",IFERROR(Q44*$D44,0)+IFERROR(R44,0))
A45: =Insumos!$A114 | B45: =Insumos!$B114 | C45: =Insumos!$E114 | D45: =Insumos!$F114 | S45: =IF(AND(E45="",F45=""),"",IFERROR(E45*$D45,0)+IFERROR(F45,0)) | T45: =IF(AND(G45="",H45=""),"",IFERROR(G45*$D45,0)+IFERROR(H45,0)) | U45: =IF(AND(I45="",J45=""),"",IFERROR(I45*$D45,0)+IFERROR(J45,0)) | V45: =IF(AND(K45="",L45=""),"",IFERROR(K45*$D45,0)+IFERROR(L45,0)) | W45: =IF(AND(M45="",N45=""),"",IFERROR(M45*$D45,0)+IFERROR(N45,0)) | X45: =IF(AND(O45="",P45=""),"",IFERROR(O45*$D45,0)+IFERROR(P45,0)) | Y45: =IF(AND(Q45="",R45=""),"",IFERROR(Q45*$D45,0)+IFERROR(R45,0))
A46: =Insumos!$A117 | B46: =Insumos!$B117 | C46: =Insumos!$E117 | D46: =Insumos!$F117 | S46: =IF(AND(E46="",F46=""),"",IFERROR(E46*$D46,0)+IFERROR(F46,0)) | T46: =IF(AND(G46="",H46=""),"",IFERROR(G46*$D46,0)+IFERROR(H46,0)) | U46: =IF(AND(I46="",J46=""),"",IFERROR(I46*$D46,0)+IFERROR(J46,0)) | V46: =IF(AND(K46="",L46=""),"",IFERROR(K46*$D46,0)+IFERROR(L46,0)) | W46: =IF(AND(M46="",N46=""),"",IFERROR(M46*$D46,0)+IFERROR(N46,0)) | X46: =IF(AND(O46="",P46=""),"",IFERROR(O46*$D46,0)+IFERROR(P46,0)) | Y46: =IF(AND(Q46="",R46=""),"",IFERROR(Q46*$D46,0)+IFERROR(R46,0))
A47: =Insumos!$A118 | B47: =Insumos!$B118 | C47: =Insumos!$E118 | D47: =Insumos!$F118 | S47: =IF(AND(E47="",F47=""),"",IFERROR(E47*$D47,0)+IFERROR(F47,0)) | T47: =IF(AND(G47="",H47=""),"",IFERROR(G47*$D47,0)+IFERROR(H47,0)) | U47: =IF(AND(I47="",J47=""),"",IFERROR(I47*$D47,0)+IFERROR(J47,0)) | V47: =IF(AND(K47="",L47=""),"",IFERROR(K47*$D47,0)+IFERROR(L47,0)) | W47: =IF(AND(M47="",N47=""),"",IFERROR(M47*$D47,0)+IFERROR(N47,0)) | X47: =IF(AND(O47="",P47=""),"",IFERROR(O47*$D47,0)+IFERROR(P47,0)) | Y47: =IF(AND(Q47="",R47=""),"",IFERROR(Q47*$D47,0)+IFERROR(R47,0))
A48: =Insumos!$A119 | B48: =Insumos!$B119 | C48: =Insumos!$E119 | D48: =Insumos!$F119 | S48: =IF(AND(E48="",F48=""),"",IFERROR(E48*$D48,0)+IFERROR(F48,0)) | T48: =IF(AND(G48="",H48=""),"",IFERROR(G48*$D48,0)+IFERROR(H48,0)) | U48: =IF(AND(I48="",J48=""),"",IFERROR(I48*$D48,0)+IFERROR(J48,0)) | V48: =IF(AND(K48="",L48=""),"",IFERROR(K48*$D48,0)+IFERROR(L48,0)) | W48: =IF(AND(M48="",N48=""),"",IFERROR(M48*$D48,0)+IFERROR(N48,0)) | X48: =IF(AND(O48="",P48=""),"",IFERROR(O48*$D48,0)+IFERROR(P48,0)) | Y48: =IF(AND(Q48="",R48=""),"",IFERROR(Q48*$D48,0)+IFERROR(R48,0))
A49: =Insumos!$A122 | B49: =Insumos!$B122 | C49: =Insumos!$E122 | D49: =Insumos!$F122 | S49: =IF(AND(E49="",F49=""),"",IFERROR(E49*$D49,0)+IFERROR(F49,0)) | T49: =IF(AND(G49="",H49=""),"",IFERROR(G49*$D49,0)+IFERROR(H49,0)) | U49: =IF(AND(I49="",J49=""),"",IFERROR(I49*$D49,0)+IFERROR(J49,0)) | V49: =IF(AND(K49="",L49=""),"",IFERROR(K49*$D49,0)+IFERROR(L49,0)) | W49: =IF(AND(M49="",N49=""),"",IFERROR(M49*$D49,0)+IFERROR(N49,0)) | X49: =IF(AND(O49="",P49=""),"",IFERROR(O49*$D49,0)+IFERROR(P49,0)) | Y49: =IF(AND(Q49="",R49=""),"",IFERROR(Q49*$D49,0)+IFERROR(R49,0))
A50: =Insumos!$A123 | B50: =Insumos!$B123 | C50: =Insumos!$E123 | D50: =Insumos!$F123 | S50: =IF(AND(E50="",F50=""),"",IFERROR(E50*$D50,0)+IFERROR(F50,0)) | T50: =IF(AND(G50="",H50=""),"",IFERROR(G50*$D50,0)+IFERROR(H50,0)) | U50: =IF(AND(I50="",J50=""),"",IFERROR(I50*$D50,0)+IFERROR(J50,0)) | V50: =IF(AND(K50="",L50=""),"",IFERROR(K50*$D50,0)+IFERROR(L50,0)) | W50: =IF(AND(M50="",N50=""),"",IFERROR(M50*$D50,0)+IFERROR(N50,0)) | X50: =IF(AND(O50="",P50=""),"",IFERROR(O50*$D50,0)+IFERROR(P50,0)) | Y50: =IF(AND(Q50="",R50=""),"",IFERROR(Q50*$D50,0)+IFERROR(R50,0))
A51: =Insumos!$A124 | B51: =Insumos!$B124 | C51: =Insumos!$E124 | D51: =Insumos!$F124 | S51: =IF(AND(E51="",F51=""),"",IFERROR(E51*$D51,0)+IFERROR(F51,0)) | T51: =IF(AND(G51="",H51=""),"",IFERROR(G51*$D51,0)+IFERROR(H51,0)) | U51: =IF(AND(I51="",J51=""),"",IFERROR(I51*$D51,0)+IFERROR(J51,0)) | V51: =IF(AND(K51="",L51=""),"",IFERROR(K51*$D51,0)+IFERROR(L51,0)) | W51: =IF(AND(M51="",N51=""),"",IFERROR(M51*$D51,0)+IFERROR(N51,0)) | X51: =IF(AND(O51="",P51=""),"",IFERROR(O51*$D51,0)+IFERROR(P51,0)) | Y51: =IF(AND(Q51="",R51=""),"",IFERROR(Q51*$D51,0)+IFERROR(R51,0))
A52: =Insumos!$A125 | B52: =Insumos!$B125 | C52: =Insumos!$E125 | D52: =Insumos!$F125 | S52: =IF(AND(E52="",F52=""),"",IFERROR(E52*$D52,0)+IFERROR(F52,0)) | T52: =IF(AND(G52="",H52=""),"",IFERROR(G52*$D52,0)+IFERROR(H52,0)) | U52: =IF(AND(I52="",J52=""),"",IFERROR(I52*$D52,0)+IFERROR(J52,0)) | V52: =IF(AND(K52="",L52=""),"",IFERROR(K52*$D52,0)+IFERROR(L52,0)) | W52: =IF(AND(M52="",N52=""),"",IFERROR(M52*$D52,0)+IFERROR(N52,0)) | X52: =IF(AND(O52="",P52=""),"",IFERROR(O52*$D52,0)+IFERROR(P52,0)) | Y52: =IF(AND(Q52="",R52=""),"",IFERROR(Q52*$D52,0)+IFERROR(R52,0))
A53: =Insumos!$A126 | B53: =Insumos!$B126 | C53: =Insumos!$E126 | D53: =Insumos!$F126 | S53: =IF(AND(E53="",F53=""),"",IFERROR(E53*$D53,0)+IFERROR(F53,0)) | T53: =IF(AND(G53="",H53=""),"",IFERROR(G53*$D53,0)+IFERROR(H53,0)) | U53: =IF(AND(I53="",J53=""),"",IFERROR(I53*$D53,0)+IFERROR(J53,0)) | V53: =IF(AND(K53="",L53=""),"",IFERROR(K53*$D53,0)+IFERROR(L53,0)) | W53: =IF(AND(M53="",N53=""),"",IFERROR(M53*$D53,0)+IFERROR(N53,0)) | X53: =IF(AND(O53="",P53=""),"",IFERROR(O53*$D53,0)+IFERROR(P53,0)) | Y53: =IF(AND(Q53="",R53=""),"",IFERROR(Q53*$D53,0)+IFERROR(R53,0))
A54: =Insumos!$A127 | B54: =Insumos!$B127 | C54: =Insumos!$E127 | D54: =Insumos!$F127 | S54: =IF(AND(E54="",F54=""),"",IFERROR(E54*$D54,0)+IFERROR(F54,0)) | T54: =IF(AND(G54="",H54=""),"",IFERROR(G54*$D54,0)+IFERROR(H54,0)) | U54: =IF(AND(I54="",J54=""),"",IFERROR(I54*$D54,0)+IFERROR(J54,0)) | V54: =IF(AND(K54="",L54=""),"",IFERROR(K54*$D54,0)+IFERROR(L54,0)) | W54: =IF(AND(M54="",N54=""),"",IFERROR(M54*$D54,0)+IFERROR(N54,0)) | X54: =IF(AND(O54="",P54=""),"",IFERROR(O54*$D54,0)+IFERROR(P54,0)) | Y54: =IF(AND(Q54="",R54=""),"",IFERROR(Q54*$D54,0)+IFERROR(R54,0))
A55: =Insumos!$A137 | B55: =Insumos!$B137 | C55: =Insumos!$E137 | D55: =Insumos!$F137 | S55: =IF(AND(E55="",F55=""),"",IFERROR(E55*$D55,0)+IFERROR(F55,0)) | T55: =IF(AND(G55="",H55=""),"",IFERROR(G55*$D55,0)+IFERROR(H55,0)) | U55: =IF(AND(I55="",J55=""),"",IFERROR(I55*$D55,0)+IFERROR(J55,0)) | V55: =IF(AND(K55="",L55=""),"",IFERROR(K55*$D55,0)+IFERROR(L55,0)) | W55: =IF(AND(M55="",N55=""),"",IFERROR(M55*$D55,0)+IFERROR(N55,0)) | X55: =IF(AND(O55="",P55=""),"",IFERROR(O55*$D55,0)+IFERROR(P55,0)) | Y55: =IF(AND(Q55="",R55=""),"",IFERROR(Q55*$D55,0)+IFERROR(R55,0))
A56: =Insumos!$A138 | B56: =Insumos!$B138 | C56: =Insumos!$E138 | D56: =Insumos!$F138 | S56: =IF(AND(E56="",F56=""),"",IFERROR(E56*$D56,0)+IFERROR(F56,0)) | T56: =IF(AND(G56="",H56=""),"",IFERROR(G56*$D56,0)+IFERROR(H56,0)) | U56: =IF(AND(I56="",J56=""),"",IFERROR(I56*$D56,0)+IFERROR(J56,0)) | V56: =IF(AND(K56="",L56=""),"",IFERROR(K56*$D56,0)+IFERROR(L56,0)) | W56: =IF(AND(M56="",N56=""),"",IFERROR(M56*$D56,0)+IFERROR(N56,0)) | X56: =IF(AND(O56="",P56=""),"",IFERROR(O56*$D56,0)+IFERROR(P56,0)) | Y56: =IF(AND(Q56="",R56=""),"",IFERROR(Q56*$D56,0)+IFERROR(R56,0))
A57: =Insumos!$A139 | B57: =Insumos!$B139 | C57: =Insumos!$E139 | D57: =Insumos!$F139 | S57: =IF(AND(E57="",F57=""),"",IFERROR(E57*$D57,0)+IFERROR(F57,0)) | T57: =IF(AND(G57="",H57=""),"",IFERROR(G57*$D57,0)+IFERROR(H57,0)) | U57: =IF(AND(I57="",J57=""),"",IFERROR(I57*$D57,0)+IFERROR(J57,0)) | V57: =IF(AND(K57="",L57=""),"",IFERROR(K57*$D57,0)+IFERROR(L57,0)) | W57: =IF(AND(M57="",N57=""),"",IFERROR(M57*$D57,0)+IFERROR(N57,0)) | X57: =IF(AND(O57="",P57=""),"",IFERROR(O57*$D57,0)+IFERROR(P57,0)) | Y57: =IF(AND(Q57="",R57=""),"",IFERROR(Q57*$D57,0)+IFERROR(R57,0))
A58: =Insumos!$A140 | B58: =Insumos!$B140 | C58: =Insumos!$E140 | D58: =Insumos!$F140 | S58: =IF(AND(E58="",F58=""),"",IFERROR(E58*$D58,0)+IFERROR(F58,0)) | T58: =IF(AND(G58="",H58=""),"",IFERROR(G58*$D58,0)+IFERROR(H58,0)) | U58: =IF(AND(I58="",J58=""),"",IFERROR(I58*$D58,0)+IFERROR(J58,0)) | V58: =IF(AND(K58="",L58=""),"",IFERROR(K58*$D58,0)+IFERROR(L58,0)) | W58: =IF(AND(M58="",N58=""),"",IFERROR(M58*$D58,0)+IFERROR(N58,0)) | X58: =IF(AND(O58="",P58=""),"",IFERROR(O58*$D58,0)+IFERROR(P58,0)) | Y58: =IF(AND(Q58="",R58=""),"",IFERROR(Q58*$D58,0)+IFERROR(R58,0))
A59: =Insumos!$A142 | B59: =Insumos!$B142 | C59: =Insumos!$E142 | D59: =Insumos!$F142 | S59: =IF(AND(E59="",F59=""),"",IFERROR(E59*$D59,0)+IFERROR(F59,0)) | T59: =IF(AND(G59="",H59=""),"",IFERROR(G59*$D59,0)+IFERROR(H59,0)) | U59: =IF(AND(I59="",J59=""),"",IFERROR(I59*$D59,0)+IFERROR(J59,0)) | V59: =IF(AND(K59="",L59=""),"",IFERROR(K59*$D59,0)+IFERROR(L59,0)) | W59: =IF(AND(M59="",N59=""),"",IFERROR(M59*$D59,0)+IFERROR(N59,0)) | X59: =IF(AND(O59="",P59=""),"",IFERROR(O59*$D59,0)+IFERROR(P59,0)) | Y59: =IF(AND(Q59="",R59=""),"",IFERROR(Q59*$D59,0)+IFERROR(R59,0))
A60: =Insumos!$A143 | B60: =Insumos!$B143 | C60: =Insumos!$E143 | D60: =Insumos!$F143 | S60: =IF(AND(E60="",F60=""),"",IFERROR(E60*$D60,0)+IFERROR(F60,0)) | T60: =IF(AND(G60="",H60=""),"",IFERROR(G60*$D60,0)+IFERROR(H60,0)) | U60: =IF(AND(I60="",J60=""),"",IFERROR(I60*$D60,0)+IFERROR(J60,0)) | V60: =IF(AND(K60="",L60=""),"",IFERROR(K60*$D60,0)+IFERROR(L60,0)) | W60: =IF(AND(M60="",N60=""),"",IFERROR(M60*$D60,0)+IFERROR(N60,0)) | X60: =IF(AND(O60="",P60=""),"",IFERROR(O60*$D60,0)+IFERROR(P60,0)) | Y60: =IF(AND(Q60="",R60=""),"",IFERROR(Q60*$D60,0)+IFERROR(R60,0))
A61: =Insumos!$A144 | B61: =Insumos!$B144 | C61: =Insumos!$E144 | D61: =Insumos!$F144 | S61: =IF(AND(E61="",F61=""),"",IFERROR(E61*$D61,0)+IFERROR(F61,0)) | T61: =IF(AND(G61="",H61=""),"",IFERROR(G61*$D61,0)+IFERROR(H61,0)) | U61: =IF(AND(I61="",J61=""),"",IFERROR(I61*$D61,0)+IFERROR(J61,0)) | V61: =IF(AND(K61="",L61=""),"",IFERROR(K61*$D61,0)+IFERROR(L61,0)) | W61: =IF(AND(M61="",N61=""),"",IFERROR(M61*$D61,0)+IFERROR(N61,0)) | X61: =IF(AND(O61="",P61=""),"",IFERROR(O61*$D61,0)+IFERROR(P61,0)) | Y61: =IF(AND(Q61="",R61=""),"",IFERROR(Q61*$D61,0)+IFERROR(R61,0))
A62: =Insumos!$A145 | B62: =Insumos!$B145 | C62: =Insumos!$E145 | D62: =Insumos!$F145 | S62: =IF(AND(E62="",F62=""),"",IFERROR(E62*$D62,0)+IFERROR(F62,0)) | T62: =IF(AND(G62="",H62=""),"",IFERROR(G62*$D62,0)+IFERROR(H62,0)) | U62: =IF(AND(I62="",J62=""),"",IFERROR(I62*$D62,0)+IFERROR(J62,0)) | V62: =IF(AND(K62="",L62=""),"",IFERROR(K62*$D62,0)+IFERROR(L62,0)) | W62: =IF(AND(M62="",N62=""),"",IFERROR(M62*$D62,0)+IFERROR(N62,0)) | X62: =IF(AND(O62="",P62=""),"",IFERROR(O62*$D62,0)+IFERROR(P62,0)) | Y62: =IF(AND(Q62="",R62=""),"",IFERROR(Q62*$D62,0)+IFERROR(R62,0))
A63: =Insumos!$A147 | B63: =Insumos!$B147 | C63: =Insumos!$E147 | D63: =Insumos!$F147 | S63: =IF(AND(E63="",F63=""),"",IFERROR(E63*$D63,0)+IFERROR(F63,0)) | T63: =IF(AND(G63="",H63=""),"",IFERROR(G63*$D63,0)+IFERROR(H63,0)) | U63: =IF(AND(I63="",J63=""),"",IFERROR(I63*$D63,0)+IFERROR(J63,0)) | V63: =IF(AND(K63="",L63=""),"",IFERROR(K63*$D63,0)+IFERROR(L63,0)) | W63: =IF(AND(M63="",N63=""),"",IFERROR(M63*$D63,0)+IFERROR(N63,0)) | X63: =IF(AND(O63="",P63=""),"",IFERROR(O63*$D63,0)+IFERROR(P63,0)) | Y63: =IF(AND(Q63="",R63=""),"",IFERROR(Q63*$D63,0)+IFERROR(R63,0))
A64: =Insumos!$A148 | B64: =Insumos!$B148 | C64: =Insumos!$E148 | D64: =Insumos!$F148 | S64: =IF(AND(E64="",F64=""),"",IFERROR(E64*$D64,0)+IFERROR(F64,0)) | T64: =IF(AND(G64="",H64=""),"",IFERROR(G64*$D64,0)+IFERROR(H64,0)) | U64: =IF(AND(I64="",J64=""),"",IFERROR(I64*$D64,0)+IFERROR(J64,0)) | V64: =IF(AND(K64="",L64=""),"",IFERROR(K64*$D64,0)+IFERROR(L64,0)) | W64: =IF(AND(M64="",N64=""),"",IFERROR(M64*$D64,0)+IFERROR(N64,0)) | X64: =IF(AND(O64="",P64=""),"",IFERROR(O64*$D64,0)+IFERROR(P64,0)) | Y64: =IF(AND(Q64="",R64=""),"",IFERROR(Q64*$D64,0)+IFERROR(R64,0))
A65: =Insumos!$A159 | B65: =Insumos!$B159 | C65: =Insumos!$E159 | D65: =Insumos!$F159 | S65: =IF(AND(E65="",F65=""),"",IFERROR(E65*$D65,0)+IFERROR(F65,0)) | T65: =IF(AND(G65="",H65=""),"",IFERROR(G65*$D65,0)+IFERROR(H65,0)) | U65: =IF(AND(I65="",J65=""),"",IFERROR(I65*$D65,0)+IFERROR(J65,0)) | V65: =IF(AND(K65="",L65=""),"",IFERROR(K65*$D65,0)+IFERROR(L65,0)) | W65: =IF(AND(M65="",N65=""),"",IFERROR(M65*$D65,0)+IFERROR(N65,0)) | X65: =IF(AND(O65="",P65=""),"",IFERROR(O65*$D65,0)+IFERROR(P65,0)) | Y65: =IF(AND(Q65="",R65=""),"",IFERROR(Q65*$D65,0)+IFERROR(R65,0))
A66: =Insumos!$A160 | B66: =Insumos!$B160 | C66: =Insumos!$E160 | D66: =Insumos!$F160 | S66: =IF(AND(E66="",F66=""),"",IFERROR(E66*$D66,0)+IFERROR(F66,0)) | T66: =IF(AND(G66="",H66=""),"",IFERROR(G66*$D66,0)+IFERROR(H66,0)) | U66: =IF(AND(I66="",J66=""),"",IFERROR(I66*$D66,0)+IFERROR(J66,0)) | V66: =IF(AND(K66="",L66=""),"",IFERROR(K66*$D66,0)+IFERROR(L66,0)) | W66: =IF(AND(M66="",N66=""),"",IFERROR(M66*$D66,0)+IFERROR(N66,0)) | X66: =IF(AND(O66="",P66=""),"",IFERROR(O66*$D66,0)+IFERROR(P66,0)) | Y66: =IF(AND(Q66="",R66=""),"",IFERROR(Q66*$D66,0)+IFERROR(R66,0))
A67: =Insumos!$A161 | B67: =Insumos!$B161 | C67: =Insumos!$E161 | D67: =Insumos!$F161 | S67: =IF(AND(E67="",F67=""),"",IFERROR(E67*$D67,0)+IFERROR(F67,0)) | T67: =IF(AND(G67="",H67=""),"",IFERROR(G67*$D67,0)+IFERROR(H67,0)) | U67: =IF(AND(I67="",J67=""),"",IFERROR(I67*$D67,0)+IFERROR(J67,0)) | V67: =IF(AND(K67="",L67=""),"",IFERROR(K67*$D67,0)+IFERROR(L67,0)) | W67: =IF(AND(M67="",N67=""),"",IFERROR(M67*$D67,0)+IFERROR(N67,0)) | X67: =IF(AND(O67="",P67=""),"",IFERROR(O67*$D67,0)+IFERROR(P67,0)) | Y67: =IF(AND(Q67="",R67=""),"",IFERROR(Q67*$D67,0)+IFERROR(R67,0))

Sheet 4 Prod Panaderia
A1: PLANILLA 4 · PRODUCCION DIARIA — PANADERÍA
A2: Jefe de area: ____________________ Semana: ____/____ al ____/____ Se elabora en: Central
A3: ELABORADO = lo que salio bueno. DESCARTE = lo que se quemo, salio mal, se cayo o se tiro. El detalle del motivo de cada descarte va en la planilla 5.
A4: PRODUCTO | B4: UNID. | C4: =IF(Config!$B$10="","LUNES",UPPER("LUN")&" "&TEXT(Config!$B$10,"dd/mm")) | E4: =IF(Config!$B$11="","MARTES",UPPER("MAR")&" "&TEXT(Config!$B$11,"dd/mm")) | G4: =IF(Config!$B$12="","MIERCOLES",UPPER("MIE")&" "&TEXT(Config!$B$12,"dd/mm")) | I4: =IF(Config!$B$13="","JUEVES",UPPER("JUE")&" "&TEXT(Config!$B$13,"dd/mm")) | K4: =IF(Config!$B$14="","VIERNES",UPPER("VIE")&" "&TEXT(Config!$B$14,"dd/mm")) | M4: =IF(Config!$B$15="","SABADO",UPPER("SAB")&" "&TEXT(Config!$B$15,"dd/mm")) | O4: =IF(Config!$B$16="","DOMINGO",UPPER("DOM")&" "&TEXT(Config!$B$16,"dd/mm")) | Q4: TOTAL ELABORADO | R4: TOTAL DESCARTE | S4: % DESC.
C5: ELABOR. | D5: DESCAR. | E5: ELABOR. | F5: DESCAR. | G5: ELABOR. | H5: DESCAR. | I5: ELABOR. | J5: DESCAR. | K5: ELABOR. | L5: DESCAR. | M5: ELABOR. | N5: DESCAR. | O5: ELABOR. | P5: DESCAR.
A6: Bagel | B6: u | Q6: =SUM(C6,E6,G6,I6,K6,M6,O6) | R6: =SUM(D6,F6,H6,J6,L6,N6,P6) | S6: =IF($Q6=0,"",$R6/$Q6)
A7: Bizcochos | B7: kg | Q7: =SUM(C7,E7,G7,I7,K7,M7,O7) | R7: =SUM(D7,F7,H7,J7,L7,N7,P7) | S7: =IF($Q7=0,"",$R7/$Q7)
A8: Bizcochos de margarina | B8: kg | Q8: =SUM(C8,E8,G8,I8,K8,M8,O8) | R8: =SUM(D8,F8,H8,J8,L8,N8,P8) | S8: =IF($Q8=0,"",$R8/$Q8)
A9: Bizcochos redondos | B9: kg | Q9: =SUM(C9,E9,G9,I9,K9,M9,O9) | R9: =SUM(D9,F9,H9,J9,L9,N9,P9) | S9: =IF($Q9=0,"",$R9/$Q9)
A10: Bollitos B/N | B10: u | Q10: =SUM(C10,E10,G10,I10,K10,M10,O10) | R10: =SUM(D10,F10,H10,J10,L10,N10,P10) | S10: =IF($Q10=0,"",$R10/$Q10)
A11: Bollos grandes | B11: u | Q11: =SUM(C11,E11,G11,I11,K11,M11,O11) | R11: =SUM(D11,F11,H11,J11,L11,N11,P11) | S11: =IF($Q11=0,"",$R11/$Q11)
A12: Caseras | B12: u | Q12: =SUM(C12,E12,G12,I12,K12,M12,O12) | R12: =SUM(D12,F12,H12,J12,L12,N12,P12) | S12: =IF($Q12=0,"",$R12/$Q12)
A13: Caseritas | B13: u | Q13: =SUM(C13,E13,G13,I13,K13,M13,O13) | R13: =SUM(D13,F13,H13,J13,L13,N13,P13) | S13: =IF($Q13=0,"",$R13/$Q13)
A14: Chatas | B14: kg | Q14: =SUM(C14,E14,G14,I14,K14,M14,O14) | R14: =SUM(D14,F14,H14,J14,L14,N14,P14) | S14: =IF($Q14=0,"",$R14/$Q14)
A15: Cremona | B15: u | Q15: =SUM(C15,E15,G15,I15,K15,M15,O15) | R15: =SUM(D15,F15,H15,J15,L15,N15,P15) | S15: =IF($Q15=0,"",$R15/$Q15)
A16: Focaccia | B16: u | Q16: =SUM(C16,E16,G16,I16,K16,M16,O16) | R16: =SUM(D16,F16,H16,J16,L16,N16,P16) | S16: =IF($Q16=0,"",$R16/$Q16)
A17: Libritos | B17: u | Q17: =SUM(C17,E17,G17,I17,K17,M17,O17) | R17: =SUM(D17,F17,H17,J17,L17,N17,P17) | S17: =IF($Q17=0,"",$R17/$Q17)
... A47: TT Tortillas | B47: u | Q47: =SUM(C47,E47,G47,I47,K47,M47,O47) | R47: =SUM(D47,F47,H47,J47,L47,N47,P47) | S47: =IF($Q47=0,"",$R47/$Q47)
Q48: =SUM(C48,E48,G48,I48,K48,M48,O48) | R48: =SUM(D48,F48,H48,J48,L48,N48,P48) | S48: =IF($Q48=0,"",$R48/$Q48)
Q49: =SUM(C49,E49,G49,I49,K49,M49,O49) | R49: =SUM(D49,F49,H49,J49,L49,N49,P49) | S49: =IF($Q49=0,"",$R49/$Q49)
Q50: =SUM(C50,E50,G50,I50,K50,M50,O50) | R50: =SUM(D50,F50,H50,J50,L50,N50,P50) | S50: =IF($Q50=0,"",$R50/$Q50)
Q51: =SUM(C51,E51,G51,I51,K51,M51,O51) | R51: =SUM(D51,F51,H51,J51,L51,N51,P51) | S51: =IF($Q51=0,"",$R51/$Q51)
Q52: =SUM(C52,E52,G52,I52,K52,M52,O52) | R52: =SUM(D52,F52,H52,J52,L52,N52,P52) | S52: =IF($Q52=0,"",$R52/$Q52)
Q53: =SUM(C53,E53,G53,I53,K53,M53,O53) | R53: =SUM(D53,F53,H53,J53,L53,N53,P53) | S53: =IF($Q53=0,"",$R53/$Q53)
Q54: =SUM(C54,E54,G54,I54,K54,M54,O54) | R54: =SUM(D54,F54,H54,J54,L54,N54,P54) | S54: =IF($Q54=0,"",$R54/$Q54)
Q55: =SUM(C55,E55,G55,I55,K55,M55,O55) | R55: =SUM(D55,F55,H55,J55,L55,N55,P55) | S55: =IF($Q55=0,"",$R55/$Q55)
A56: TOTALES DEL AREA | C56: =SUM(C6:C55) | D56: =SUM(D6:D55) | E56: =SUM(E6:E55) | F56: =SUM(F6:F55) | G56: =SUM(G6:G55) | H56: =SUM(H6:H55) | I56: =SUM(I6:I55) | J56: =SUM(J6:J55) | ... R56: =SUM(R6:R55) | S56: =IF($Q56=0,"",$R56/$Q56)

Sheet 4 Prod Pasteleria
A1: PLANILLA 4 · PRODUCCION DIARIA — PASTELERÍA
A2: Jefe de area: ____________________ Semana: ____/____ al ____/____ Se elabora en: Central
A3: ELABORADO = lo que salio bueno. DESCARTE = lo que se quemo, salio mal, se cayo o se tiro. El detalle del motivo de cada descarte va en la planilla 5.
A4: PRODUCTO | B4: UNID. | C4: =IF(Config!$B$10="","LUNES",UPPER("LUN")&" "&TEXT(Config!$B$10,"dd/mm")) | E4: =IF(Config!$B$11="","MARTES",UPPER("MAR")&" "&TEXT(Config!$B$11,"dd/mm")) | G4: =IF(Config!$B$12="","MIERCOLES",UPPER("MIE")&" "&TEXT(Config!$B$12,"dd/mm")) | I4: =IF(Config!$B$13="","JUEVES",UPPER("JUE")&" "&TEXT(Config!$B$13,"dd/mm")) | K4: =IF(Config!$B$14="","VIERNES",UPPER("VIE")&" "&TEXT(Config!$B$14,"dd/mm")) | M4: =IF(Config!$B$15="","SABADO",UPPER("SAB")&" "&TEXT(Config!$B$15,"dd/mm")) | O4: =IF(Config!$B$16="","DOMINGO",UPPER("DOM")&" "&TEXT(Config!$B$16,"dd/mm")) | Q4: TOTAL ELABORADO | R4: TOTAL DESCARTE | S4: % DESC.
C5: ELABOR. | D5: DESCAR. | E5: ELABOR. | F5: DESCAR. | G5: ELABOR. | H5: DESCAR. | I5: ELABOR. | J5: DESCAR. | K5: ELABOR. | L5: DESCAR. | M5: ELABOR. | N5: DESCAR. | O5: ELABOR. | P5: DESCAR.
A6: Alemana | B6: u | Q6: =SUM(C6,E6,G6,I6,K6,M6,O6) | R6: =SUM(D6,F6,H6,J6,L6,N6,P6) | S6: =IF($Q6=0,"",$R6/$Q6)
A7: Bariloche | B7: u | Q7: =SUM(C7,E7,G7,I7,K7,M7,O7) | R7: =SUM(D7,F7,H7,J7,L7,N7,P7) | S7: =IF($Q7=0,"",$R7/$Q7)
A8: Cabsha | B8: u | Q8: =SUM(C8,E8,G8,I8,K8,M8,O8) | R8: =SUM(D8,F8,H8,J8,L8,N8,P8) | S8: =IF($Q8=0,"",$R8/$Q8)
A9: Cheesecake frutos rojos | B9: u | Q9: =SUM(C9,E9,G9,I9,K9,M9,O9) | R9: =SUM(D9,F9,H9,J9,L9,N9,P9) | S9: =IF($Q9=0,"",$R9/$Q9)
A10: Cheesecake maracuyá | B10: u | Q10: =SUM(C10,E10,G10,I10,K10,M10,O10) | R10: =SUM(D10,F10,H10,J10,L10,N10,P10) | S10: =IF($Q10=0,"",$R10/$Q10)
A11: Cheesecake NY cocido | B11: u | Q11: =SUM(C11,E11,G11,I11,K11,M11,O11) | R11: =SUM(D11,F11,H11,J11,L11,N11,P11) | S11: =IF($Q11=0,"",$R11/$Q11)
A12: Chocotorta | B12: u | Q12: =SUM(C12,E12,G12,I12,K12,M12,O12) | R12: =SUM(D12,F12,H12,J12,L12,N12,P12) | S12: =IF($Q12=0,"",$R12/$Q12)
A13: Delicia con chocolates | B13: u | Q13: =SUM(C13,E13,G13,I13,K13,M13,O13) | R13: =SUM(D13,F13,H13,J13,L13,N13,P13) | S13: =IF($Q13=0,"",$R13/$Q13)
A14: Delicia con frutas | B14: u | Q14: =SUM(C14,E14,G14,I14,K14,M14,O14) | R14: =SUM(D14,F14,H14,J14,L14,N14,P14) | S14: =IF($Q14=0,"",$R14/$Q14)
A15: Lemon Pie | B15: u | Q15: =SUM(C15,E15,G15,I15,K15,M15,O15) | R15: =SUM(D15,F15,H15,J15,L15,N15,P15) | S15: =IF($Q15=0,"",$R15/$Q15)
A16: Marquise | B16: u | Q16: =SUM(C16,E16,G16,I16,K16,M16,O16) | R16: =SUM(D16,F16,H16,J16,L16,N16,P16) | S16: =IF($Q16=0,"",$R16/$Q16)
A17: Mini Cabsha | B17: u | Q17: =SUM(C17,E17,G17,I17,K17,M17,O17) | R17: =SUM(D17,F17,H17,J17,L17,N17,P17) | S17: =IF($Q17=0,"",$R17/$Q17)
... A43: Turrón Salteño | B43: u | Q43: =SUM(C43,E43,G43,I43,K43,M43,O43) | R43: =SUM(D43,F43,H43,J43,L43,N43,P43) | S43: =IF($Q43=0,"",$R43/$Q43)
Q44: =SUM(C44,E44,G44,I44,K44,M44,O44) | R44: =SUM(D44,F44,H44,J44,L44,N44,P44) | S44: =IF($Q44=0,"",$R44/$Q44)
Q45: =SUM(C45,E45,G45,I45,K45,M45,O45) | R45: =SUM(D45,F45,H45,J45,L45,N45,P45) | S45: =IF($Q45=0,"",$R45/$Q45)
Q46: =SUM(C46,E46,G46,I46,K46,M46,O46) | R46: =SUM(D46,F46,H46,J46,L46,N46,P46) | S46: =IF($Q46=0,"",$R46/$Q46)
Q47: =SUM(C47,E47,G47,I47,K47,M47,O47) | R47: =SUM(D47,F47,H47,J47,L47,N47,P47) | S47: =IF($Q47=0,"",$R47/$Q47)
Q48: =SUM(C48,E48,G48,I48,K48,M48,O48) | R48: =SUM(D48,F48,H48,J48,L48,N48,P48) | S48: =IF($Q48=0,"",$R48/$Q48)
Q49: =SUM(C49,E49,G49,I49,K49,M49,O49) | R49: =SUM(D49,F49,H49,J49,L49,N49,P49) | S49: =IF($Q49=0,"",$R49/$Q49)
Q50: =SUM(C50,E50,G50,I50,K50,M50,O50) | R50: =SUM(D50,F50,H50,J50,L50,N50,P50) | S50: =IF($Q50=0,"",$R50/$Q50)
Q51: =SUM(C51,E51,G51,I51,K51,M51,O51) | R51: =SUM(D51,F51,H51,J51,L51,N51,P51) | S51: =IF($Q51=0,"",$R51/$Q51)
A52: TOTALES DEL AREA | C52: =SUM(C6:C51) | D52: =SUM(D6:D51) | E52: =SUM(E6:E51) | F52: =SUM(F6:F51) | G52: =SUM(G6:G51) | H52: =SUM(H6:H51) | I52: =SUM(I6:I51) | J52: =SUM(J6:J51) | ... R52: =SUM(R6:R51) | S52: =IF($Q52=0,"",$R52/$Q52)

Sheet 4 Prod Especialidades
A1: PLANILLA 4 · PRODUCCION DIARIA — ESPECIALIDADES
A2: Jefe de area: ____________________ Semana: ____/____ al ____/____ Se elabora en: Central
A3: ELABORADO = lo que salio bueno. DESCARTE = lo que se quemo, salio mal, se cayo o se tiro. El detalle del motivo de cada descarte va en la planilla 5.
A4: PRODUCTO | B4: UNID. | C4: =IF(Config!$B$10="","LUNES",UPPER("LUN")&" "&TEXT(Config!$B$10,"dd/mm")) | E4: =IF(Config!$B$11="","MARTES",UPPER("MAR")&" "&TEXT(Config!$B$11,"dd/mm")) | G4: =IF(Config!$B$12="","MIERCOLES",UPPER("MIE")&" "&TEXT(Config!$B$12,"dd/mm")) | I4: =IF(Config!$B$13="","JUEVES",UPPER("JUE")&" "&TEXT(Config!$B$13,"dd/mm")) | K4: =IF(Config!$B$14="","VIERNES",UPPER("VIE")&" "&TEXT(Config!$B$14,"dd/mm")) | M4: =IF(Config!$B$15="","SABADO",UPPER("SAB")&" "&TEXT(Config!$B$15,"dd/mm")) | O4: =IF(Config!$B$16="","DOMINGO",UPPER("DOM")&" "&TEXT(Config!$B$16,"dd/mm")) | Q4: TOTAL ELABORADO | R4: TOTAL DESCARTE | S4: % DESC.
C5: ELABOR. | D5: DESCAR. | E5: ELABOR. | F5: DESCAR. | G5: ELABOR. | H5: DESCAR. | I5: ELABOR. | J5: DESCAR. | K5: ELABOR. | L5: DESCAR. | M5: ELABOR. | N5: DESCAR. | O5: ELABOR. | P5: DESCAR.
A6: Alfajores choco blanco | B6: u | Q6: =SUM(C6,E6,G6,I6,K6,M6,O6) | R6: =SUM(D6,F6,H6,J6,L6,N6,P6) | S6: =IF($Q6=0,"",$R6/$Q6)
A7: Alfajores choco negro | B7: u | Q7: =SUM(C7,E7,G7,I7,K7,M7,O7) | R7: =SUM(D7,F7,H7,J7,L7,N7,P7) | S7: =IF($Q7=0,"",$R7/$Q7)
A8: Alfajores choco negro grande | B8: u | Q8: =SUM(C8,E8,G8,I8,K8,M8,O8) | R8: =SUM(D8,F8,H8,J8,L8,N8,P8) | S8: =IF($Q8=0,"",$R8/$Q8)
A9: Alfajores impalpable | B9: u | Q9: =SUM(C9,E9,G9,I9,K9,M9,O9) | R9: =SUM(D9,F9,H9,J9,L9,N9,P9) | S9: =IF($Q9=0,"",$R9/$Q9)
A10: Boulévant | B10: u | Q10: =SUM(C10,E10,G10,I10,K10,M10,O10) | R10: =SUM(D10,F10,H10,J10,L10,N10,P10) | S10: =IF($Q10=0,"",$R10/$Q10)
A11: Budín x kg naranja y amapola | B11: kg | Q11: =SUM(C11,E11,G11,I11,K11,M11,O11) | R11: =SUM(D11,F11,H11,J11,L11,N11,P11) | S11: =IF($Q11=0,"",$R11/$Q11)
A12: Budín x kg nuez y dulce | B12: kg | Q12: =SUM(C12,E12,G12,I12,K12,M12,O12) | R12: =SUM(D12,F12,H12,J12,L12,N12,P12) | S12: =IF($Q12=0,"",$R12/$Q12)
A13: Budín x unidad chico | B13: u | Q13: =SUM(C13,E13,G13,I13,K13,M13,O13) | R13: =SUM(D13,F13,H13,J13,L13,N13,P13) | S13: =IF($Q13=0,"",$R13/$Q13)
A14: Cañoncitos | B14: u | Q14: =SUM(C14,E14,G14,I14,K14,M14,O14) | R14: =SUM(D14,F14,H14,J14,L14,N14,P14) | S14: =IF($Q14=0,"",$R14/$Q14)
A15: Carasucias | B15: u | Q15: =SUM(C15,E15,G15,I15,K15,M15,O15) | R15: =SUM(D15,F15,H15,J15,L15,N15,P15) | S15: =IF($Q15=0,"",$R15/$Q15)
A16: Chipa | B16: u | Q16: =SUM(C16,E16,G16,I16,K16,M16,O16) | R16: =SUM(D16,F16,H16,J16,L16,N16,P16) | S16: =IF($Q16=0,"",$R16/$Q16)
A17: Chipa crudo bandeja x30 | B17: u | Q17: =SUM(C17,E17,G17,I17,K17,M17,O17) | R17: =SUM(D17,F17,H17,J17,L17,N17,P17) | S17: =IF($Q17=0,"",$R17/$Q17)
... A41: Torta x porción | B41: u | Q41: =SUM(C41,E41,G41,I41,K41,M41,O41) | R41: =SUM(D41,F41,H41,J41,L41,N41,P41) | S41: =IF($Q41=0,"",$R41/$Q41)
Q42: =SUM(C42,E42,G42,I42,K42,M42,O42) | R42: =SUM(D42,F42,H42,J42,L42,N42,P42) | S42: =IF($Q42=0,"",$R42/$Q42)
Q43: =SUM(C43,E43,G43,I43,K43,M43,O43) | R43: =SUM(D43,F43,H43,J43,L43,N43,P43) | S43: =IF($Q43=0,"",$R43/$Q43)
Q44: =SUM(C44,E44,G44,I44,K44,M44,O44) | R44: =SUM(D44,F44,H44,J44,L44,N44,P44) | S44: =IF($Q44=0,"",$R44/$Q44)
Q45: =SUM(C45,E45,G45,I45,K45,M45,O45) | R45: =SUM(D45,F45,H45,J45,L45,N45,P45) | S45: =IF($Q45=0,"",$R45/$Q45)
Q46: =SUM(C46,E46,G46,I46,K46,M46,O46) | R46: =SUM(D46,F46,H46,J46,L46,N46,P46) | S46: =IF($Q46=0,"",$R46/$Q46)
Q47: =SUM(C47,E47,G47,I47,K47,M47,O47) | R47: =SUM(D47,F47,H47,J47,L47,N47,P47) | S47: =IF($Q47=0,"",$R47/$Q47)
Q48: =SUM(C48,E48,G48,I48,K48,M48,O48) | R48: =SUM(D48,F48,H48,J48,L48,N48,P48) | S48: =IF($Q48=0,"",$R48/$Q48)
Q49: =SUM(C49,E49,G49,I49,K49,M49,O49) | R49: =SUM(D49,F49,H49,J49,L49,N49,P49) | S49: =IF($Q49=0,"",$R49/$Q49)
A50: TOTALES DEL AREA | C50: =SUM(C6:C49) | D50: =SUM(D6:D49) | E50: =SUM(E6:E49) | F50: =SUM(F6:F49) | G50: =SUM(G6:G49) | H50: =SUM(H6:H49) | I50: =SUM(I6:I49) | J50: =SUM(J6:J49) | ... R50: =SUM(R6:R49) | S50: =IF($Q50=0,"",$R50/$Q50)

Sheet 4 Prod Factureria
A1: PLANILLA 4 · PRODUCCION DIARIA — FACTURERÍA
A2: Jefe de area: ____________________ Semana: ____/____ al ____/____ Se elabora en: Central
A3: ELABORADO = lo que salio bueno. DESCARTE = lo que se quemo, salio mal, se cayo o se tiro. El detalle del motivo de cada descarte va en la planilla 5.
A4: PRODUCTO | B4: UNID. | C4: =IF(Config!$B$10="","LUNES",UPPER("LUN")&" "&TEXT(Config!$B$10,"dd/mm")) | E4: =IF(Config!$B$11="","MARTES",UPPER("MAR")&" "&TEXT(Config!$B$11,"dd/mm")) | G4: =IF(Config!$B$12="","MIERCOLES",UPPER("MIE")&" "&TEXT(Config!$B$12,"dd/mm")) | I4: =IF(Config!$B$13="","JUEVES",UPPER("JUE")&" "&TEXT(Config!$B$13,"dd/mm")) | K4: =IF(Config!$B$14="","VIERNES",UPPER("VIE")&" "&TEXT(Config!$B$14,"dd/mm")) | M4: =IF(Config!$B$15="","SABADO",UPPER("SAB")&" "&TEXT(Config!$B$15,"dd/mm")) | O4: =IF(Config!$B$16="","DOMINGO",UPPER("DOM")&" "&TEXT(Config!$B$16,"dd/mm")) | Q4: TOTAL ELABORADO | R4: TOTAL DESCARTE | S4: % DESC.
C5: ELABOR. | D5: DESCAR. | E5: ELABOR. | F5: DESCAR. | G5: ELABOR. | H5: DESCAR. | I5: ELABOR. | J5: DESCAR. | K5: ELABOR. | L5: DESCAR. | M5: ELABOR. | N5: DESCAR. | O5: ELABOR. | P5: DESCAR.
A6: Churros rellenos x unidad | B6: u | Q6: =SUM(C6,E6,G6,I6,K6,M6,O6) | R6: =SUM(D6,F6,H6,J6,L6,N6,P6) | S6: =IF($Q6=0,"",$R6/$Q6)
A7: Churros x unidad | B7: u | Q7: =SUM(C7,E7,G7,I7,K7,M7,O7) | R7: =SUM(D7,F7,H7,J7,L7,N7,P7) | S7: =IF($Q7=0,"",$R7/$Q7)
A8: Croissant | B8: u | Q8: =SUM(C8,E8,G8,I8,K8,M8,O8) | R8: =SUM(D8,F8,H8,J8,L8,N8,P8) | S8: =IF($Q8=0,"",$R8/$Q8)
A9: Facturas c/crema | B9: u | Q9: =SUM(C9,E9,G9,I9,K9,M9,O9) | R9: =SUM(D9,F9,H9,J9,L9,N9,P9) | S9: =IF($Q9=0,"",$R9/$Q9)
A10: Facturas c/crema y DDL | B10: u | Q10: =SUM(C10,E10,G10,I10,K10,M10,O10) | R10: =SUM(D10,F10,H10,J10,L10,N10,P10) | S10: =IF($Q10=0,"",$R10/$Q10)
A11: Facturas c/crema y membr. | B11: u | Q11: =SUM(C11,E11,G11,I11,K11,M11,O11) | R11: =SUM(D11,F11,H11,J11,L11,N11,P11) | S11: =IF($Q11=0,"",$R11/$Q11)
A12: Libritos | B12: u | Q12: =SUM(C12,E12,G12,I12,K12,M12,O12) | R12: =SUM(D12,F12,H12,J12,L12,N12,P12) | S12: =IF($Q12=0,"",$R12/$Q12)
A13: Medialunas | B13: u | Q13: =SUM(C13,E13,G13,I13,K13,M13,O13) | R13: =SUM(D13,F13,H13,J13,L13,N13,P13) | S13: =IF($Q13=0,"",$R13/$Q13)
A14: Medialunas crudas x16 | B14: u | Q14: =SUM(C14,E14,G14,I14,K14,M14,O14) | R14: =SUM(D14,F14,H14,J14,L14,N14,P14) | S14: =IF($Q14=0,"",$R14/$Q14)
A15: Medialunas saladas | B15: u | Q15: =SUM(C15,E15,G15,I15,K15,M15,O15) | R15: =SUM(D15,F15,H15,J15,L15,N15,P15) | S15: =IF($Q15=0,"",$R15/$Q15)
A16: Minifacturas | B16: kg | Q16: =SUM(C16,E16,G16,I16,K16,M16,O16) | R16: =SUM(D16,F16,H16,J16,L16,N16,P16) | S16: =IF($Q16=0,"",$R16/$Q16)
A17: Pan dulce | B17: u | Q17: =SUM(C17,E17,G17,I17,K17,M17,O17) | R17: =SUM(D17,F17,H17,J17,L17,N17,P17) | S17: =IF($Q17=0,"",$R17/$Q17)
... A21: Vigilantes | B21: u | Q21: =SUM(C21,E21,G21,I21,K21,M21,O21) | R21: =SUM(D21,F21,H21,J21,L21,N21,P21) | S21: =IF($Q21=0,"",$R21/$Q21)
Q22: =SUM(C22,E22,G22,I22,K22,M22,O22) | R22: =SUM(D22,F22,H22,J22,L22,N22,P22) | S22: =IF($Q22=0,"",$R22/$Q22)
Q23: =SUM(C23,E23,G23,I23,K23,M23,O23) | R23: =SUM(D23,F23,H23,J23,L23,N23,P23) | S23: =IF($Q23=0,"",$R23/$Q23)
Q24: =SUM(C24,E24,G24,I24,K24,M24,O24) | R24: =SUM(D24,F24,H24,J24,L24,N24,P24) | S24: =IF($Q24=0,"",$R24/$Q24)
Q25: =SUM(C25,E25,G25,I25,K25,M25,O25) | R25: =SUM(D25,F25,H25,J25,L25,N25,P25) | S25: =IF($Q25=0,"",$R25/$Q25)
Q26: =SUM(C26,E26,G26,I26,K26,M26,O26) | R26: =SUM(D26,F26,H26,J26,L26,N26,P26) | S26: =IF($Q26=0,"",$R26/$Q26)
Q27: =SUM(C27,E27,G27,I27,K27,M27,O27) | R27: =SUM(D27,F27,H27,J27,L27,N27,P27) | S27: =IF($Q27=0,"",$R27/$Q27)
Q28: =SUM(C28,E28,G28,I28,K28,M28,O28) | R28: =SUM(D28,F28,H28,J28,L28,N28,P28) | S28: =IF($Q28=0,"",$R28/$Q28)
Q29: =SUM(C29,E29,G29,I29,K29,M29,O29) | R29: =SUM(D29,F29,H29,J29,L29,N29,P29) | S29: =IF($Q29=0,"",$R29/$Q29)
A30: TOTALES DEL AREA | C30: =SUM(C6:C29) | D30: =SUM(D6:D29) | E30: =SUM(E6:E29) | F30: =SUM(F6:F29) | G30: =SUM(G6:G29) | H30: =SUM(H6:H29) | I30: =SUM(I6:I29) | J30: =SUM(J6:J29) | ... R30: =SUM(R6:R29) | S30: =IF($Q30=0,"",$R30/$Q30)

Sheet 4 Prod Sandwiches
A1: PLANILLA 4 · PRODUCCION DIARIA — SANDWICHES
A2: Jefe de area: ____________________ Semana: ____/____ al ____/____ Se elabora en: Central
A3: ELABORADO = lo que salio bueno. DESCARTE = lo que se quemo, salio mal, se cayo o se tiro. El detalle del motivo de cada descarte va en la planilla 5.
A4: PRODUCTO | B4: UNID. | C4: =IF(Config!$B$10="","LUNES",UPPER("LUN")&" "&TEXT(Config!$B$10,"dd/mm")) | E4: =IF(Config!$B$11="","MARTES",UPPER("MAR")&" "&TEXT(Config!$B$11,"dd/mm")) | G4: =IF(Config!$B$12="","MIERCOLES",UPPER("MIE")&" "&TEXT(Config!$B$12,"dd/mm")) | I4: =IF(Config!$B$13="","JUEVES",UPPER("JUE")&" "&TEXT(Config!$B$13,"dd/mm")) | K4: =IF(Config!$B$14="","VIERNES",UPPER("VIE")&" "&TEXT(Config!$B$14,"dd/mm")) | M4: =IF(Config!$B$15="","SABADO",UPPER("SAB")&" "&TEXT(Config!$B$15,"dd/mm")) | O4: =IF(Config!$B$16="","DOMINGO",UPPER("DOM")&" "&TEXT(Config!$B$16,"dd/mm")) | Q4: TOTAL ELABORADO | R4: TOTAL DESCARTE | S4: % DESC.
C5: ELABOR. | D5: DESCAR. | E5: ELABOR. | F5: DESCAR. | G5: ELABOR. | H5: DESCAR. | I5: ELABOR. | J5: DESCAR. | K5: ELABOR. | L5: DESCAR. | M5: ELABOR. | N5: DESCAR. | O5: ELABOR. | P5: DESCAR.
A6: Ciabatta de Lomito ahumado, muzzarella y rúcula con oliva | B6: u | Q6: =SUM(C6,E6,G6,I6,K6,M6,O6) | R6: =SUM(D6,F6,H6,J6,L6,N6,P6) | S6: =IF($Q6=0,"",$R6/$Q6)
A7: Ciabatta de Muzzarella, provolone, albahaca y cherrys confitados | B7: u | Q7: =SUM(C7,E7,G7,I7,K7,M7,O7) | R7: =SUM(D7,F7,H7,J7,L7,N7,P7) | S7: =IF($Q7=0,"",$R7/$Q7)
A8: Baguette de jamón cocido, queso, lechuga y tomate | B8: u | Q8: =SUM(C8,E8,G8,I8,K8,M8,O8) | R8: =SUM(D8,F8,H8,J8,L8,N8,P8) | S8: =IF($Q8=0,"",$R8/$Q8)
A9: Baguette de salame y queso | B9: u | Q9: =SUM(C9,E9,G9,I9,K9,M9,O9) | R9: =SUM(D9,F9,H9,J9,L9,N9,P9) | S9: =IF($Q9=0,"",$R9/$Q9)
A10: Miga de jamón cocido y queso | B10: u | Q10: =SUM(C10,E10,G10,I10,K10,M10,O10) | R10: =SUM(D10,F10,H10,J10,L10,N10,P10) | S10: =IF($Q10=0,"",$R10/$Q10)
A11: Miga de Ternera y tomate | B11: u | Q11: =SUM(C11,E11,G11,I11,K11,M11,O11) | R11: =SUM(D11,F11,H11,J11,L11,N11,P11) | S11: =IF($Q11=0,"",$R11/$Q11)
A12: Miga de ternera y huevo | B12: u | Q12: =SUM(C12,E12,G12,I12,K12,M12,O12) | R12: =SUM(D12,F12,H12,J12,L12,N12,P12) | S12: =IF($Q12=0,"",$R12/$Q12)
A13: Miga de crudo y queso | B13: u | Q13: =SUM(C13,E13,G13,I13,K13,M13,O13) | R13: =SUM(D13,F13,H13,J13,L13,N13,P13) | S13: =IF($Q13=0,"",$R13/$Q13)
A14: Miga de cantimpalo y queso | B14: u | Q14: =SUM(C14,E14,G14,I14,K14,M14,O14) | R14: =SUM(D14,F14,H14,J14,L14,N14,P14) | S14: =IF($Q14=0,"",$R14/$Q14)
Q15: =SUM(C15,E15,G15,I15,K15,M15,O15) | R15: =SUM(D15,F15,H15,J15,L15,N15,P15) | S15: =IF($Q15=0,"",$R15/$Q15)
Q16: =SUM(C16,E16,G16,I16,K16,M16,O16) | R16: =SUM(D16,F16,H16,J16,L16,N16,P16) | S16: =IF($Q16=0,"",$R16/$Q16)
Q17: =SUM(C17,E17,G17,I17,K17,M17,O17) | R17: =SUM(D17,F17,H17,J17,L17,N17,P17) | S17: =IF($Q17=0,"",$R17/$Q17)
Q18: =SUM(C18,E18,G18,I18,K18,M18,O18) | R18: =SUM(D18,F18,H18,J18,L18,N18,P18) | S18: =IF($Q18=0,"",$R18/$Q18)
Q19: =SUM(C19,E19,G19,I19,K19,M19,O19) | R19: =SUM(D19,F19,H19,J19,L19,N19,P19) | S19: =IF($Q19=0,"",$R19/$Q19)
Q20: =SUM(C20,E20,G20,I20,K20,M20,O20) | R20: =SUM(D20,F20,H20,J20,L20,N20,P20) | S20: =IF($Q20=0,"",$R20/$Q20)
Q21: =SUM(C21,E21,G21,I21,K21,M21,O21) | R21: =SUM(D21,F21,H21,J21,L21,N21,P21) | S21: =IF($Q21=0,"",$R21/$Q21)
Q22: =SUM(C22,E22,G22,I22,K22,M22,O22) | R22: =SUM(D22,F22,H22,J22,L22,N22,P22) | S22: =IF($Q22=0,"",$R22/$Q22)
A23: TOTALES DEL AREA | C23: =SUM(C6:C22) | D23: =SUM(D6:D22) | E23: =SUM(E6:E22) | F23: =SUM(F6:F22) | G23: =SUM(G6:G22) | H23: =SUM(H6:H22) | I23: =SUM(I6:I22) | J23: =SUM(J6:J22) | ... R23: =SUM(R6:R22) | S23: =IF($Q23=0,"",$R23/$Q23)

Sheet 4 Prod Cocina SL
A1: PLANILLA 4 · PRODUCCION DIARIA — COCINA SAN LUIS
A2: Jefe de area: ____________________ Semana: ____/____ al ____/____ Se elabora en: Local San Luis
A3: ELABORADO = lo que salio bueno. DESCARTE = lo que se quemo, salio mal, se cayo o se tiro. El detalle del motivo de cada descarte va en la planilla 5.
A4: PRODUCTO | B4: UNID. | C4: =IF(Config!$B$10="","LUNES",UPPER("LUN")&" "&TEXT(Config!$B$10,"dd/mm")) | E4: =IF(Config!$B$11="","MARTES",UPPER("MAR")&" "&TEXT(Config!$B$11,"dd/mm")) | G4: =IF(Config!$B$12="","MIERCOLES",UPPER("MIE")&" "&TEXT(Config!$B$12,"dd/mm")) | I4: =IF(Config!$B$13="","JUEVES",UPPER("JUE")&" "&TEXT(Config!$B$13,"dd/mm")) | K4: =IF(Config!$B$14="","VIERNES",UPPER("VIE")&" "&TEXT(Config!$B$14,"dd/mm")) | M4: =IF(Config!$B$15="","SABADO",UPPER("SAB")&" "&TEXT(Config!$B$15,"dd/mm")) | O4: =IF(Config!$B$16="","DOMINGO",UPPER("DOM")&" "&TEXT(Config!$B$16,"dd/mm")) | Q4: TOTAL ELABORADO | R4: TOTAL DESCARTE | S4: % DESC.
C5: ELABOR. | D5: DESCAR. | E5: ELABOR. | F5: DESCAR. | G5: ELABOR. | H5: DESCAR. | I5: ELABOR. | J5: DESCAR. | K5: ELABOR. | L5: DESCAR. | M5: ELABOR. | N5: DESCAR. | O5: ELABOR. | P5: DESCAR.
Q6: =SUM(C6,E6,G6,I6,K6,M6,O6) | R6: =SUM(D6,F6,H6,J6,L6,N6,P6) | S6: =IF($Q6=0,"",$R6/$Q6)
Q7: =SUM(C7,E7,G7,I7,K7,M7,O7) | R7: =SUM(D7,F7,H7,J7,L7,N7,P7) | S7: =IF($Q7=0,"",$R7/$Q7)
Q8: =SUM(C8,E8,G8,I8,K8,M8,O8) | R8: =SUM(D8,F8,H8,J8,L8,N8,P8) | S8: =IF($Q8=0,"",$R8/$Q8)
Q9: =SUM(C9,E9,G9,I9,K9,M9,O9) | R9: =SUM(D9,F9,H9,J9,L9,N9,P9) | S9: =IF($Q9=0,"",$R9/$Q9)
Q10: =SUM(C10,E10,G10,I10,K10,M10,O10) | R10: =SUM(D10,F10,H10,J10,L10,N10,P10) | S10: =IF($Q10=0,"",$R10/$Q10)
Q11: =SUM(C11,E11,G11,I11,K11,M11,O11) | R11: =SUM(D11,F11,H11,J11,L11,N11,P11) | S11: =IF($Q11=0,"",$R11/$Q11)
Q12: =SUM(C12,E12,G12,I12,K12,M12,O12) | R12: =SUM(D12,F12,H12,J12,L12,N12,P12) | S12: =IF($Q12=0,"",$R12/$Q12)
Q13: =SUM(C13,E13,G13,I13,K13,M13,O13) | R13: =SUM(D13,F13,H13,J13,L13,N13,P13) | S13: =IF($Q13=0,"",$R13/$Q13)
Q14: =SUM(C14,E14,G14,I14,K14,M14,O14) | R14: =SUM(D14,F14,H14,J14,L14,N14,P14) | S14: =IF($Q14=0,"",$R14/$Q14)
Q15: =SUM(C15,E15,G15,I15,K15,M15,O15) | R15: =SUM(D15,F15,H15,J15,L15,N15,P15) | S15: =IF($Q15=0,"",$R15/$Q15)
Q16: =SUM(C16,E16,G16,I16,K16,M16,O16) | R16: =SUM(D16,F16,H16,J16,L16,N16,P16) | S16: =IF($Q16=0,"",$R16/$Q16)
Q17: =SUM(C17,E17,G17,I17,K17,M17,O17) | R17: =SUM(D17,F17,H17,J17,L17,N17,P17) | S17: =IF($Q17=0,"",$R17/$Q17)
... Q45: =SUM(C45,E45,G45,I45,K45,M45,O45) | R45: =SUM(D45,F45,H45,J45,L45,N45,P45) | S45: =IF($Q45=0,"",$R45/$Q45)
A46: TOTALES DEL AREA | C46: =SUM(C6:C45) | D46: =SUM(D6:D45) | E46: =SUM(E6:E45) | F46: =SUM(F6:F45) | G46: =SUM(G6:G45) | H46: =SUM(H6:H45) | I46: =SUM(I6:I45) | J46: =SUM(J6:J45) | ... R46: =SUM(R6:R45) | S46: =IF($Q46=0,"",$R46/$Q46)

Sheet 5 Descartes
A1: PLANILLA 5 · DETALLE DE DESCARTES, QUEMADO Y TIRADO
A2: Una linea por cada cosa que se descarta, con el motivo. Es la planilla que explica los faltantes: lo que no se anota aca aparece despues como perdida sin justificar.
A3: La fila 5 es un EJEMPLO: borrela antes de empezar. Cargue desde la fila 6.
A4: FECHA | B4: AREA | C4: PRODUCTO O INSUMO | D4: CANTIDAD | E4: UNID. | F4: MOTIVO | G4: RESPONSABLE | H4: OBSERVACIONES
A5: =IF(Config!$B$6="","",Config!$B$6) | B5: Panaderia | C5: Medialunas | D5: 18 | E5: u | F5: Quemado / mal cocido | G5: JP | H5: Horno con temperatura alta

Sheet 6 Inv Final
A1: PLANILLA 6 · INVENTARIO FINAL DE INSUMOS
A2: Se cuenta el DOMINGO al cierre, con el mismo criterio que el inicial. Misma persona si es posible.
A3: COMO CONTAR: bultos cerrados + lo que hay suelto del abierto. Ejemplo: 3 bolsas de 25 kg + 8,5 kg sueltos -> Bultos = 3, Parcial = 8,5, TOTAL = 83,5 kg (lo calcula la planilla).
A4: AREA | B4: INSUMO | C4: UNID. | D4: CONTENIDO POR BULTO | E4: BULTOS CERRADOS | F4: PARCIAL (suelto) | G4: TOTAL (calculado) | H4: CONTO (iniciales) | I4: OBSERVACIONES
A5: =Insumos!$A5 | B5: =Insumos!$B5 | C5: =Insumos!$E5 | D5: =Insumos!$F5 | G5: =IFERROR($E5*$D5,0)+IFERROR($F5,0)
A6: =Insumos!$A6 | B6: =Insumos!$B6 | C6: =Insumos!$E6 | D6: =Insumos!$F6 | G6: =IFERROR($E6*$D6,0)+IFERROR($F6,0)
A7: =Insumos!$A7 | B7: =Insumos!$B7 | C7: =Insumos!$E7 | D7: =Insumos!$F7 | G7: =IFERROR($E7*$D7,0)+IFERROR($F7,0)
A8: =Insumos!$A8 | B8: =Insumos!$B8 | C8: =Insumos!$E8 | D8: =Insumos!$F8 | G8: =IFERROR($E8*$D8,0)+IFERROR($F8,0)
A9: =Insumos!$A9 | B9: =Insumos!$B9 | C9: =Insumos!$E9 | D9: =Insumos!$F9 | G9: =IFERROR($E9*$D9,0)+IFERROR($F9,0)
A10: =Insumos!$A10 | B10: =Insumos!$B10 | C10: =Insumos!$E10 | D10: =Insumos!$F10 | G10: =IFERROR($E10*$D10,0)+IFERROR($F10,0)
A11: =Insumos!$A11 | B11: =Insumos!$B11 | C11: =Insumos!$E11 | D11: =Insumos!$F11 | G11: =IFERROR($E11*$D11,0)+IFERROR($F11,0)
A12: =Insumos!$A12 | B12: =Insumos!$B12 | C12: =Insumos!$E12 | D12: =Insumos!$F12 | G12: =IFERROR($E12*$D12,0)+IFERROR($F12,0)
A13: =Insumos!$A13 | B13: =Insumos!$B13 | C13: =Insumos!$E13 | D13: =Insumos!$F13 | G13: =IFERROR($E13*$D13,0)+IFERROR($F13,0)
A14: =Insumos!$A14 | B14: =Insumos!$B14 | C14: =Insumos!$E14 | D14: =Insumos!$F14 | G14: =IFERROR($E14*$D14,0)+IFERROR($F14,0)
A15: =Insumos!$A15 | B15: =Insumos!$B15 | C15: =Insumos!$E15 | D15: =Insumos!$F15 | G15: =IFERROR($E15*$D15,0)+IFERROR($F15,0)
A16: =Insumos!$A16 | B16: =Insumos!$B16 | C16: =Insumos!$E16 | D16: =Insumos!$F16 | G16: =IFERROR($E16*$D16,0)+IFERROR($F16,0)
... A163: =Insumos!$A163 | B163: =Insumos!$B163 | C163: =Insumos!$E163 | D163: =Insumos!$F163 | G163: =IFERROR($E163*$D163,0)+IFERROR($F163,0)

Sheet 7 Facturas
A1: CARGA 7 · FACTURAS DE COMPRA DE LA SEMANA
A2: Se carga DESPUES de la semana, con las facturas en la mano. La CANTIDAD va en la unidad base del insumo (kg, u, L), no en bultos.
A3: La fila 5 es un EJEMPLO: borrela antes de empezar. Cargue desde la fila 6.
A4: FECHA | B4: PROVEEDOR | C4: N° FACTURA | D4: AREA | E4: INSUMO | F4: CANTIDAD (unidad base) | G4: UNID. | H4: IMPORTE TOTAL $ | I4: COSTO UNITARIO $ (calculado) | J4: CONTROL AUTOMATICO
A5: =IF(Config!$B$6="","",Config!$B$6) | B5: Molino XX | C5: A-0001-00012345 | D5: Panaderia | E5: Harina 000 x25kg | F5: 100 | G5: kg | H5: 85000 | I5: =IFERROR($H5/$F5,"") | J5: EJEMPLO - borrar esta fila
G6: =IFERROR(INDEX(Insumos!$E$5:$E$163,MATCH($D6&" | "&$E6,Insumos!$I$5:$I$163,0)),"") | I6: =IFERROR($H6/$F6,"") | J6: =IF($E6="","",IF(COUNTIF(Insumos!$I$5:$I$163,$D6&" | "&$E6)=0,"REVISAR: area+insumo no existe en el maestro","OK"))
G7: =IFERROR(INDEX(Insumos!$E$5:$E$163,MATCH($D7&" | "&$E7,Insumos!$I$5:$I$163,0)),"") | I7: =IFERROR($H7/$F7,"") | J7: =IF($E7="","",IF(COUNTIF(Insumos!$I$5:$I$163,$D7&" | "&$E7)=0,"REVISAR: area+insumo no existe en el maestro","OK"))
G8: =IFERROR(INDEX(Insumos!$E$5:$E$163,MATCH($D8&" | "&$E8,Insumos!$I$5:$I$163,0)),"") | I8: =IFERROR($H8/$F8,"") | J8: =IF($E8="","",IF(COUNTIF(Insumos!$I$5:$I$163,$D8&" | "&$E8)=0,"REVISAR: area+insumo no existe en el maestro","OK"))
G9: =IFERROR(INDEX(Insumos!$E$5:$E$163,MATCH($D9&" | "&$E9,Insumos!$I$5:$I$163,0)),"") | I9: =IFERROR($H9/$F9,"") | J9: =IF($E9="","",IF(COUNTIF(Insumos!$I$5:$I$163,$D9&" | "&$E9)=0,"REVISAR: area+insumo no existe en el maestro","OK"))
G10: =IFERROR(INDEX(Insumos!$E$5:$E$163,MATCH($D10&" | "&$E10,Insumos!$I$5:$I$163,0)),"") | I10: =IFERROR($H10/$F10,"") | J10: =IF($E10="","",IF(COUNTIF(Insumos!$I$5:$I$163,$D10&" | "&$E10)=0,"REVISAR: area+insumo no existe en el maestro","OK"))
G11: =IFERROR(INDEX(Insumos!$E$5:$E$163,MATCH($D11&" | "&$E11,Insumos!$I$5:$I$163,0)),"") | I11: =IFERROR($H11/$F11,"") | J11: =IF($E11="","",IF(COUNTIF(Insumos!$I$5:$I$163,$D11&" | "&$E11)=0,"REVISAR: area+insumo no existe en el maestro","OK"))
G12: =IFERROR(INDEX(Insumos!$E$5:$E$163,MATCH($D12&" | "&$E12,Insumos!$I$5:$I$163,0)),"") | I12: =IFERROR($H12/$F12,"") | J12: =IF($E12="","",IF(COUNTIF(Insumos!$I$5:$I$163,$D12&" | "&$E12)=0,"REVISAR: area+insumo no existe en el maestro","OK"))
G13: =IFERROR(INDEX(Insumos!$E$5:$E$163,MATCH($D13&" | "&$E13,Insumos!$I$5:$I$163,0)),"") | I13: =IFERROR($H13/$F13,"") | J13: =IF($E13="","",IF(COUNTIF(Insumos!$I$5:$I$163,$D13&" | "&$E13)=0,"REVISAR: area+insumo no existe en el maestro","OK"))
G14: =IFERROR(INDEX(Insumos!$E$5:$E$163,MATCH($D14&" | "&$E14,Insumos!$I$5:$I$163,0)),"") | I14: =IFERROR($H14/$F14,"") | J14: =IF($E14="","",IF(COUNTIF(Insumos!$I$5:$I$163,$D14&" | "&$E14)=0,"REVISAR: area+insumo no existe en el maestro","OK"))
G15: =IFERROR(INDEX(Insumos!$E$5:$E$163,MATCH($D15&" | "&$E15,Insumos!$I$5:$I$163,0)),"") | I15: =IFERROR($H15/$F15,"") | J15: =IF($E15="","",IF(COUNTIF(Insumos!$I$5:$I$163,$D15&" | "&$E15)=0,"REVISAR: area+insumo no existe en el maestro","OK"))
G16: =IFERROR(INDEX(Insumos!$E$5:$E$163,MATCH($D16&" | "&$E16,Insumos!$I$5:$I$163,0)),"") | I16: =IFERROR($H16/$F16,"") | J16: =IF($E16="","",IF(COUNTIF(Insumos!$I$5:$I$163,$D16&" | "&$E16)=0,"REVISAR: area+insumo no existe en el maestro","OK"))
G17: =IFERROR(INDEX(Insumos!$E$5:$E$163,MATCH($D17&" | "&$E17,Insumos!$I$5:$I$163,0)),"") | I17: =IFERROR($H17/$F17,"") | J17: =IF($E17="","",IF(COUNTIF(Insumos!$I$5:$I$163,$D17&" | "&$E17)=0,"REVISAR: area+insumo no existe en el maestro","OK"))
... G255: =IFERROR(INDEX(Insumos!$E$5:$E$163,MATCH($D255&" | "&$E255,Insumos!$I$5:$I$163,0)),"") | I255: =IFERROR($H255/$F255,"") | J255: =IF($E255="","",IF(COUNTIF(Insumos!$I$5:$I$163,$D255&" | "&$E255)=0,"REVISAR: area+insumo no existe en el maestro","OK"))
E257: TOTAL COMPRADO EN LA SEMANA | H257: =SUM($H$6:$H$255)

Sheet 8 Fudo Ventas
A1: CARGA 8a · VENTAS POR PRODUCTO SEGUN FUDO
A2: Pegue el export de Fudo en las columnas A y B. Despues indique a que AREA y a que PRODUCTO de Candela corresponde cada linea.
A3: Si un producto de Fudo no se mapea, no entra en la conciliacion. La fila 5 es un EJEMPLO: borrela.
A4: PRODUCTO SEGUN FUDO (pegar del export) | B4: UNIDADES VENDIDAS | C4: AREA DE CANDELA | D4: PRODUCTO DE CANDELA | E4: CONTROL AUTOMATICO
A5: Medialuna de manteca | B5: 640 | C5: Facturería | D5: Medialunas | E5: EJEMPLO - borrar esta fila
E6: =IF($A6="","",IF($D6="","FALTA MAPEAR","OK"))
E7: =IF($A7="","",IF($D7="","FALTA MAPEAR","OK"))
E8: =IF($A8="","",IF($D8="","FALTA MAPEAR","OK"))
E9: =IF($A9="","",IF($D9="","FALTA MAPEAR","OK"))
E10: =IF($A10="","",IF($D10="","FALTA MAPEAR","OK"))
E11: =IF($A11="","",IF($D11="","FALTA MAPEAR","OK"))
E12: =IF($A12="","",IF($D12="","FALTA MAPEAR","OK"))
E13: =IF($A13="","",IF($D13="","FALTA MAPEAR","OK"))
E14: =IF($A14="","",IF($D14="","FALTA MAPEAR","OK"))
E15: =IF($A15="","",IF($D15="","FALTA MAPEAR","OK"))
E16: =IF($A16="","",IF($D16="","FALTA MAPEAR","OK"))
E17: =IF($A17="","",IF($D17="","FALTA MAPEAR","OK"))
... E305: =IF($A305="","",IF($D305="","FALTA MAPEAR","OK"))

Sheet 8 Fudo Stock
A1: CARGA 8b · MOVIMIENTOS DE STOCK DE INSUMOS SEGUN FUDO
A2: Pegue el reporte de existencias/movimientos de Fudo en A:E. Despues mapee AREA e INSUMO de Candela.
A3: Si Fudo no informa egresos, la planilla los calcula: inicial + ingresos - final. La fila 5 es un EJEMPLO: borrela.
A4: INSUMO SEGUN FUDO (pegar del export) | B4: STOCK INICIAL | C4: INGRESOS | D4: EGRESOS | E4: STOCK FINAL | F4: AREA DE CANDELA | G4: INSUMO DE CANDELA | H4: CONSUMO S/FUDO (calculado) | I4: CLAVE (no tocar)
A5: Harina 000 | B5: 120 | C5: 100 | E5: 95 | F5: Panadería | G5: Harina 000 x25kg | H5: =IF($D5<>"",$D5,IF(COUNT($B5,$E5)=2,$B5+IFERROR($C5,0)-$E5,""))
H6: =IF($D6<>"",$D6,IF(COUNT($B6,$E6)=2,$B6+IFERROR($C6,0)-$E6,"")) | I6: =IF($G6="","",$F6&" | "&$G6)
H7: =IF($D7<>"",$D7,IF(COUNT($B7,$E7)=2,$B7+IFERROR($C7,0)-$E7,"")) | I7: =IF($G7="","",$F7&" | "&$G7)
H8: =IF($D8<>"",$D8,IF(COUNT($B8,$E8)=2,$B8+IFERROR($C8,0)-$E8,"")) | I8: =IF($G8="","",$F8&" | "&$G8)
H9: =IF($D9<>"",$D9,IF(COUNT($B9,$E9)=2,$B9+IFERROR($C9,0)-$E9,"")) | I9: =IF($G9="","",$F9&" | "&$G9)
H10: =IF($D10<>"",$D10,IF(COUNT($B10,$E10)=2,$B10+IFERROR($C10,0)-$E10,"")) | I10: =IF($G10="","",$F10&" | "&$G10)
H11: =IF($D11<>"",$D11,IF(COUNT($B11,$E11)=2,$B11+IFERROR($C11,0)-$E11,"")) | I11: =IF($G11="","",$F11&" | "&$G11)
H12: =IF($D12<>"",$D12,IF(COUNT($B12,$E12)=2,$B12+IFERROR($C12,0)-$E12,"")) | I12: =IF($G12="","",$F12&" | "&$G12)
H13: =IF($D13<>"",$D13,IF(COUNT($B13,$E13)=2,$B13+IFERROR($C13,0)-$E13,"")) | I13: =IF($G13="","",$F13&" | "&$G13)
H14: =IF($D14<>"",$D14,IF(COUNT($B14,$E14)=2,$B14+IFERROR($C14,0)-$E14,"")) | I14: =IF($G14="","",$F14&" | "&$G14)
H15: =IF($D15<>"",$D15,IF(COUNT($B15,$E15)=2,$B15+IFERROR($C15,0)-$E15,"")) | I15: =IF($G15="","",$F15&" | "&$G15)
H16: =IF($D16<>"",$D16,IF(COUNT($B16,$E16)=2,$B16+IFERROR($C16,0)-$E16,"")) | I16: =IF($G16="","",$F16&" | "&$G16)
H17: =IF($D17<>"",$D17,IF(COUNT($B17,$E17)=2,$B17+IFERROR($C17,0)-$E17,"")) | I17: =IF($G17="","",$F17&" | "&$G17)
... H205: =IF($D205<>"",$D205,IF(COUNT($B205,$E205)=2,$B205+IFERROR($C205,0)-$E205,"")) | I205: =IF($G205="","",$F205&" | "&$G205)

Sheet 8 Fudo Consumos
A1: CARGA 8c · CONSUMOS INTERNOS Y CORTESIAS SEGUN FUDO
A2: Todo lo que se consumio sin venderse y quedo registrado en Fudo: consumo del personal, cortesias, pruebas.
A3: Esta hoja es la que separa el consumo legitimo del faltante real. La fila 5 es un EJEMPLO: borrela.
A4: FECHA | B4: PRODUCTO DE CANDELA | C4: AREA | D4: CANTIDAD | E4: UNID. | F4: TIPO | G4: RESPONSABLE / SECTOR | H4: OBSERVACIONES
A5: =IF(Config!$B$6="","",Config!$B$6) | B5: Medialunas | C5: Facturería | D5: 24 | E5: u | F5: Consumo del personal | G5: Salon manana

Sheet A Consumo Insumos
A1: ANALISIS A · CONSUMO REAL DE INSUMOS DE LA SEMANA
A2: CONSUMO REAL = Stock inicial + Ingresos de la semana - Stock final. Se compara contra las facturas y contra Fudo.
A3: Un CONSUMO NEGATIVO significa que entro mercaderia que nadie anoto. Un DESVIO ALTO contra Fudo es el candidato a faltante o a mal uso.
A4: AREA | B4: INSUMO | C4: UNID. | D4: STOCK INICIAL | E4: INGRESOS S/PLANILLA | F4: STOCK FINAL | G4: CONSUMO REAL | H4: COMPRAS S/FACTURAS | I4: DIF. RECEP. VS FACTURA | J4: CONSUMO S/FUDO | K4: DIF. REAL VS FUDO | L4: % DESVIO | M4: COSTO UNIT. $ | N4: CONSUMO VALORIZADO $ | O4: DESVIO VALORIZADO $ | P4: ALERTA | Q4: k% | R4: k$
A5: =Insumos!$A5 | B5: =Insumos!$B5 | C5: =Insumos!$E5 | D5: ='1 Inv Inicial'!$G5 | E5: =SUMIFS('2 Ingresos'!$I$6:$I$255,'2 Ingresos'!$B$6:$B$255,$A5,'2 Ingresos'!$C$6:$C$255,$B5) | F5: ='6 Inv Final'!$G5 | G5: =$D5+$E5-$F5 | H5: =SUMIFS('7 Facturas'!$F$6:$F$255,'7 Facturas'!$D$6:$D$255,$A5,'7 Facturas'!$E$6:$E$255,$B5) | I5: =$E5-$H5 | J5: =IFERROR(INDEX('8 Fudo Stock'!$H$6:$H$205,MATCH($A5&" | "&$B5,'8 Fudo Stock'!$I$6:$I$205,0)),"") | K5: =IF($J5="","",$G5-$J5) | L5: =IF(OR($J5="",$J5=0),"",$K5/$J5) | M5: =IF(Insumos!$H5="","",Insumos!$H5) | N5: =IF($M5="","",$G5*$M5) | O5: =IF(OR($M5="",$K5=""),"",$K5*$M5) | P5: =IF(AND('1 Inv Inicial'!$E5="",'1 Inv Inicial'!$F5=""),"Falta inventario inicial",IF(AND('6 Inv Final'!$E5="",'6 Inv Final'!$F5=""),"Falta inventario final",IF($G5<0,"Consumo negativo: entro mercaderia sin registrar",IF(AND($L5<>"",ABS($L5)>Config!$B$46),"Desvio alto vs Fudo: investigar",IF(AND($H5>0,ABS($I5)/$H5>Config!$B$46),"Lo recibido no coincide con la factura",IF(AND($J5="",$G5>0),"Sin dato de Fudo para comparar","OK")))))) | Q5: =IF($L5="","",ABS($L5)+ROW()/1000000) | R5: =IF($O5="","",ABS($O5)+ROW()/1000000)
A6: =Insumos!$A6 | B6: =Insumos!$B6 | C6: =Insumos!$E6 | D6: ='1 Inv Inicial'!$G6 | E6: =SUMIFS('2 Ingresos'!$I$6:$I$255,'2 Ingresos'!$B$6:$B$255,$A6,'2 Ingresos'!$C$6:$C$255,$B6) | F6: ='6 Inv Final'!$G6 | G6: =$D6+$E6-$F6 | H6: =SUMIFS('7 Facturas'!$F$6:$F$255,'7 Facturas'!$D$6:$D$255,$A6,'7 Facturas'!$E$6:$E$255,$B6) | I6: =$E6-$H6 | J6: =IFERROR(INDEX('8 Fudo Stock'!$H$6:$H$205,MATCH($A6&" | "&$B6,'8 Fudo Stock'!$I$6:$I$205,0)),"") | K6: =IF($J6="","",$G6-$J6) | L6: =IF(OR($J6="",$J6=0),"",$K6/$J6) | M6: =IF(Insumos!$H6="","",Insumos!$H6) | N6: =IF($M6="","",$G6*$M6) | O6: =IF(OR($M6="",$K6=""),"",$K6*$M6) | P6: =IF(AND('1 Inv Inicial'!$E6="",'1 Inv Inicial'!$F6=""),"Falta inventario inicial",IF(AND('6 Inv Final'!$E6="",'6 Inv Final'!$F6=""),"Falta inventario final",IF($G6<0,"Consumo negativo: entro mercaderia sin registrar",IF(AND($L6<>"",ABS($L6)>Config!$B$46),"Desvio alto vs Fudo: investigar",IF(AND($H6>0,ABS($I6)/$H6>Config!$B$46),"Lo recibido no coincide con la factura",IF(AND($J6="",$G6>0),"Sin dato de Fudo para comparar","OK")))))) | Q6: =IF($L6="","",ABS($L6)+ROW()/1000000) | R6: =IF($O6="","",ABS($O6)+ROW()/1000000)
A7: =Insumos!$A7 | B7: =Insumos!$B7 | C7: =Insumos!$E7 | D7: ='1 Inv Inicial'!$G7 | E7: =SUMIFS('2 Ingresos'!$I$6:$I$255,'2 Ingresos'!$B$6:$B$255,$A7,'2 Ingresos'!$C$6:$C$255,$B7) | F7: ='6 Inv Final'!$G7 | G7: =$D7+$E7-$F7 | H7: =SUMIFS('7 Facturas'!$F$6:$F$255,'7 Facturas'!$D$6:$D$255,$A7,'7 Facturas'!$E$6:$E$255,$B7) | I7: =$E7-$H7 | J7: =IFERROR(INDEX('8 Fudo Stock'!$H$6:$H$205,MATCH($A7&" | "&$B7,'8 Fudo Stock'!$I$6:$I$205,0)),"") | K7: =IF($J7="","",$G7-$J7) | L7: =IF(OR($J7="",$J7=0),"",$K7/$J7) | M7: =IF(Insumos!$H7="","",Insumos!$H7) | N7: =IF($M7="","",$G7*$M7) | O7: =IF(OR($M7="",$K7=""),"",$K7*$M7) | P7: =IF(AND('1 Inv Inicial'!$E7="",'1 Inv Inicial'!$F7=""),"Falta inventario inicial",IF(AND('6 Inv Final'!$E7="",'6 Inv Final'!$F7=""),"Falta inventario final",IF($G7<0,"Consumo negativo: entro mercaderia sin registrar",IF(AND($L7<>"",ABS($L7)>Config!$B$46),"Desvio alto vs Fudo: investigar",IF(AND($H7>0,ABS($I7)/$H7>Config!$B$46),"Lo recibido no coincide con la factura",IF(AND($J7="",$G7>0),"Sin dato de Fudo para comparar","OK")))))) | Q7: =IF($L7="","",ABS($L7)+ROW()/1000000) | R7: =IF($O7="","",ABS($O7)+ROW()/1000000)
A8: =Insumos!$A8 | B8: =Insumos!$B8 | C8: =Insumos!$E8 | D8: ='1 Inv Inicial'!$G8 | E8: =SUMIFS('2 Ingresos'!$I$6:$I$255,'2 Ingresos'!$B$6:$B$255,$A8,'2 Ingresos'!$C$6:$C$255,$B8) | F8: ='6 Inv Final'!$G8 | G8: =$D8+$E8-$F8 | H8: =SUMIFS('7 Facturas'!$F$6:$F$255,'7 Facturas'!$D$6:$D$255,$A8,'7 Facturas'!$E$6:$E$255,$B8) | I8: =$E8-$H8 | J8: =IFERROR(INDEX('8 Fudo Stock'!$H$6:$H$205,MATCH($A8&" | "&$B8,'8 Fudo Stock'!$I$6:$I$205,0)),"") | K8: =IF($J8="","",$G8-$J8) | L8: =IF(OR($J8="",$J8=0),"",$K8/$J8) | M8: =IF(Insumos!$H8="","",Insumos!$H8) | N8: =IF($M8="","",$G8*$M8) | O8: =IF(OR($M8="",$K8=""),"",$K8*$M8) | P8: =IF(AND('1 Inv Inicial'!$E8="",'1 Inv Inicial'!$F8=""),"Falta inventario inicial",IF(AND('6 Inv Final'!$E8="",'6 Inv Final'!$F8=""),"Falta inventario final",IF($G8<0,"Consumo negativo: entro mercaderia sin registrar",IF(AND($L8<>"",ABS($L8)>Config!$B$46),"Desvio alto vs Fudo: investigar",IF(AND($H8>0,ABS($I8)/$H8>Config!$B$46),"Lo recibido no coincide con la factura",IF(AND($J8="",$G8>0),"Sin dato de Fudo para comparar","OK")))))) | Q8: =IF($L8="","",ABS($L8)+ROW()/1000000) | R8: =IF($O8="","",ABS($O8)+ROW()/1000000)
A9: =Insumos!$A9 | B9: =Insumos!$B9 | C9: =Insumos!$E9 | D9: ='1 Inv Inicial'!$G9 | E9: =SUMIFS('2 Ingresos'!$I$6:$I$255,'2 Ingresos'!$B$6:$B$255,$A9,'2 Ingresos'!$C$6:$C$255,$B9) | F9: ='6 Inv Final'!$G9 | G9: =$D9+$E9-$F9 | H9: =SUMIFS('7 Facturas'!$F$6:$F$255,'7 Facturas'!$D$6:$D$255,$A9,'7 Facturas'!$E$6:$E$255,$B9) | I9: =$E9-$H9 | J9: =IFERROR(INDEX('8 Fudo Stock'!$H$6:$H$205,MATCH($A9&" | "&$B9,'8 Fudo Stock'!$I$6:$I$205,0)),"") | K9: =IF($J9="","",$G9-$J9) | L9: =IF(OR($J9="",$J9=0),"",$K9/$J9) | M9: =IF(Insumos!$H9="","",Insumos!$H9) | N9: =IF($M9="","",$G9*$M9) | O9: =IF(OR($M9="",$K9=""),"",$K9*$M9) | P9: =IF(AND('1 Inv Inicial'!$E9="",'1 Inv Inicial'!$F9=""),"Falta inventario inicial",IF(AND('6 Inv Final'!$E9="",'6 Inv Final'!$F9=""),"Falta inventario final",IF($G9<0,"Consumo negativo: entro mercaderia sin registrar",IF(AND($L9<>"",ABS($L9)>Config!$B$46),"Desvio alto vs Fudo: investigar",IF(AND($H9>0,ABS($I9)/$H9>Config!$B$46),"Lo recibido no coincide con la factura",IF(AND($J9="",$G9>0),"Sin dato de Fudo para comparar","OK")))))) | Q9: =IF($L9="","",ABS($L9)+ROW()/1000000) | R9: =IF($O9="","",ABS($O9)+ROW()/1000000)
A10: =Insumos!$A10 | B10: =Insumos!$B10 | C10: =Insumos!$E10 | D10: ='1 Inv Inicial'!$G10 | E10: =SUMIFS('2 Ingresos'!$I$6:$I$255,'2 Ingresos'!$B$6:$B$255,$A10,'2 Ingresos'!$C$6:$C$255,$B10) | F10: ='6 Inv Final'!$G10 | G10: =$D10+$E10-$F10 | H10: =SUMIFS('7 Facturas'!$F$6:$F$255,'7 Facturas'!$D$6:$D$255,$A10,'7 Facturas'!$E$6:$E$255,$B10) | I10: =$E10-$H10 | J10: =IFERROR(INDEX('8 Fudo Stock'!$H$6:$H$205,MATCH($A10&" | "&$B10,'8 Fudo Stock'!$I$6:$I$205,0)),"") | K10: =IF($J10="","",$G10-$J10) | L10: =IF(OR($J10="",$J10=0),"",$K10/$J10) | M10: =IF(Insumos!$H10="","",Insumos!$H10) | N10: =IF($M10="","",$G10*$M10) | O10: =IF(OR($M10="",$K10=""),"",$K10*$M10) | P10: =IF(AND('1 Inv Inicial'!$E10="",'1 Inv Inicial'!$F10=""),"Falta inventario inicial",IF(AND('6 Inv Final'!$E10="",'6 Inv Final'!$F10=""),"Falta inventario final",IF($G10<0,"Consumo negativo: entro mercaderia sin registrar",IF(AND($L10<>"",ABS($L10)>Config!$B$46),"Desvio alto vs Fudo: investigar",IF(AND($H10>0,ABS($I10)/$H10>Config!$B$46),"Lo recibido no coincide con la factura",IF(AND($J10="",$G10>0),"Sin dato de Fudo para comparar","OK")))))) | Q10: =IF($L10="","",ABS($L10)+ROW()/1000000) | R10: =IF($O10="","",ABS($O10)+ROW()/1000000)
A11: =Insumos!$A11 | B11: =Insumos!$B11 | C11: =Insumos!$E11 | D11: ='1 Inv Inicial'!$G11 | E11: =SUMIFS('2 Ingresos'!$I$6:$I$255,'2 Ingresos'!$B$6:$B$255,$A11,'2 Ingresos'!$C$6:$C$255,$B11) | F11: ='6 Inv Final'!$G11 | G11: =$D11+$E11-$F11 | H11: =SUMIFS('7 Facturas'!$F$6:$F$255,'7 Facturas'!$D$6:$D$255,$A11,'7 Facturas'!$E$6:$E$255,$B11) | I11: =$E11-$H11 | J11: =IFERROR(INDEX('8 Fudo Stock'!$H$6:$H$205,MATCH($A11&" | "&$B11,'8 Fudo Stock'!$I$6:$I$205,0)),"") | K11: =IF($J11="","",$G11-$J11) | L11: =IF(OR($J11="",$J11=0),"",$K11/$J11) | M11: =IF(Insumos!$H11="","",Insumos!$H11) | N11: =IF($M11="","",$G11*$M11) | O11: =IF(OR($M11="",$K11=""),"",$K11*$M11) | P11: =IF(AND('1 Inv Inicial'!$E11="",'1 Inv Inicial'!$F11=""),"Falta inventario inicial",IF(AND('6 Inv Final'!$E11="",'6 Inv Final'!$F11=""),"Falta inventario final",IF($G11<0,"Consumo negativo: entro mercaderia sin registrar",IF(AND($L11<>"",ABS($L11)>Config!$B$46),"Desvio alto vs Fudo: investigar",IF(AND($H11>0,ABS($I11)/$H11>Config!$B$46),"Lo recibido no coincide con la factura",IF(AND($J11="",$G11>0),"Sin dato de Fudo para comparar","OK")))))) | Q11: =IF($L11="","",ABS($L11)+ROW()/1000000) | R11: =IF($O11="","",ABS($O11)+ROW()/1000000)
A12: =Insumos!$A12 | B12: =Insumos!$B12 | C12: =Insumos!$E12 | D12: ='1 Inv Inicial'!$G12 | E12: =SUMIFS('2 Ingresos'!$I$6:$I$255,'2 Ingresos'!$B$6:$B$255,$A12,'2 Ingresos'!$C$6:$C$255,$B12) | F12: ='6 Inv Final'!$G12 | G12: =$D12+$E12-$F12 | H12: =SUMIFS('7 Facturas'!$F$6:$F$255,'7 Facturas'!$D$6:$D$255,$A12,'7 Facturas'!$E$6:$E$255,$B12) | I12: =$E12-$H12 | J12: =IFERROR(INDEX('8 Fudo Stock'!$H$6:$H$205,MATCH($A12&" | "&$B12,'8 Fudo Stock'!$I$6:$I$205,0)),"") | K12: =IF($J12="","",$G12-$J12) | L12: =IF(OR($J12="",$J12=0),"",$K12/$J12) | M12: =IF(Insumos!$H12="","",Insumos!$H12) | N12: =IF($M12="","",$G12*$M12) | O12: =IF(OR($M12="",$K12=""),"",$K12*$M12) | P12: =IF(AND('1 Inv Inicial'!$E12="",'1 Inv Inicial'!$F12=""),"Falta inventario inicial",IF(AND('6 Inv Final'!$E12="",'6 Inv Final'!$F12=""),"Falta inventario final",IF($G12<0,"Consumo negativo: entro mercaderia sin registrar",IF(AND($L12<>"",ABS($L12)>Config!$B$46),"Desvio alto vs Fudo: investigar",IF(AND($H12>0,ABS($I12)/$H12>Config!$B$46),"Lo recibido no coincide con la factura",IF(AND($J12="",$G12>0),"Sin dato de Fudo para comparar","OK")))))) | Q12: =IF($L12="","",ABS($L12)+ROW()/1000000) | R12: =IF($O12="","",ABS($O12)+ROW()/1000000)
A13: =Insumos!$A13 | B13: =Insumos!$B13 | C13: =Insumos!$E13 | D13: ='1 Inv Inicial'!$G13 | E13: =SUMIFS('2 Ingresos'!$I$6:$I$255,'2 Ingresos'!$B$6:$B$255,$A13,'2 Ingresos'!$C$6:$C$255,$B13) | F13: ='6 Inv Final'!$G13 | G13: =$D13+$E13-$F13 | H13: =SUMIFS('7 Facturas'!$F$6:$F$255,'7 Facturas'!$D$6:$D$255,$A13,'7 Facturas'!$E$6:$E$255,$B13) | I13: =$E13-$H13 | J13: =IFERROR(INDEX('8 Fudo Stock'!$H$6:$H$205,MATCH($A13&" | "&$B13,'8 Fudo Stock'!$I$6:$I$205,0)),"") | K13: =IF($J13="","",$G13-$J13) | L13: =IF(OR($J13="",$J13=0),"",$K13/$J13) | M13: =IF(Insumos!$H13="","",Insumos!$H13) | N13: =IF($M13="","",$G13*$M13) | O13: =IF(OR($M13="",$K13=""),"",$K13*$M13) | P13: =IF(AND('1 Inv Inicial'!$E13="",'1 Inv Inicial'!$F13=""),"Falta inventario inicial",IF(AND('6 Inv Final'!$E13="",'6 Inv Final'!$F13=""),"Falta inventario final",IF($G13<0,"Consumo negativo: entro mercaderia sin registrar",IF(AND($L13<>"",ABS($L13)>Config!$B$46),"Desvio alto vs Fudo: investigar",IF(AND($H13>0,ABS($I13)/$H13>Config!$B$46),"Lo recibido no coincide con la factura",IF(AND($J13="",$G13>0),"Sin dato de Fudo para comparar","OK")))))) | Q13: =IF($L13="","",ABS($L13)+ROW()/1000000) | R13: =IF($O13="","",ABS($O13)+ROW()/1000000)
A14: =Insumos!$A14 | B14: =Insumos!$B14 | C14: =Insumos!$E14 | D14: ='1 Inv Inicial'!$G14 | E14: =SUMIFS('2 Ingresos'!$I$6:$I$255,'2 Ingresos'!$B$6:$B$255,$A14,'2 Ingresos'!$C$6:$C$255,$B14) | F14: ='6 Inv Final'!$G14 | G14: =$D14+$E14-$F14 | H14: =SUMIFS('7 Facturas'!$F$6:$F$255,'7 Facturas'!$D$6:$D$255,$A14,'7 Facturas'!$E$6:$E$255,$B14) | I14: =$E14-$H14 | J14: =IFERROR(INDEX('8 Fudo Stock'!$H$6:$H$205,MATCH($A14&" | "&$B14,'8 Fudo Stock'!$I$6:$I$205,0)),"") | K14: =IF($J14="","",$G14-$J14) | L14: =IF(OR($J14="",$J14=0),"",$K14/$J14) | M14: =IF(Insumos!$H14="","",Insumos!$H14) | N14: =IF($M14="","",$G14*$M14) | O14: =IF(OR($M14="",$K14=""),"",$K14*$M14) | P14: =IF(AND('1 Inv Inicial'!$E14="",'1 Inv Inicial'!$F14=""),"Falta inventario inicial",IF(AND('6 Inv Final'!$E14="",'6 Inv Final'!$F14=""),"Falta inventario final",IF($G14<0,"Consumo negativo: entro mercaderia sin registrar",IF(AND($L14<>"",ABS($L14)>Config!$B$46),"Desvio alto vs Fudo: investigar",IF(AND($H14>0,ABS($I14)/$H14>Config!$B$46),"Lo recibido no coincide con la factura",IF(AND($J14="",$G14>0),"Sin dato de Fudo para comparar","OK")))))) | Q14: =IF($L14="","",ABS($L14)+ROW()/1000000) | R14: =IF($O14="","",ABS($O14)+ROW()/1000000)
A15: =Insumos!$A15 | B15: =Insumos!$B15 | C15: =Insumos!$E15 | D15: ='1 Inv Inicial'!$G15 | E15: =SUMIFS('2 Ingresos'!$I$6:$I$255,'2 Ingresos'!$B$6:$B$255,$A15,'2 Ingresos'!$C$6:$C$255,$B15) | F15: ='6 Inv Final'!$G15 | G15: =$D15+$E15-$F15 | H15: =SUMIFS('7 Facturas'!$F$6:$F$255,'7 Facturas'!$D$6:$D$255,$A15,'7 Facturas'!$E$6:$E$255,$B15) | I15: =$E15-$H15 | J15: =IFERROR(INDEX('8 Fudo Stock'!$H$6:$H$205,MATCH($A15&" | "&$B15,'8 Fudo Stock'!$I$6:$I$205,0)),"") | K15: =IF($J15="","",$G15-$J15) | L15: =IF(OR($J15="",$J15=0),"",$K15/$J15) | M15: =IF(Insumos!$H15="","",Insumos!$H15) | N15: =IF($M15="","",$G15*$M15) | O15: =IF(OR($M15="",$K15=""),"",$K15*$M15) | P15: =IF(AND('1 Inv Inicial'!$E15="",'1 Inv Inicial'!$F15=""),"Falta inventario inicial",IF(AND('6 Inv Final'!$E15="",'6 Inv Final'!$F15=""),"Falta inventario final",IF($G15<0,"Consumo negativo: entro mercaderia sin registrar",IF(AND($L15<>"",ABS($L15)>Config!$B$46),"Desvio alto vs Fudo: investigar",IF(AND($H15>0,ABS($I15)/$H15>Config!$B$46),"Lo recibido no coincide con la factura",IF(AND($J15="",$G15>0),"Sin dato de Fudo para comparar","OK")))))) | Q15: =IF($L15="","",ABS($L15)+ROW()/1000000) | R15: =IF($O15="","",ABS($O15)+ROW()/1000000)
A16: =Insumos!$A16 | B16: =Insumos!$B16 | C16: =Insumos!$E16 | D16: ='1 Inv Inicial'!$G16 | E16: =SUMIFS('2 Ingresos'!$I$6:$I$255,'2 Ingresos'!$B$6:$B$255,$A16,'2 Ingresos'!$C$6:$C$255,$B16) | F16: ='6 Inv Final'!$G16 | G16: =$D16+$E16-$F16 | H16: =SUMIFS('7 Facturas'!$F$6:$F$255,'7 Facturas'!$D$6:$D$255,$A16,'7 Facturas'!$E$6:$E$255,$B16) | I16: =$E16-$H16 | J16: =IFERROR(INDEX('8 Fudo Stock'!$H$6:$H$205,MATCH($A16&" | "&$B16,'8 Fudo Stock'!$I$6:$I$205,0)),"") | K16: =IF($J16="","",$G16-$J16) | L16: =IF(OR($J16="",$J16=0),"",$K16/$J16) | M16: =IF(Insumos!$H16="","",Insumos!$H16) | N16: =IF($M16="","",$G16*$M16) | O16: =IF(OR($M16="",$K16=""),"",$K16*$M16) | P16: =IF(AND('1 Inv Inicial'!$E16="",'1 Inv Inicial'!$F16=""),"Falta inventario inicial",IF(AND('6 Inv Final'!$E16="",'6 Inv Final'!$F16=""),"Falta inventario final",IF($G16<0,"Consumo negativo: entro mercaderia sin registrar",IF(AND($L16<>"",ABS($L16)>Config!$B$46),"Desvio alto vs Fudo: investigar",IF(AND($H16>0,ABS($I16)/$H16>Config!$B$46),"Lo recibido no coincide con la factura",IF(AND($J16="",$G16>0),"Sin dato de Fudo para comparar","OK")))))) | Q16: =IF($L16="","",ABS($L16)+ROW()/1000000) | R16: =IF($O16="","",ABS($O16)+ROW()/1000000)
... A163: =Insumos!$A163 | B163: =Insumos!$B163 | C163: =Insumos!$E163 | D163: ='1 Inv Inicial'!$G163 | E163: =SUMIFS('2 Ingresos'!$I$6:$I$255,'2 Ingresos'!$B$6:$B$255,$A163,'2 Ingresos'!$C$6:$C$255,$B163) | F163: ='6 Inv Final'!$G163 | G163: =$D163+$E163-$F163 | H163: =SUMIFS('7 Facturas'!$F$6:$F$255,'7 Facturas'!$D$6:$D$255,$A163,'7 Facturas'!$E$6:$E$255,$B163) | I163: =$E163-$H163 | J163: =IFERROR(INDEX('8 Fudo Stock'!$H$6:$H$205,MATCH($A163&" | "&$B163,'8 Fudo Stock'!$I$6:$I$205,0)),"") | K163: =IF($J163="","",$G163-$J163) | L163: =IF(OR($J163="",$J163=0),"",$K163/$J163) | M163: =IF(Insumos!$H163="","",Insumos!$H163) | N163: =IF($M163="","",$G163*$M163) | O163: =IF(OR($M163="",$K163=""),"",$K163*$M163) | P163: =IF(AND('1 Inv Inicial'!$E163="",'1 Inv Inicial'!$F163=""),"Falta inventario inicial",IF(AND('6 Inv Final'!$E163="",'6 Inv Final'!$F163=""),"Falta inventario final",IF($G163<0,"Consumo negativo: entro mercaderia sin registrar",IF(AND($L163<>"",ABS($L163)>Config!$B$46),"Desvio alto vs Fudo: investigar",IF(AND($H163>0,ABS($I163)/$H163>Config!$B$46),"Lo recibido no coincide con la factura",IF(AND($J163="",$G163>0),"Sin dato de Fudo para comparar","OK")))))) | Q163: =IF($L163="","",ABS($L163)+ROW()/1000000) | R163: =IF($O163="","",ABS($O163)+ROW()/1000000)
A164: TOTALES | N164: =SUM(N$5:N$163) | O164: =SUM(O$5:O$163) | P164: =COUNTIF($P$5:$P$163,"OK")&" de 159 insumos OK"

Sheet B Concil Productos
A1: ANALISIS B · CONCILIACION DE PRODUCTOS ELABORADOS
A2: ELABORADO - VENDIDO (Fudo) - CONSUMO INTERNO (Fudo) - DESCARTE DECLARADO = DIFERENCIA SIN EXPLICAR.
A3: OJO: no se lleva stock de producto terminado, asi que la diferencia incluye lo que quedo en exhibicion. Lea la TENDENCIA y los casos grandes, no el numero exacto.
A4: AREA | B4: PRODUCTO | C4: UNID. | D4: ELABORADO (planilla 4) | E4: VENDIDO (Fudo) | F4: CONSUMO INTERNO (Fudo) | G4: DESCARTE (planilla 4) | H4: DESCARTE DETALLADO (planilla 5) | I4: DESCARTE SIN DETALLAR | J4: DIFERENCIA SIN EXPLICAR | K4: % S/ELAB. | L4: ALERTA | M4: k
A6: Panadería | B6: =IF('4 Prod Panaderia'!$A6="","",'4 Prod Panaderia'!$A6) | C6: =IF('4 Prod Panaderia'!$B6="","",'4 Prod Panaderia'!$B6) | D6: ='4 Prod Panaderia'!$Q6 | E6: =IF($B6="","",SUMIFS('8 Fudo Ventas'!$B$6:$B$305,'8 Fudo Ventas'!$D$6:$D$305,$B6,'8 Fudo Ventas'!$C$6:$C$305,$A6)) | F6: =IF($B6="","",SUMIFS('8 Fudo Consumos'!$D$6:$D$255,'8 Fudo Consumos'!$B$6:$B$255,$B6,'8 Fudo Consumos'!$C$6:$C$255,$A6)) | G6: ='4 Prod Panaderia'!$R6 | H6: =IF($B6="","",SUMIFS('5 Descartes'!$D$6:$D$205,'5 Descartes'!$C$6:$C$205,$B6,'5 Descartes'!$B$6:$B$205,$A6)) | I6: =IF($B6="","",$G6-$H6) | J6: =IF($B6="","",$D6-$E6-$F6-$G6) | K6: =IF(OR($B6="",$D6=0),"",$J6/$D6) | L6: =IF($B6="","",IF($D6=0,"Sin produccion registrada",IF($E6=0,"Sin ventas mapeadas en Fudo",IF(AND($K6<>"",ABS($K6)>Config!$B$48),IF($J6>0,"Salida sin explicar: consumo no registrado o faltante","Se vendio mas de lo elaborado: revisar stock previo"),IF($I6<>0,"Hay descarte sin detallar en la planilla 5","OK"))))) | M6: =IF($K6="","",ABS($K6)+ROW()/1000000)
A7: Panadería | B7: =IF('4 Prod Panaderia'!$A7="","",'4 Prod Panaderia'!$A7) | C7: =IF('4 Prod Panaderia'!$B7="","",'4 Prod Panaderia'!$B7) | D7: ='4 Prod Panaderia'!$Q7 | E7: =IF($B7="","",SUMIFS('8 Fudo Ventas'!$B$6:$B$305,'8 Fudo Ventas'!$D$6:$D$305,$B7,'8 Fudo Ventas'!$C$6:$C$305,$A7)) | F7: =IF($B7="","",SUMIFS('8 Fudo Consumos'!$D$6:$D$255,'8 Fudo Consumos'!$B$6:$B$255,$B7,'8 Fudo Consumos'!$C$6:$C$255,$A7)) | G7: ='4 Prod Panaderia'!$R7 | H7: =IF($B7="","",SUMIFS('5 Descartes'!$D$6:$D$205,'5 Descartes'!$C$6:$C$205,$B7,'5 Descartes'!$B$6:$B$205,$A7)) | I7: =IF($B7="","",$G7-$H7) | J7: =IF($B7="","",$D7-$E7-$F7-$G7) | K7: =IF(OR($B7="",$D7=0),"",$J7/$D7) | L7: =IF($B7="","",IF($D7=0,"Sin produccion registrada",IF($E7=0,"Sin ventas mapeadas en Fudo",IF(AND($K7<>"",ABS($K7)>Config!$B$48),IF($J7>0,"Salida sin explicar: consumo no registrado o faltante","Se vendio mas de lo elaborado: revisar stock previo"),IF($I7<>0,"Hay descarte sin detallar en la planilla 5","OK"))))) | M7: =IF($K7="","",ABS($K7)+ROW()/1000000)
A8: Panadería | B8: =IF('4 Prod Panaderia'!$A8="","",'4 Prod Panaderia'!$A8) | C8: =IF('4 Prod Panaderia'!$B8="","",'4 Prod Panaderia'!$B8) | D8: ='4 Prod Panaderia'!$Q8 | E8: =IF($B8="","",SUMIFS('8 Fudo Ventas'!$B$6:$B$305,'8 Fudo Ventas'!$D$6:$D$305,$B8,'8 Fudo Ventas'!$C$6:$C$305,$A8)) | F8: =IF($B8="","",SUMIFS('8 Fudo Consumos'!$D$6:$D$255,'8 Fudo Consumos'!$B$6:$B$255,$B8,'8 Fudo Consumos'!$C$6:$C$255,$A8)) | G8: ='4 Prod Panaderia'!$R8 | H8: =IF($B8="","",SUMIFS('5 Descartes'!$D$6:$D$205,'5 Descartes'!$C$6:$C$205,$B8,'5 Descartes'!$B$6:$B$205,$A8)) | I8: =IF($B8="","",$G8-$H8) | J8: =IF($B8="","",$D8-$E8-$F8-$G8) | K8: =IF(OR($B8="",$D8=0),"",$J8/$D8) | L8: =IF($B8="","",IF($D8=0,"Sin produccion registrada",IF($E8=0,"Sin ventas mapeadas en Fudo",IF(AND($K8<>"",ABS($K8)>Config!$B$48),IF($J8>0,"Salida sin explicar: consumo no registrado o faltante","Se vendio mas de lo elaborado: revisar stock previo"),IF($I8<>0,"Hay descarte sin detallar en la planilla 5","OK"))))) | M8: =IF($K8="","",ABS($K8)+ROW()/1000000)
A9: Panadería | B9: =IF('4 Prod Panaderia'!$A9="","",'4 Prod Panaderia'!$A9) | C9: =IF('4 Prod Panaderia'!$B9="","",'4 Prod Panaderia'!$B9) | D9: ='4 Prod Panaderia'!$Q9 | E9: =IF($B9="","",SUMIFS('8 Fudo Ventas'!$B$6:$B$305,'8 Fudo Ventas'!$D$6:$D$305,$B9,'8 Fudo Ventas'!$C$6:$C$305,$A9)) | F9: =IF($B9="","",SUMIFS('8 Fudo Consumos'!$D$6:$D$255,'8 Fudo Consumos'!$B$6:$B$255,$B9,'8 Fudo Consumos'!$C$6:$C$255,$A9)) | G9: ='4 Prod Panaderia'!$R9 | H9: =IF($B9="","",SUMIFS('5 Descartes'!$D$6:$D$205,'5 Descartes'!$C$6:$C$205,$B9,'5 Descartes'!$B$6:$B$205,$A9)) | I9: =IF($B9="","",$G9-$H9) | J9: =IF($B9="","",$D9-$E9-$F9-$G9) | K9: =IF(OR($B9="",$D9=0),"",$J9/$D9) | L9: =IF($B9="","",IF($D9=0,"Sin produccion registrada",IF($E9=0,"Sin ventas mapeadas en Fudo",IF(AND($K9<>"",ABS($K9)>Config!$B$48),IF($J9>0,"Salida sin explicar: consumo no registrado o faltante","Se vendio mas de lo elaborado: revisar stock previo"),IF($I9<>0,"Hay descarte sin detallar en la planilla 5","OK"))))) | M9: =IF($K9="","",ABS($K9)+ROW()/1000000)
A10: Panadería | B10: =IF('4 Prod Panaderia'!$A10="","",'4 Prod Panaderia'!$A10) | C10: =IF('4 Prod Panaderia'!$B10="","",'4 Prod Panaderia'!$B10) | D10: ='4 Prod Panaderia'!$Q10 | E10: =IF($B10="","",SUMIFS('8 Fudo Ventas'!$B$6:$B$305,'8 Fudo Ventas'!$D$6:$D$305,$B10,'8 Fudo Ventas'!$C$6:$C$305,$A10)) | F10: =IF($B10="","",SUMIFS('8 Fudo Consumos'!$D$6:$D$255,'8 Fudo Consumos'!$B$6:$B$255,$B10,'8 Fudo Consumos'!$C$6:$C$255,$A10)) | G10: ='4 Prod Panaderia'!$R10 | H10: =IF($B10="","",SUMIFS('5 Descartes'!$D$6:$D$205,'5 Descartes'!$C$6:$C$205,$B10,'5 Descartes'!$B$6:$B$205,$A10)) | I10: =IF($B10="","",$G10-$H10) | J10: =IF($B10="","",$D10-$E10-$F10-$G10) | K10: =IF(OR($B10="",$D10=0),"",$J10/$D10) | L10: =IF($B10="","",IF($D10=0,"Sin produccion registrada",IF($E10=0,"Sin ventas mapeadas en Fudo",IF(AND($K10<>"",ABS($K10)>Config!$B$48),IF($J10>0,"Salida sin explicar: consumo no registrado o faltante","Se vendio mas de lo elaborado: revisar stock previo"),IF($I10<>0,"Hay descarte sin detallar en la planilla 5","OK"))))) | M10: =IF($K10="","",ABS($K10)+ROW()/1000000)
A11: Panadería | B11: =IF('4 Prod Panaderia'!$A11="","",'4 Prod Panaderia'!$A11) | C11: =IF('4 Prod Panaderia'!$B11="","",'4 Prod Panaderia'!$B11) | D11: ='4 Prod Panaderia'!$Q11 | E11: =IF($B11="","",SUMIFS('8 Fudo Ventas'!$B$6:$B$305,'8 Fudo Ventas'!$D$6:$D$305,$B11,'8 Fudo Ventas'!$C$6:$C$305,$A11)) | F11: =IF($B11="","",SUMIFS('8 Fudo Consumos'!$D$6:$D$255,'8 Fudo Consumos'!$B$6:$B$255,$B11,'8 Fudo Consumos'!$C$6:$C$255,$A11)) | G11: ='4 Prod Panaderia'!$R11 | H11: =IF($B11="","",SUMIFS('5 Descartes'!$D$6:$D$205,'5 Descartes'!$C$6:$C$205,$B11,'5 Descartes'!$B$6:$B$205,$A11)) | I11: =IF($B11="","",$G11-$H11) | J11: =IF($B11="","",$D11-$E11-$F11-$G11) | K11: =IF(OR($B11="",$D11=0),"",$J11/$D11) | L11: =IF($B11="","",IF($D11=0,"Sin produccion registrada",IF($E11=0,"Sin ventas mapeadas en Fudo",IF(AND($K11<>"",ABS($K11)>Config!$B$48),IF($J11>0,"Salida sin explicar: consumo no registrado o faltante","Se vendio mas de lo elaborado: revisar stock previo"),IF($I11<>0,"Hay descarte sin detallar en la planilla 5","OK"))))) | M11: =IF($K11="","",ABS($K11)+ROW()/1000000)
A12: Panadería | B12: =IF('4 Prod Panaderia'!$A12="","",'4 Prod Panaderia'!$A12) | C12: =IF('4 Prod Panaderia'!$B12="","",'4 Prod Panaderia'!$B12) | D12: ='4 Prod Panaderia'!$Q12 | E12: =IF($B12="","",SUMIFS('8 Fudo Ventas'!$B$6:$B$305,'8 Fudo Ventas'!$D$6:$D$305,$B12,'8 Fudo Ventas'!$C$6:$C$305,$A12)) | F12: =IF($B12="","",SUMIFS('8 Fudo Consumos'!$D$6:$D$255,'8 Fudo Consumos'!$B$6:$B$255,$B12,'8 Fudo Consumos'!$C$6:$C$255,$A12)) | G12: ='4 Prod Panaderia'!$R12 | H12: =IF($B12="","",SUMIFS('5 Descartes'!$D$6:$D$205,'5 Descartes'!$C$6:$C$205,$B12,'5 Descartes'!$B$6:$B$205,$A12)) | I12: =IF($B12="","",$G12-$H12) | J12: =IF($B12="","",$D12-$E12-$F12-$G12) | K12: =IF(OR($B12="",$D12=0),"",$J12/$D12) | L12: =IF($B12="","",IF($D12=0,"Sin produccion registrada",IF($E12=0,"Sin ventas mapeadas en Fudo",IF(AND($K12<>"",ABS($K12)>Config!$B$48),IF($J12>0,"Salida sin explicar: consumo no registrado o faltante","Se vendio mas de lo elaborado: revisar stock previo"),IF($I12<>0,"Hay descarte sin detallar en la planilla 5","OK"))))) | M12: =IF($K12="","",ABS($K12)+ROW()/1000000)
A13: Panadería | B13: =IF('4 Prod Panaderia'!$A13="","",'4 Prod Panaderia'!$A13) | C13: =IF('4 Prod Panaderia'!$B13="","",'4 Prod Panaderia'!$B13) | D13: ='4 Prod Panaderia'!$Q13 | E13: =IF($B13="","",SUMIFS('8 Fudo Ventas'!$B$6:$B$305,'8 Fudo Ventas'!$D$6:$D$305,$B13,'8 Fudo Ventas'!$C$6:$C$305,$A13)) | F13: =IF($B13="","",SUMIFS('8 Fudo Consumos'!$D$6:$D$255,'8 Fudo Consumos'!$B$6:$B$255,$B13,'8 Fudo Consumos'!$C$6:$C$255,$A13)) | G13: ='4 Prod Panaderia'!$R13 | H13: =IF($B13="","",SUMIFS('5 Descartes'!$D$6:$D$205,'5 Descartes'!$C$6:$C$205,$B13,'5 Descartes'!$B$6:$B$205,$A13)) | I13: =IF($B13="","",$G13-$H13) | J13: =IF($B13="","",$D13-$E13-$F13-$G13) | K13: =IF(OR($B13="",$D13=0),"",$J13/$D13) | L13: =IF($B13="","",IF($D13=0,"Sin produccion registrada",IF($E13=0,"Sin ventas mapeadas en Fudo",IF(AND($K13<>"",ABS($K13)>Config!$B$48),IF($J13>0,"Salida sin explicar: consumo no registrado o faltante","Se vendio mas de lo elaborado: revisar stock previo"),IF($I13<>0,"Hay descarte sin detallar en la planilla 5","OK"))))) | M13: =IF($K13="","",ABS($K13)+ROW()/1000000)
A14: Panadería | B14: =IF('4 Prod Panaderia'!$A14="","",'4 Prod Panaderia'!$A14) | C14: =IF('4 Prod Panaderia'!$B14="","",'4 Prod Panaderia'!$B14) | D14: ='4 Prod Panaderia'!$Q14 | E14: =IF($B14="","",SUMIFS('8 Fudo Ventas'!$B$6:$B$305,'8 Fudo Ventas'!$D$6:$D$305,$B14,'8 Fudo Ventas'!$C$6:$C$305,$A14)) | F14: =IF($B14="","",SUMIFS('8 Fudo Consumos'!$D$6:$D$255,'8 Fudo Consumos'!$B$6:$B$255,$B14,'8 Fudo Consumos'!$C$6:$C$255,$A14)) | G14: ='4 Prod Panaderia'!$R14 | H14: =IF($B14="","",SUMIFS('5 Descartes'!$D$6:$D$205,'5 Descartes'!$C$6:$C$205,$B14,'5 Descartes'!$B$6:$B$205,$A14)) | I14: =IF($B14="","",$G14-$H14) | J14: =IF($B14="","",$D14-$E14-$F14-$G14) | K14: =IF(OR($B14="",$D14=0),"",$J14/$D14) | L14: =IF($B14="","",IF($D14=0,"Sin produccion registrada",IF($E14=0,"Sin ventas mapeadas en Fudo",IF(AND($K14<>"",ABS($K14)>Config!$B$48),IF($J14>0,"Salida sin explicar: consumo no registrado o faltante","Se vendio mas de lo elaborado: revisar stock previo"),IF($I14<>0,"Hay descarte sin detallar en la planilla 5","OK"))))) | M14: =IF($K14="","",ABS($K14)+ROW()/1000000)
A15: Panadería | B15: =IF('4 Prod Panaderia'!$A15="","",'4 Prod Panaderia'!$A15) | C15: =IF('4 Prod Panaderia'!$B15="","",'4 Prod Panaderia'!$B15) | D15: ='4 Prod Panaderia'!$Q15 | E15: =IF($B15="","",SUMIFS('8 Fudo Ventas'!$B$6:$B$305,'8 Fudo Ventas'!$D$6:$D$305,$B15,'8 Fudo Ventas'!$C$6:$C$305,$A15)) | F15: =IF($B15="","",SUMIFS('8 Fudo Consumos'!$D$6:$D$255,'8 Fudo Consumos'!$B$6:$B$255,$B15,'8 Fudo Consumos'!$C$6:$C$255,$A15)) | G15: ='4 Prod Panaderia'!$R15 | H15: =IF($B15="","",SUMIFS('5 Descartes'!$D$6:$D$205,'5 Descartes'!$C$6:$C$205,$B15,'5 Descartes'!$B$6:$B$205,$A15)) | I15: =IF($B15="","",$G15-$H15) | J15: =IF($B15="","",$D15-$E15-$F15-$G15) | K15: =IF(OR($B15="",$D15=0),"",$J15/$D15) | L15: =IF($B15="","",IF($D15=0,"Sin produccion registrada",IF($E15=0,"Sin ventas mapeadas en Fudo",IF(AND($K15<>"",ABS($K15)>Config!$B$48),IF($J15>0,"Salida sin explicar: consumo no registrado o faltante","Se vendio mas de lo elaborado: revisar stock previo"),IF($I15<>0,"Hay descarte sin detallar en la planilla 5","OK"))))) | M15: =IF($K15="","",ABS($K15)+ROW()/1000000)
A16: Panadería | B16: =IF('4 Prod Panaderia'!$A16="","",'4 Prod Panaderia'!$A16) | C16: =IF('4 Prod Panaderia'!$B16="","",'4 Prod Panaderia'!$B16) | D16: ='4 Prod Panaderia'!$Q16 | E16: =IF($B16="","",SUMIFS('8 Fudo Ventas'!$B$6:$B$305,'8 Fudo Ventas'!$D$6:$D$305,$B16,'8 Fudo Ventas'!$C$6:$C$305,$A16)) | F16: =IF($B16="","",SUMIFS('8 Fudo Consumos'!$D$6:$D$255,'8 Fudo Consumos'!$B$6:$B$255,$B16,'8 Fudo Consumos'!$C$6:$C$255,$A16)) | G16: ='4 Prod Panaderia'!$R16 | H16: =IF($B16="","",SUMIFS('5 Descartes'!$D$6:$D$205,'5 Descartes'!$C$6:$C$205,$B16,'5 Descartes'!$B$6:$B$205,$A16)) | I16: =IF($B16="","",$G16-$H16) | J16: =IF($B16="","",$D16-$E16-$F16-$G16) | K16: =IF(OR($B16="",$D16=0),"",$J16/$D16) | L16: =IF($B16="","",IF($D16=0,"Sin produccion registrada",IF($E16=0,"Sin ventas mapeadas en Fudo",IF(AND($K16<>"",ABS($K16)>Config!$B$48),IF($J16>0,"Salida sin explicar: consumo no registrado o faltante","Se vendio mas de lo elaborado: revisar stock previo"),IF($I16<>0,"Hay descarte sin detallar en la planilla 5","OK"))))) | M16: =IF($K16="","",ABS($K16)+ROW()/1000000)
A17: Panadería | B17: =IF('4 Prod Panaderia'!$A17="","",'4 Prod Panaderia'!$A17) | C17: =IF('4 Prod Panaderia'!$B17="","",'4 Prod Panaderia'!$B17) | D17: ='4 Prod Panaderia'!$Q17 | E17: =IF($B17="","",SUMIFS('8 Fudo Ventas'!$B$6:$B$305,'8 Fudo Ventas'!$D$6:$D$305,$B17,'8 Fudo Ventas'!$C$6:$C$305,$A17)) | F17: =IF($B17="","",SUMIFS('8 Fudo Consumos'!$D$6:$D$255,'8 Fudo Consumos'!$B$6:$B$255,$B17,'8 Fudo Consumos'!$C$6:$C$255,$A17)) | G17: ='4 Prod Panaderia'!$R17 | H17: =IF($B17="","",SUMIFS('5 Descartes'!$D$6:$D$205,'5 Descartes'!$C$6:$C$205,$B17,'5 Descartes'!$B$6:$B$205,$A17)) | I17: =IF($B17="","",$G17-$H17) | J17: =IF($B17="","",$D17-$E17-$F17-$G17) | K17: =IF(OR($B17="",$D17=0),"",$J17/$D17) | L17: =IF($B17="","",IF($D17=0,"Sin produccion registrada",IF($E17=0,"Sin ventas mapeadas en Fudo",IF(AND($K17<>"",ABS($K17)>Config!$B$48),IF($J17>0,"Salida sin explicar: consumo no registrado o faltante","Se vendio mas de lo elaborado: revisar stock previo"),IF($I17<>0,"Hay descarte sin detallar en la planilla 5","OK"))))) | M17: =IF($K17="","",ABS($K17)+ROW()/1000000)
... A55: Panadería | B55: =IF('4 Prod Panaderia'!$A55="","",'4 Prod Panaderia'!$A55) | C55: =IF('4 Prod Panaderia'!$B55="","",'4 Prod Panaderia'!$B55) | D55: ='4 Prod Panaderia'!$Q55 | E55: =IF($B55="","",SUMIFS('8 Fudo Ventas'!$B$6:$B$305,'8 Fudo Ventas'!$D$6:$D$305,$B55,'8 Fudo Ventas'!$C$6:$C$305,$A55)) | F55: =IF($B55="","",SUMIFS('8 Fudo Consumos'!$D$6:$D$255,'8 Fudo Consumos'!$B$6:$B$255,$B55,'8 Fudo Consumos'!$C$6:$C$255,$A55)) | G55: ='4 Prod Panaderia'!$R55 | H55: =IF($B55="","",SUMIFS('5 Descartes'!$D$6:$D$205,'5 Descartes'!$C$6:$C$205,$B55,'5 Descartes'!$B$6:$B$205,$A55)) | I55: =IF($B55="","",$G55-$H55) | J55: =IF($B55="","",$D55-$E55-$F55-$G55) | K55: =IF(OR($B55="",$D55=0),"",$J55/$D55) | L55: =IF($B55="","",IF($D55=0,"Sin produccion registrada",IF($E55=0,"Sin ventas mapeadas en Fudo",IF(AND($K55<>"",ABS($K55)>Config!$B$48),IF($J55>0,"Salida sin explicar: consumo no registrado o faltante","Se vendio mas de lo elaborado: revisar stock previo"),IF($I55<>0,"Hay descarte sin detallar en la planilla 5","OK"))))) | M55: =IF($K55="","",ABS($K55)+ROW()/1000000)
A56: Pastelería | B56: =IF('4 Prod Pasteleria'!$A6="","",'4 Prod Pasteleria'!$A6) | C56: =IF('4 Prod Pasteleria'!$B6="","",'4 Prod Pasteleria'!$B6) | D56: ='4 Prod Pasteleria'!$Q6 | E56: =IF($B56="","",SUMIFS('8 Fudo Ventas'!$B$6:$B$305,'8 Fudo Ventas'!$D$6:$D$305,$B56,'8 Fudo Ventas'!$C$6:$C$305,$A56)) | F56: =IF($B56="","",SUMIFS('8 Fudo Consumos'!$D$6:$D$255,'8 Fudo Consumos'!$B$6:$B$255,$B56,'8 Fudo Consumos'!$C$6:$C$255,$A56)) | G56: ='4 Prod Pasteleria'!$R6 | H56: =IF($B56="","",SUMIFS('5 Descartes'!$D$6:$D$205,'5 Descartes'!$C$6:$C$205,$B56,'5 Descartes'!$B$6:$B$205,$A56)) | I56: =IF($B56="","",$G56-$H56) | J56: =IF($B56="","",$D56-$E56-$F56-$G56) | K56: =IF(OR($B56="",$D56=0),"",$J56/$D56) | L56: =IF($B56="","",IF($D56=0,"Sin produccion registrada",IF($E56=0,"Sin ventas mapeadas en Fudo",IF(AND($K56<>"",ABS($K56)>Config!$B$48),IF($J56>0,"Salida sin explicar: consumo no registrado o faltante","Se vendio mas de lo elaborado: revisar stock previo"),IF($I56<>0,"Hay descarte sin detallar en la planilla 5","OK"))))) | M56: =IF($K56="","",ABS($K56)+ROW()/1000000)
A57: Pastelería | B57: =IF('4 Prod Pasteleria'!$A7="","",'4 Prod Pasteleria'!$A7) | C57: =IF('4 Prod Pasteleria'!$B7="","",'4 Prod Pasteleria'!$B7) | D57: ='4 Prod Pasteleria'!$Q7 | E57: =IF($B57="","",SUMIFS('8 Fudo Ventas'!$B$6:$B$305,'8 Fudo Ventas'!$D$6:$D$305,$B57,'8 Fudo Ventas'!$C$6:$C$305,$A57)) | F57: =IF($B57="","",SUMIFS('8 Fudo Consumos'!$D$6:$D$255,'8 Fudo Consumos'!$B$6:$B$255,$B57,'8 Fudo Consumos'!$C$6:$C$255,$A57)) | G57: ='4 Prod Pasteleria'!$R7 | H57: =IF($B57="","",SUMIFS('5 Descartes'!$D$6:$D$205,'5 Descartes'!$C$6:$C$205,$B57,'5 Descartes'!$B$6:$B$205,$A57)) | I57: =IF($B57="","",$G57-$H57) | J57: =IF($B57="","",$D57-$E57-$F57-$G57) | K57: =IF(OR($B57="",$D57=0),"",$J57/$D57) | L57: =IF($B57="","",IF($D57=0,"Sin produccion registrada",IF($E57=0,"Sin ventas mapeadas en Fudo",IF(AND($K57<>"",ABS($K57)>Config!$B$48),IF($J57>0,"Salida sin explicar: consumo no registrado o faltante","Se vendio mas de lo elaborado: revisar stock previo"),IF($I57<>0,"Hay descarte sin detallar en la planilla 5","OK"))))) | M57: =IF($K57="","",ABS($K57)+ROW()/1000000)
A58: Pastelería | B58: =IF('4 Prod Pasteleria'!$A8="","",'4 Prod Pasteleria'!$A8) | C58: =IF('4 Prod Pasteleria'!$B8="","",'4 Prod Pasteleria'!$B8) | D58: ='4 Prod Pasteleria'!$Q8 | E58: =IF($B58="","",SUMIFS('8 Fudo Ventas'!$B$6:$B$305,'8 Fudo Ventas'!$D$6:$D$305,$B58,'8 Fudo Ventas'!$C$6:$C$305,$A58)) | F58: =IF($B58="","",SUMIFS('8 Fudo Consumos'!$D$6:$D$255,'8 Fudo Consumos'!$B$6:$B$255,$B58,'8 Fudo Consumos'!$C$6:$C$255,$A58)) | G58: ='4 Prod Pasteleria'!$R8 | H58: =IF($B58="","",SUMIFS('5 Descartes'!$D$6:$D$205,'5 Descartes'!$C$6:$C$205,$B58,'5 Descartes'!$B$6:$B$205,$A58)) | I58: =IF($B58="","",$G58-$H58) | J58: =IF($B58="","",$D58-$E58-$F58-$G58) | K58: =IF(OR($B58="",$D58=0),"",$J58/$D58) | L58: =IF($B58="","",IF($D58=0,"Sin produccion registrada",IF($E58=0,"Sin ventas mapeadas en Fudo",IF(AND($K58<>"",ABS($K58)>Config!$B$48),IF($J58>0,"Salida sin explicar: consumo no registrado o faltante","Se vendio mas de lo elaborado: revisar stock previo"),IF($I58<>0,"Hay descarte sin detallar en la planilla 5","OK"))))) | M58: =IF($K58="","",ABS($K58)+ROW()/1000000)
A59: Pastelería | B59: =IF('4 Prod Pasteleria'!$A9="","",'4 Prod Pasteleria'!$A9) | C59: =IF('4 Prod Pasteleria'!$B9="","",'4 Prod Pasteleria'!$B9) | D59: ='4 Prod Pasteleria'!$Q9 | E59: =IF($B59="","",SUMIFS('8 Fudo Ventas'!$B$6:$B$305,'8 Fudo Ventas'!$D$6:$D$305,$B59,'8 Fudo Ventas'!$C$6:$C$305,$A59)) | F59: =IF($B59="","",SUMIFS('8 Fudo Consumos'!$D$6:$D$255,'8 Fudo Consumos'!$B$6:$B$255,$B59,'8 Fudo Consumos'!$C$6:$C$255,$A59)) | G59: ='4 Prod Pasteleria'!$R9 | H59: =IF($B59="","",SUMIFS('5 Descartes'!$D$6:$D$205,'5 Descartes'!$C$6:$C$205,$B59,'5 Descartes'!$B$6:$B$205,$A59)) | I59: =IF($B59="","",$G59-$H59) | J59: =IF($B59="","",$D59-$E59-$F59-$G59) | K59: =IF(OR($B59="",$D59=0),"",$J59/$D59) | L59: =IF($B59="","",IF($D59=0,"Sin produccion registrada",IF($E59=0,"Sin ventas mapeadas en Fudo",IF(AND($K59<>"",ABS($K59)>Config!$B$48),IF($J59>0,"Salida sin explicar: consumo no registrado o faltante","Se vendio mas de lo elaborado: revisar stock previo"),IF($I59<>0,"Hay descarte sin detallar en la planilla 5","OK"))))) | M59: =IF($K59="","",ABS($K59)+ROW()/1000000)
A60: Pastelería | B60: =IF('4 Prod Pasteleria'!$A10="","",'4 Prod Pasteleria'!$A10) | C60: =IF('4 Prod Pasteleria'!$B10="","",'4 Prod Pasteleria'!$B10) | D60: ='4 Prod Pasteleria'!$Q10 | E60: =IF($B60="","",SUMIFS('8 Fudo Ventas'!$B$6:$B$305,'8 Fudo Ventas'!$D$6:$D$305,$B60,'8 Fudo Ventas'!$C$6:$C$305,$A60)) | F60: =IF($B60="","",SUMIFS('8 Fudo Consumos'!$D$6:$D$255,'8 Fudo Consumos'!$B$6:$B$255,$B60,'8 Fudo Consumos'!$C$6:$C$255,$A60)) | G60: ='4 Prod Pasteleria'!$R10 | H60: =IF($B60="","",SUMIFS('5 Descartes'!$D$6:$D$205,'5 Descartes'!$C$6:$C$205,$B60,'5 Descartes'!$B$6:$B$205,$A60)) | I60: =IF($B60="","",$G60-$H60) | J60: =IF($B60="","",$D60-$E60-$F60-$G60) | K60: =IF(OR($B60="",$D60=0),"",$J60/$D60) | L60: =IF($B60="","",IF($D60=0,"Sin produccion registrada",IF($E60=0,"Sin ventas mapeadas en Fudo",IF(AND($K60<>"",ABS($K60)>Config!$B$48),IF($J60>0,"Salida sin explicar: consumo no registrado o faltante","Se vendio mas de lo elaborado: revisar stock previo"),IF($I60<>0,"Hay descarte sin detallar en la planilla 5","OK"))))) | M60: =IF($K60="","",ABS($K60)+ROW()/1000000)
A61: Pastelería | B61: =IF('4 Prod Pasteleria'!$A11="","",'4 Prod Pasteleria'!$A11) | C61: =IF('4 Prod Pasteleria'!$B11="","",'4 Prod Pasteleria'!$B11) | D61: ='4 Prod Pasteleria'!$Q11 | E61: =IF($B61="","",SUMIFS('8 Fudo Ventas'!$B$6:$B$305,'8 Fudo Ventas'!$D$6:$D$305,$B61,'8 Fudo Ventas'!$C$6:$C$305,$A61)) | F61: =IF($B61="","",SUMIFS('8 Fudo Consumos'!$D$6:$D$255,'8 Fudo Consumos'!$B$6:$B$255,$B61,'8 Fudo Consumos'!$C$6:$C$255,$A61)) | G61: ='4 Prod Pasteleria'!$R11 | H61: =IF($B61="","",SUMIFS('5 Descartes'!$D$6:$D$205,'5 Descartes'!$C$6:$C$205,$B61,'5 Descartes'!$B$6:$B$205,$A61)) | I61: =IF($B61="","",$G61-$H61) | J61: =IF($B61="","",$D61-$E61-$F61-$G61) | K61: =IF(OR($B61="",$D61=0),"",$J61/$D61) | L61: =IF($B61="","",IF($D61=0,"Sin produccion registrada",IF($E61=0,"Sin ventas mapeadas en Fudo",IF(AND($K61<>"",ABS($K61)>Config!$B$48),IF($J61>0,"Salida sin explicar: consumo no registrado o faltante","Se vendio mas de lo elaborado: revisar stock previo"),IF($I61<>0,"Hay descarte sin detallar en la planilla 5","OK"))))) | M61: =IF($K61="","",ABS($K61)+ROW()/1000000)
A62: Pastelería | B62: =IF('4 Prod Pasteleria'!$A12="","",'4 Prod Pasteleria'!$A12) | C62: =IF('4 Prod Pasteleria'!$B12="","",'4 Prod Pasteleria'!$B12) | D62: ='4 Prod Pasteleria'!$Q12 | E62: =IF($B62="","",SUMIFS('8 Fudo Ventas'!$B$6:$B$305,'8 Fudo Ventas'!$D$6:$D$305,$B62,'8 Fudo Ventas'!$C$6:$C$305,$A62)) | F62: =IF($B62="","",SUMIFS('8 Fudo Consumos'!$D$6:$D$255,'8 Fudo Consumos'!$B$6:$B$255,$B62,'8 Fudo Consumos'!$C$6:$C$255,$A62)) | G62: ='4 Prod Pasteleria'!$R12 | H62: =IF($B62="","",SUMIFS('5 Descartes'!$D$6:$D$205,'5 Descartes'!$C$6:$C$205,$B62,'5 Descartes'!$B$6:$B$205,$A62)) | I62: =IF($B62="","",$G62-$H62) | J62: =IF($B62="","",$D62-$E62-$F62-$G62) | K62: =IF(OR($B62="",$D62=0),"",$J62/$D62) | L62: =IF($B62="","",IF($D62=0,"Sin produccion registrada",IF($E62=0,"Sin ventas mapeadas en Fudo",IF(AND($K62<>"",ABS($K62)>Config!$B$48),IF($J62>0,"Salida sin explicar: consumo no registrado o faltante","Se vendio mas de lo elaborado: revisar stock previo"),IF($I62<>0,"Hay descarte sin detallar en la planilla 5","OK"))))) | M62: =IF($K62="","",ABS($K62)+ROW()/1000000)
A63: Pastelería | B63: =IF('4 Prod Pasteleria'!$A13="","",'4 Prod Pasteleria'!$A13) | C63: =IF('4 Prod Pasteleria'!$B13="","",'4 Prod Pasteleria'!$B13) | D63: ='4 Prod Pasteleria'!$Q13 | E63: =IF($B63="","",SUMIFS('8 Fudo Ventas'!$B$6:$B$305,'8 Fudo Ventas'!$D$6:$D$305,$B63,'8 Fudo Ventas'!$C$6:$C$305,$A63)) | F63: =IF($B63="","",SUMIFS('8 Fudo Consumos'!$D$6:$D$255,'8 Fudo Consumos'!$B$6:$B$255,$B63,'8 Fudo Consumos'!$C$6:$C$255,$A63)) | G63: ='4 Prod Pasteleria'!$R13 | H63: =IF($B63="","",SUMIFS('5 Descartes'!$D$6:$D$205,'5 Descartes'!$C$6:$C$205,$B63,'5 Descartes'!$B$6:$B$205,$A63)) | I63: =IF($B63="","",$G63-$H63) | J63: =IF($B63="","",$D63-$E63-$F63-$G63) | K63: =IF(OR($B63="",$D63=0),"",$J63/$D63) | L63: =IF($B63="","",IF($D63=0,"Sin produccion registrada",IF($E63=0,"Sin ventas mapeadas en Fudo",IF(AND($K63<>"",ABS($K63)>Config!$B$48),IF($J63>0,"Salida sin explicar: consumo no registrado o faltante","Se vendio mas de lo elaborado: revisar stock previo"),IF($I63<>0,"Hay descarte sin detallar en la planilla 5","OK"))))) | M63: =IF($K63="","",ABS($K63)+ROW()/1000000)
A64: Pastelería | B64: =IF('4 Prod Pasteleria'!$A14="","",'4 Prod Pasteleria'!$A14) | C64: =IF('4 Prod Pasteleria'!$B14="","",'4 Prod Pasteleria'!$B14) | D64: ='4 Prod Pasteleria'!$Q14 | E64: =IF($B64="","",SUMIFS('8 Fudo Ventas'!$B$6:$B$305,'8 Fudo Ventas'!$D$6:$D$305,$B64,'8 Fudo Ventas'!$C$6:$C$305,$A64)) | F64: =IF($B64="","",SUMIFS('8 Fudo Consumos'!$D$6:$D$255,'8 Fudo Consumos'!$B$6:$B$255,$B64,'8 Fudo Consumos'!$C$6:$C$255,$A64)) | G64: ='4 Prod Pasteleria'!$R14 | H64: =IF($B64="","",SUMIFS('5 Descartes'!$D$6:$D$205,'5 Descartes'!$C$6:$C$205,$B64,'5 Descartes'!$B$6:$B$205,$A64)) | I64: =IF($B64="","",$G64-$H64) | J64: =IF($B64="","",$D64-$E64-$F64-$G64) | K64: =IF(OR($B64="",$D64=0),"",$J64/$D64) | L64: =IF($B64="","",IF($D64=0,"Sin produccion registrada",IF($E64=0,"Sin ventas mapeadas en Fudo",IF(AND($K64<>"",ABS($K64)>Config!$B$48),IF($J64>0,"Salida sin explicar: consumo no registrado o faltante","Se vendio mas de lo elaborado: revisar stock previo"),IF($I64<>0,"Hay descarte sin detallar en la planilla 5","OK"))))) | M64: =IF($K64="","",ABS($K64)+ROW()/1000000)
A65: Pastelería | B65: =IF('4 Prod Pasteleria'!$A15="","",'4 Prod Pasteleria'!$A15) | C65: =IF('4 Prod Pasteleria'!$B15="","",'4 Prod Pasteleria'!$B15) | D65: ='4 Prod Pasteleria'!$Q15 | E65: =IF($B65="","",SUMIFS('8 Fudo Ventas'!$B$6:$B$305,'8 Fudo Ventas'!$D$6:$D$305,$B65,'8 Fudo Ventas'!$C$6:$C$305,$A65)) | F65: =IF($B65="","",SUMIFS('8 Fudo Consumos'!$D$6:$D$255,'8 Fudo Consumos'!$B$6:$B$255,$B65,'8 Fudo Consumos'!$C$6:$C$255,$A65)) | G65: ='4 Prod Pasteleria'!$R15 | H65: =IF($B65="","",SUMIFS('5 Descartes'!$D$6:$D$205,'5 Descartes'!$C$6:$C$205,$B65,'5 Descartes'!$B$6:$B$205,$A65)) | I65: =IF($B65="","",$G65-$H65) | J65: =IF($B65="","",$D65-$E65-$F65-$G65) | K65: =IF(OR($B65="",$D65=0),"",$J65/$D65) | L65: =IF($B65="","",IF($D65=0,"Sin produccion registrada",IF($E65=0,"Sin ventas mapeadas en Fudo",IF(AND($K65<>"",ABS($K65)>Config!$B$48),IF($J65>0,"Salida sin explicar: consumo no registrado o faltante","Se vendio mas de lo elaborado: revisar stock previo"),IF($I65<>0,"Hay descarte sin detallar en la planilla 5","OK"))))) | M65: =IF($K65="","",ABS($K65)+ROW()/1000000)
A66: Pastelería | B66: =IF('4 Prod Pasteleria'!$A16="","",'4 Prod Pasteleria'!$A16) | C66: =IF('4 Prod Pasteleria'!$B16="","",'4 Prod Pasteleria'!$B16) | D66: ='4 Prod Pasteleria'!$Q16 | E66: =IF($B66="","",SUMIFS('8 Fudo Ventas'!$B$6:$B$305,'8 Fudo Ventas'!$D$6:$D$305,$B66,'8 Fudo Ventas'!$C$6:$C$305,$A66)) | F66: =IF($B66="","",SUMIFS('8 Fudo Consumos'!$D$6:$D$255,'8 Fudo Consumos'!$B$6:$B$255,$B66,'8 Fudo Consumos'!$C$6:$C$255,$A66)) | G66: ='4 Prod Pasteleria'!$R16 | H66: =IF($B66="","",SUMIFS('5 Descartes'!$D$6:$D$205,'5 Descartes'!$C$6:$C$205,$B66,'5 Descartes'!$B$6:$B$205,$A66)) | I66: =IF($B66="","",$G66-$H66) | J66: =IF($B66="","",$D66-$E66-$F66-$G66) | K66: =IF(OR($B66="",$D66=0),"",$J66/$D66) | L66: =IF($B66="","",IF($D66=0,"Sin produccion registrada",IF($E66=0,"Sin ventas mapeadas en Fudo",IF(AND($K66<>"",ABS($K66)>Config!$B$48),IF($J66>0,"Salida sin explicar: consumo no registrado o faltante","Se vendio mas de lo elaborado: revisar stock previo"),IF($I66<>0,"Hay descarte sin detallar en la planilla 5","OK"))))) | M66: =IF($K66="","",ABS($K66)+ROW()/1000000)
A67: Pastelería | B67: =IF('4 Prod Pasteleria'!$A17="","",'4 Prod Pasteleria'!$A17) | C67: =IF('4 Prod Pasteleria'!$B17="","",'4 Prod Pasteleria'!$B17) | D67: ='4 Prod Pasteleria'!$Q17 | E67: =IF($B67="","",SUMIFS('8 Fudo Ventas'!$B$6:$B$305,'8 Fudo Ventas'!$D$6:$D$305,$B67,'8 Fudo Ventas'!$C$6:$C$305,$A67)) | F67: =IF($B67="","",SUMIFS('8 Fudo Consumos'!$D$6:$D$255,'8 Fudo Consumos'!$B$6:$B$255,$B67,'8 Fudo Consumos'!$C$6:$C$255,$A67)) | G67: ='4 Prod Pasteleria'!$R17 | H67: =IF($B67="","",SUMIFS('5 Descartes'!$D$6:$D$205,'5 Descartes'!$C$6:$C$205,$B67,'5 Descartes'!$B$6:$B$205,$A67)) | I67: =IF($B67="","",$G67-$H67) | J67: =IF($B67="","",$D67-$E67-$F67-$G67) | K67: =IF(OR($B67="",$D67=0),"",$J67/$D67) | L67: =IF($B67="","",IF($D67=0,"Sin produccion registrada",IF($E67=0,"Sin ventas mapeadas en Fudo",IF(AND($K67<>"",ABS($K67)>Config!$B$48),IF($J67>0,"Salida sin explicar: consumo no registrado o faltante","Se vendio mas de lo elaborado: revisar stock previo"),IF($I67<>0,"Hay descarte sin detallar en la planilla 5","OK"))))) | M67: =IF($K67="","",ABS($K67)+ROW()/1000000)
... A101: Pastelería | B101: =IF('4 Prod Pasteleria'!$A51="","",'4 Prod Pasteleria'!$A51) | C101: =IF('4 Prod Pasteleria'!$B51="","",'4 Prod Pasteleria'!$B51) | D101: ='4 Prod Pasteleria'!$Q51 | E101: =IF($B101="","",SUMIFS('8 Fudo Ventas'!$B$6:$B$305,'8 Fudo Ventas'!$D$6:$D$305,$B101,'8 Fudo Ventas'!$C$6:$C$305,$A101)) | F101: =IF($B101="","",SUMIFS('8 Fudo Consumos'!$D$6:$D$255,'8 Fudo Consumos'!$B$6:$B$255,$B101,'8 Fudo Consumos'!$C$6:$C$255,$A101)) | G101: ='4 Prod Pasteleria'!$R51 | H101: =IF($B101="","",SUMIFS('5 Descartes'!$D$6:$D$205,'5 Descartes'!$C$6:$C$205,$B101,'5 Descartes'!$B$6:$B$205,$A101)) | I101: =IF($B101="","",$G101-$H101) | J101: =IF($B101="","",$D101-$E101-$F101-$G101) | K101: =IF(OR($B101="",$D101=0),"",$J101/$D101) | L101: =IF($B101="","",IF($D101=0,"Sin produccion registrada",IF($E101=0,"Sin ventas mapeadas en Fudo",IF(AND($K101<>"",ABS($K101)>Config!$B$48),IF($J101>0,"Salida sin explicar: consumo no registrado o faltante","Se vendio mas de lo elaborado: revisar stock previo"),IF($I101<>0,"Hay descarte sin detallar en la planilla 5","OK"))))) | M101: =IF($K101="","",ABS($K101)+ROW()/1000000)
A102: Especialidades | B102: =IF('4 Prod Especialidades'!$A6="","",'4 Prod Especialidades'!$A6) | C102: =IF('4 Prod Especialidades'!$B6="","",'4 Prod Especialidades'!$B6) | D102: ='4 Prod Especialidades'!$Q6 | E102: =IF($B102="","",SUMIFS('8 Fudo Ventas'!$B$6:$B$305,'8 Fudo Ventas'!$D$6:$D$305,$B102,'8 Fudo Ventas'!$C$6:$C$305,$A102)) | F102: =IF($B102="","",SUMIFS('8 Fudo Consumos'!$D$6:$D$255,'8 Fudo Consumos'!$B$6:$B$255,$B102,'8 Fudo Consumos'!$C$6:$C$255,$A102)) | G102: ='4 Prod Especialidades'!$R6 | H102: =IF($B102="","",SUMIFS('5 Descartes'!$D$6:$D$205,'5 Descartes'!$C$6:$C$205,$B102,'5 Descartes'!$B$6:$B$205,$A102)) | I102: =IF($B102="","",$G102-$H102) | J102: =IF($B102="","",$D102-$E102-$F102-$G102) | K102: =IF(OR($B102="",$D102=0),"",$J102/$D102) | L102: =IF($B102="","",IF($D102=0,"Sin produccion registrada",IF($E102=0,"Sin ventas mapeadas en Fudo",IF(AND($K102<>"",ABS($K102)>Config!$B$48),IF($J102>0,"Salida sin explicar: consumo no registrado o faltante","Se vendio mas de lo elaborado: revisar stock previo"),IF($I102<>0,"Hay descarte sin detallar en la planilla 5","OK"))))) | M102: =IF($K102="","",ABS($K102)+ROW()/1000000)
A103: Especialidades | B103: =IF('4 Prod Especialidades'!$A7="","",'4 Prod Especialidades'!$A7) | C103: =IF('4 Prod Especialidades'!$B7="","",'4 Prod Especialidades'!$B7) | D103: ='4 Prod Especialidades'!$Q7 | E103: =IF($B103="","",SUMIFS('8 Fudo Ventas'!$B$6:$B$305,'8 Fudo Ventas'!$D$6:$D$305,$B103,'8 Fudo Ventas'!$C$6:$C$305,$A103)) | F103: =IF($B103="","",SUMIFS('8 Fudo Consumos'!$D$6:$D$255,'8 Fudo Consumos'!$B$6:$B$255,$B103,'8 Fudo Consumos'!$C$6:$C$255,$A103)) | G103: ='4 Prod Especialidades'!$R7 | H103: =IF($B103="","",SUMIFS('5 Descartes'!$D$6:$D$205,'5 Descartes'!$C$6:$C$205,$B103,'5 Descartes'!$B$6:$B$205,$A103)) | I103: =IF($B103="","",$G103-$H103) | J103: =IF($B103="","",$D103-$E103-$F103-$G103) | K103: =IF(OR($B103="",$D103=0),"",$J103/$D103) | L103: =IF($B103="","",IF($D103=0,"Sin produccion registrada",IF($E103=0,"Sin ventas mapeadas en Fudo",IF(AND($K103<>"",ABS($K103)>Config!$B$48),IF($J103>0,"Salida sin explicar: consumo no registrado o faltante","Se vendio mas de lo elaborado: revisar stock previo"),IF($I103<>0,"Hay descarte sin detallar en la planilla 5","OK"))))) | M103: =IF($K103="","",ABS($K103)+ROW()/1000000)
A104: Especialidades | B104: =IF('4 Prod Especialidades'!$A8="","",'4 Prod Especialidades'!$A8) | C104: =IF('4 Prod Especialidades'!$B8="","",'4 Prod Especialidades'!$B8) | D104: ='4 Prod Especialidades'!$Q8 | E104: =IF($B104="","",SUMIFS('8 Fudo Ventas'!$B$6:$B$305,'8 Fudo Ventas'!$D$6:$D$305,$B104,'8 Fudo Ventas'!$C$6:$C$305,$A104)) | F104: =IF($B104="","",SUMIFS('8 Fudo Consumos'!$D$6:$D$255,'8 Fudo Consumos'!$B$6:$B$255,$B104,'8 Fudo Consumos'!$C$6:$C$255,$A104)) | G104: ='4 Prod Especialidades'!$R8 | H104: =IF($B104="","",SUMIFS('5 Descartes'!$D$6:$D$205,'5 Descartes'!$C$6:$C$205,$B104,'5 Descartes'!$B$6:$B$205,$A104)) | I104: =IF($B104="","",$G104-$H104) | J104: =IF($B104="","",$D104-$E104-$F104-$G104) | K104: =IF(OR($B104="",$D104=0),"",$J104/$D104) | L104: =IF($B104="","",IF($D104=0,"Sin produccion registrada",IF($E104=0,"Sin ventas mapeadas en Fudo",IF(AND($K104<>"",ABS($K104)>Config!$B$48),IF($J104>0,"Salida sin explicar: consumo no registrado o faltante","Se vendio mas de lo elaborado: revisar stock previo"),IF($I104<>0,"Hay descarte sin detallar en la planilla 5","OK"))))) | M104: =IF($K104="","",ABS($K104)+ROW()/1000000)
A105: Especialidades | B105: =IF('4 Prod Especialidades'!$A9="","",'4 Prod Especialidades'!$A9) | C105: =IF('4 Prod Especialidades'!$B9="","",'4 Prod Especialidades'!$B9) | D105: ='4 Prod Especialidades'!$Q9 | E105: =IF($B105="","",SUMIFS('8 Fudo Ventas'!$B$6:$B$305,'8 Fudo Ventas'!$D$6:$D$305,$B105,'8 Fudo Ventas'!$C$6:$C$305,$A105)) | F105: =IF($B105="","",SUMIFS('8 Fudo Consumos'!$D$6:$D$255,'8 Fudo Consumos'!$B$6:$B$255,$B105,'8 Fudo Consumos'!$C$6:$C$255,$A105)) | G105: ='4 Prod Especialidades'!$R9 | H105: =IF($B105="","",SUMIFS('5 Descartes'!$D$6:$D$205,'5 Descartes'!$C$6:$C$205,$B105,'5 Descartes'!$B$6:$B$205,$A105)) | I105: =IF($B105="","",$G105-$H105) | J105: =IF($B105="","",$D105-$E105-$F105-$G105) | K105: =IF(OR($B105="",$D105=0),"",$J105/$D105) | L105: =IF($B105="","",IF($D105=0,"Sin produccion registrada",IF($E105=0,"Sin ventas mapeadas en Fudo",IF(AND($K105<>"",ABS($K105)>Config!$B$48),IF($J105>0,"Salida sin explicar: consumo no registrado o faltante","Se vendio mas de lo elaborado: revisar stock previo"),IF($I105<>0,"Hay descarte sin detallar en la planilla 5","OK"))))) | M105: =IF($K105="","",ABS($K105)+ROW()/1000000)
A106: Especialidades | B106: =IF('4 Prod Especialidades'!$A10="","",'4 Prod Especialidades'!$A10) | C106: =IF('4 Prod Especialidades'!$B10="","",'4 Prod Especialidades'!$B10) | D106: ='4 Prod Especialidades'!$Q10 | E106: =IF($B106="","",SUMIFS('8 Fudo Ventas'!$B$6:$B$305,'8 Fudo Ventas'!$D$6:$D$305,$B106,'8 Fudo Ventas'!$C$6:$C$305,$A106)) | F106: =IF($B106="","",SUMIFS('8 Fudo Consumos'!$D$6:$D$255,'8 Fudo Consumos'!$B$6:$B$255,$B106,'8 Fudo Consumos'!$C$6:$C$255,$A106)) | G106: ='4 Prod Especialidades'!$R10 | H106: =IF($B106="","",SUMIFS('5 Descartes'!$D$6:$D$205,'5 Descartes'!$C$6:$C$205,$B106,'5 Descartes'!$B$6:$B$205,$A106)) | I106: =IF($B106="","",$G106-$H106) | J106: =IF($B106="","",$D106-$E106-$F106-$G106) | K106: =IF(OR($B106="",$D106=0),"",$J106/$D106) | L106: =IF($B106="","",IF($D106=0,"Sin produccion registrada",IF($E106=0,"Sin ventas mapeadas en Fudo",IF(AND($K106<>"",ABS($K106)>Config!$B$48),IF($J106>0,"Salida sin explicar: consumo no registrado o faltante","Se vendio mas de lo elaborado: revisar stock previo"),IF($I106<>0,"Hay descarte sin detallar en la planilla 5","OK"))))) | M106: =IF($K106="","",ABS($K106)+ROW()/1000000)
A107: Especialidades | B107: =IF('4 Prod Especialidades'!$A11="","",'4 Prod Especialidades'!$A11) | C107: =IF('4 Prod Especialidades'!$B11="","",'4 Prod Especialidades'!$B11) | D107: ='4 Prod Especialidades'!$Q11 | E107: =IF($B107="","",SUMIFS('8 Fudo Ventas'!$B$6:$B$305,'8 Fudo Ventas'!$D$6:$D$305,$B107,'8 Fudo Ventas'!$C$6:$C$305,$A107)) | F107: =IF($B107="","",SUMIFS('8 Fudo Consumos'!$D$6:$D$255,'8 Fudo Consumos'!$B$6:$B$255,$B107,'8 Fudo Consumos'!$C$6:$C$255,$A107)) | G107: ='4 Prod Especialidades'!$R11 | H107: =IF($B107="","",SUMIFS('5 Descartes'!$D$6:$D$205,'5 Descartes'!$C$6:$C$205,$B107,'5 Descartes'!$B$6:$B$205,$A107)) | I107: =IF($B107="","",$G107-$H107) | J107: =IF($B107="","",$D107-$E107-$F107-$G107) | K107: =IF(OR($B107="",$D107=0),"",$J107/$D107) | L107: =IF($B107="","",IF($D107=0,"Sin produccion registrada",IF($E107=0,"Sin ventas mapeadas en Fudo",IF(AND($K107<>"",ABS($K107)>Config!$B$48),IF($J107>0,"Salida sin explicar: consumo no registrado o faltante","Se vendio mas de lo elaborado: revisar stock previo"),IF($I107<>0,"Hay descarte sin detallar en la planilla 5","OK"))))) | M107: =IF($K107="","",ABS($K107)+ROW()/1000000)
A108: Especialidades | B108: =IF('4 Prod Especialidades'!$A12="","",'4 Prod Especialidades'!$A12) | C108: =IF('4 Prod Especialidades'!$B12="","",'4 Prod Especialidades'!$B12) | D108: ='4 Prod Especialidades'!$Q12 | E108: =IF($B108="","",SUMIFS('8 Fudo Ventas'!$B$6:$B$305,'8 Fudo Ventas'!$D$6:$D$305,$B108,'8 Fudo Ventas'!$C$6:$C$305,$A108)) | F108: =IF($B108="","",SUMIFS('8 Fudo Consumos'!$D$6:$D$255,'8 Fudo Consumos'!$B$6:$B$255,$B108,'8 Fudo Consumos'!$C$6:$C$255,$A108)) | G108: ='4 Prod Especialidades'!$R12 | H108: =IF($B108="","",SUMIFS('5 Descartes'!$D$6:$D$205,'5 Descartes'!$C$6:$C$205,$B108,'5 Descartes'!$B$6:$B$205,$A108)) | I108: =IF($B108="","",$G108-$H108) | J108: =IF($B108="","",$D108-$E108-$F108-$G108) | K108: =IF(OR($B108="",$D108=0),"",$J108/$D108) | L108: =IF($B108="","",IF($D108=0,"Sin produccion registrada",IF($E108=0,"Sin ventas mapeadas en Fudo",IF(AND($K108<>"",ABS($K108)>Config!$B$48),IF($J108>0,"Salida sin explicar: consumo no registrado o faltante","Se vendio mas de lo elaborado: revisar stock previo"),IF($I108<>0,"Hay descarte sin detallar en la planilla 5","OK"))))) | M108: =IF($K108="","",ABS($K108)+ROW()/1000000)
A109: Especialidades | B109: =IF('4 Prod Especialidades'!$A13="","",'4 Prod Especialidades'!$A13) | C109: =IF('4 Prod Especialidades'!$B13="","",'4 Prod Especialidades'!$B13) | D109: ='4 Prod Especialidades'!$Q13 | E109: =IF($B109="","",SUMIFS('8 Fudo Ventas'!$B$6:$B$305,'8 Fudo Ventas'!$D$6:$D$305,$B109,'8 Fudo Ventas'!$C$6:$C$305,$A109)) | F109: =IF($B109="","",SUMIFS('8 Fudo Consumos'!$D$6:$D$255,'8 Fudo Consumos'!$B$6:$B$255,$B109,'8 Fudo Consumos'!$C$6:$C$255,$A109)) | G109: ='4 Prod Especialidades'!$R13 | H109: =IF($B109="","",SUMIFS('5 Descartes'!$D$6:$D$205,'5 Descartes'!$C$6:$C$205,$B109,'5 Descartes'!$B$6:$B$205,$A109)) | I109: =IF($B109="","",$G109-$H109) | J109: =IF($B109="","",$D109-$E109-$F109-$G109) | K109: =IF(OR($B109="",$D109=0),"",$J109/$D109) | L109: =IF($B109="","",IF($D109=0,"Sin produccion registrada",IF($E109=0,"Sin ventas mapeadas en Fudo",IF(AND($K109<>"",ABS($K109)>Config!$B$48),IF($J109>0,"Salida sin explicar: consumo no registrado o faltante","Se vendio mas de lo elaborado: revisar stock previo"),IF($I109<>0,"Hay descarte sin detallar en la planilla 5","OK"))))) | M109: =IF($K109="","",ABS($K109)+ROW()/1000000)
A110: Especialidades | B110: =IF('4 Prod Especialidades'!$A14="","",'4 Prod Especialidades'!$A14) | C110: =IF('4 Prod Especialidades'!$B14="","",'4 Prod Especialidades'!$B14) | D110: ='4 Prod Especialidades'!$Q14 | E110: =IF($B110="","",SUMIFS('8 Fudo Ventas'!$B$6:$B$305,'8 Fudo Ventas'!$D$6:$D$305,$B110,'8 Fudo Ventas'!$C$6:$C$305,$A110)) | F110: =IF($B110="","",SUMIFS('8 Fudo Consumos'!$D$6:$D$255,'8 Fudo Consumos'!$B$6:$B$255,$B110,'8 Fudo Consumos'!$C$6:$C$255,$A110)) | G110: ='4 Prod Especialidades'!$R14 | H110: =IF($B110="","",SUMIFS('5 Descartes'!$D$6:$D$205,'5 Descartes'!$C$6:$C$205,$B110,'5 Descartes'!$B$6:$B$205,$A110)) | I110: =IF($B110="","",$G110-$H110) | J110: =IF($B110="","",$D110-$E110-$F110-$G110) | K110: =IF(OR($B110="",$D110=0),"",$J110/$D110) | L110: =IF($B110="","",IF($D110=0,"Sin produccion registrada",IF($E110=0,"Sin ventas mapeadas en Fudo",IF(AND($K110<>"",ABS($K110)>Config!$B$48),IF($J110>0,"Salida sin explicar: consumo no registrado o faltante","Se vendio mas de lo elaborado: revisar stock previo"),IF($I110<>0,"Hay descarte sin detallar en la planilla 5","OK"))))) | M110: =IF($K110="","",ABS($K110)+ROW()/1000000)
A111: Especialidades | B111: =IF('4 Prod Especialidades'!$A15="","",'4 Prod Especialidades'!$A15) | C111: =IF('4 Prod Especialidades'!$B15="","",'4 Prod Especialidades'!$B15) | D111: ='4 Prod Especialidades'!$Q15 | E111: =IF($B111="","",SUMIFS('8 Fudo Ventas'!$B$6:$B$305,'8 Fudo Ventas'!$D$6:$D$305,$B111,'8 Fudo Ventas'!$C$6:$C$305,$A111)) | F111: =IF($B111="","",SUMIFS('8 Fudo Consumos'!$D$6:$D$255,'8 Fudo Consumos'!$B$6:$B$255,$B111,'8 Fudo Consumos'!$C$6:$C$255,$A111)) | G111: ='4 Prod Especialidades'!$R15 | H111: =IF($B111="","",SUMIFS('5 Descartes'!$D$6:$D$205,'5 Descartes'!$C$6:$C$205,$B111,'5 Descartes'!$B$6:$B$205,$A111)) | I111: =IF($B111="","",$G111-$H111) | J111: =IF($B111="","",$D111-$E111-$F111-$G111) | K111: =IF(OR($B111="",$D111=0),"",$J111/$D111) | L111: =IF($B111="","",IF($D111=0,"Sin produccion registrada",IF($E111=0,"Sin ventas mapeadas en Fudo",IF(AND($K111<>"",ABS($K111)>Config!$B$48),IF($J111>0,"Salida sin explicar: consumo no registrado o faltante","Se vendio mas de lo elaborado: revisar stock previo"),IF($I111<>0,"Hay descarte sin detallar en la planilla 5","OK"))))) | M111: =IF($K111="","",ABS($K111)+ROW()/1000000)
A112: Especialidades | B112: =IF('4 Prod Especialidades'!$A16="","",'4 Prod Especialidades'!$A16) | C112: =IF('4 Prod Especialidades'!$B16="","",'4 Prod Especialidades'!$B16) | D112: ='4 Prod Especialidades'!$Q16 | E112: =IF($B112="","",SUMIFS('8 Fudo Ventas'!$B$6:$B$305,'8 Fudo Ventas'!$D$6:$D$305,$B112,'8 Fudo Ventas'!$C$6:$C$305,$A112)) | F112: =IF($B112="","",SUMIFS('8 Fudo Consumos'!$D$6:$D$255,'8 Fudo Consumos'!$B$6:$B$255,$B112,'8 Fudo Consumos'!$C$6:$C$255,$A112)) | G112: ='4 Prod Especialidades'!$R16 | H112: =IF($B112="","",SUMIFS('5 Descartes'!$D$6:$D$205,'5 Descartes'!$C$6:$C$205,$B112,'5 Descartes'!$B$6:$B$205,$A112)) | I112: =IF($B112="","",$G112-$H112) | J112: =IF($B112="","",$D112-$E112-$F112-$G112) | K112: =IF(OR($B112="",$D112=0),"",$J112/$D112) | L112: =IF($B112="","",IF($D112=0,"Sin produccion registrada",IF($E112=0,"Sin ventas mapeadas en Fudo",IF(AND($K112<>"",ABS($K112)>Config!$B$48),IF($J112>0,"Salida sin explicar: consumo no registrado o faltante","Se vendio mas de lo elaborado: revisar stock previo"),IF($I112<>0,"Hay descarte sin detallar en la planilla 5","OK"))))) | M112: =IF($K112="","",ABS($K112)+ROW()/1000000)
A113: Especialidades | B113: =IF('4 Prod Especialidades'!$A17="","",'4 Prod Especialidades'!$A17) | C113: =IF('4 Prod Especialidades'!$B17="","",'4 Prod Especialidades'!$B17) | D113: ='4 Prod Especialidades'!$Q17 | E113: =IF($B113="","",SUMIFS('8 Fudo Ventas'!$B$6:$B$305,'8 Fudo Ventas'!$D$6:$D$305,$B113,'8 Fudo Ventas'!$C$6:$C$305,$A113)) | F113: =IF($B113="","",SUMIFS('8 Fudo Consumos'!$D$6:$D$255,'8 Fudo Consumos'!$B$6:$B$255,$B113,'8 Fudo Consumos'!$C$6:$C$255,$A113)) | G113: ='4 Prod Especialidades'!$R17 | H113: =IF($B113="","",SUMIFS('5 Descartes'!$D$6:$D$205,'5 Descartes'!$C$6:$C$205,$B113,'5 Descartes'!$B$6:$B$205,$A113)) | I113: =IF($B113="","",$G113-$H113) | J113: =IF($B113="","",$D113-$E113-$F113-$G113) | K113: =IF(OR($B113="",$D113=0),"",$J113/$D113) | L113: =IF($B113="","",IF($D113=0,"Sin produccion registrada",IF($E113=0,"Sin ventas mapeadas en Fudo",IF(AND($K113<>"",ABS($K113)>Config!$B$48),IF($J113>0,"Salida sin explicar: consumo no registrado o faltante","Se vendio mas de lo elaborado: revisar stock previo"),IF($I113<>0,"Hay descarte sin detallar en la planilla 5","OK"))))) | M113: =IF($K113="","",ABS($K113)+ROW()/1000000)
... A145: Especialidades | B145: =IF('4 Prod Especialidades'!$A49="","",'4 Prod Especialidades'!$A49) | C145: =IF('4 Prod Especialidades'!$B49="","",'4 Prod Especialidades'!$B49) | D145: ='4 Prod Especialidades'!$Q49 | E145: =IF($B145="","",SUMIFS('8 Fudo Ventas'!$B$6:$B$305,'8 Fudo Ventas'!$D$6:$D$305,$B145,'8 Fudo Ventas'!$C$6:$C$305,$A145)) | F145: =IF($B145="","",SUMIFS('8 Fudo Consumos'!$D$6:$D$255,'8 Fudo Consumos'!$B$6:$B$255,$B145,'8 Fudo Consumos'!$C$6:$C$255,$A145)) | G145: ='4 Prod Especialidades'!$R49 | H145: =IF($B145="","",SUMIFS('5 Descartes'!$D$6:$D$205,'5 Descartes'!$C$6:$C$205,$B145,'5 Descartes'!$B$6:$B$205,$A145)) | I145: =IF($B145="","",$G145-$H145) | J145: =IF($B145="","",$D145-$E145-$F145-$G145) | K145: =IF(OR($B145="",$D145=0),"",$J145/$D145) | L145: =IF($B145="","",IF($D145=0,"Sin produccion registrada",IF($E145=0,"Sin ventas mapeadas en Fudo",IF(AND($K145<>"",ABS($K145)>Config!$B$48),IF($J145>0,"Salida sin explicar: consumo no registrado o faltante","Se vendio mas de lo elaborado: revisar stock previo"),IF($I145<>0,"Hay descarte sin detallar en la planilla 5","OK"))))) | M145: =IF($K145="","",ABS($K145)+ROW()/1000000)
A146: Facturería | B146: =IF('4 Prod Factureria'!$A6="","",'4 Prod Factureria'!$A6) | C146: =IF('4 Prod Factureria'!$B6="","",'4 Prod Factureria'!$B6) | D146: ='4 Prod Factureria'!$Q6 | E146: =IF($B146="","",SUMIFS('8 Fudo Ventas'!$B$6:$B$305,'8 Fudo Ventas'!$D$6:$D$305,$B146,'8 Fudo Ventas'!$C$6:$C$305,$A146)) | F146: =IF($B146="","",SUMIFS('8 Fudo Consumos'!$D$6:$D$255,'8 Fudo Consumos'!$B$6:$B$255,$B146,'8 Fudo Consumos'!$C$6:$C$255,$A146)) | G146: ='4 Prod Factureria'!$R6 | H146: =IF($B146="","",SUMIFS('5 Descartes'!$D$6:$D$205,'5 Descartes'!$C$6:$C$205,$B146,'5 Descartes'!$B$6:$B$205,$A146)) | I146: =IF($B146="","",$G146-$H146) | J146: =IF($B146="","",$D146-$E146-$F146-$G146) | K146: =IF(OR($B146="",$D146=0),"",$J146/$D146) | L146: =IF($B146="","",IF($D146=0,"Sin produccion registrada",IF($E146=0,"Sin ventas mapeadas en Fudo",IF(AND($K146<>"",ABS($K146)>Config!$B$48),IF($J146>0,"Salida sin explicar: consumo no registrado o faltante","Se vendio mas de lo elaborado: revisar stock previo"),IF($I146<>0,"Hay descarte sin detallar en la planilla 5","OK"))))) | M146: =IF($K146="","",ABS($K146)+ROW()/1000000)
A147: Facturería | B147: =IF('4 Prod Factureria'!$A7="","",'4 Prod Factureria'!$A7) | C147: =IF('4 Prod Factureria'!$B7="","",'4 Prod Factureria'!$B7) | D147: ='4 Prod Factureria'!$Q7 | E147: =IF($B147="","",SUMIFS('8 Fudo Ventas'!$B$6:$B$305,'8 Fudo Ventas'!$D$6:$D$305,$B147,'8 Fudo Ventas'!$C$6:$C$305,$A147)) | F147: =IF($B147="","",SUMIFS('8 Fudo Consumos'!$D$6:$D$255,'8 Fudo Consumos'!$B$6:$B$255,$B147,'8 Fudo Consumos'!$C$6:$C$255,$A147)) | G147: ='4 Prod Factureria'!$R7 | H147: =IF($B147="","",SUMIFS('5 Descartes'!$D$6:$D$205,'5 Descartes'!$C$6:$C$205,$B147,'5 Descartes'!$B$6:$B$205,$A147)) | I147: =IF($B147="","",$G147-$H147) | J147: =IF($B147="","",$D147-$E147-$F147-$G147) | K147: =IF(OR($B147="",$D147=0),"",$J147/$D147) | L147: =IF($B147="","",IF($D147=0,"Sin produccion registrada",IF($E147=0,"Sin ventas mapeadas en Fudo",IF(AND($K147<>"",ABS($K147)>Config!$B$48),IF($J147>0,"Salida sin explicar: consumo no registrado o faltante","Se vendio mas de lo elaborado: revisar stock previo"),IF($I147<>0,"Hay descarte sin detallar en la planilla 5","OK"))))) | M147: =IF($K147="","",ABS($K147)+ROW()/1000000)
A148: Facturería | B148: =IF('4 Prod Factureria'!$A8="","",'4 Prod Factureria'!$A8) | C148: =IF('4 Prod Factureria'!$B8="","",'4 Prod Factureria'!$B8) | D148: ='4 Prod Factureria'!$Q8 | E148: =IF($B148="","",SUMIFS('8 Fudo Ventas'!$B$6:$B$305,'8 Fudo Ventas'!$D$6:$D$305,$B148,'8 Fudo Ventas'!$C$6:$C$305,$A148)) | F148: =IF($B148="","",SUMIFS('8 Fudo Consumos'!$D$6:$D$255,'8 Fudo Consumos'!$B$6:$B$255,$B148,'8 Fudo Consumos'!$C$6:$C$255,$A148)) | G148: ='4 Prod Factureria'!$R8 | H148: =IF($B148="","",SUMIFS('5 Descartes'!$D$6:$D$205,'5 Descartes'!$C$6:$C$205,$B148,'5 Descartes'!$B$6:$B$205,$A148)) | I148: =IF($B148="","",$G148-$H148) | J148: =IF($B148="","",$D148-$E148-$F148-$G148) | K148: =IF(OR($B148="",$D148=0),"",$J148/$D148) | L148: =IF($B148="","",IF($D148=0,"Sin produccion registrada",IF($E148=0,"Sin ventas mapeadas en Fudo",IF(AND($K148<>"",ABS($K148)>Config!$B$48),IF($J148>0,"Salida sin explicar: consumo no registrado o faltante","Se vendio mas de lo elaborado: revisar stock previo"),IF($I148<>0,"Hay descarte sin detallar en la planilla 5","OK"))))) | M148: =IF($K148="","",ABS($K148)+ROW()/1000000)
A149: Facturería | B149: =IF('4 Prod Factureria'!$A9="","",'4 Prod Factureria'!$A9) | C149: =IF('4 Prod Factureria'!$B9="","",'4 Prod Factureria'!$B9) | D149: ='4 Prod Factureria'!$Q9 | E149: =IF($B149="","",SUMIFS('8 Fudo Ventas'!$B$6:$B$305,'8 Fudo Ventas'!$D$6:$D$305,$B149,'8 Fudo Ventas'!$C$6:$C$305,$A149)) | F149: =IF($B149="","",SUMIFS('8 Fudo Consumos'!$D$6:$D$255,'8 Fudo Consumos'!$B$6:$B$255,$B149,'8 Fudo Consumos'!$C$6:$C$255,$A149)) | G149: ='4 Prod Factureria'!$R9 | H149: =IF($B149="","",SUMIFS('5 Descartes'!$D$6:$D$205,'5 Descartes'!$C$6:$C$205,$B149,'5 Descartes'!$B$6:$B$205,$A149)) | I149: =IF($B149="","",$G149-$H149) | J149: =IF($B149="","",$D149-$E149-$F149-$G149) | K149: =IF(OR($B149="",$D149=0),"",$J149/$D149) | L149: =IF($B149="","",IF($D149=0,"Sin produccion registrada",IF($E149=0,"Sin ventas mapeadas en Fudo",IF(AND($K149<>"",ABS($K149)>Config!$B$48),IF($J149>0,"Salida sin explicar: consumo no registrado o faltante","Se vendio mas de lo elaborado: revisar stock previo"),IF($I149<>0,"Hay descarte sin detallar en la planilla 5","OK"))))) | M149: =IF($K149="","",ABS($K149)+ROW()/1000000)
A150: Facturería | B150: =IF('4 Prod Factureria'!$A10="","",'4 Prod Factureria'!$A10) | C150: =IF('4 Prod Factureria'!$B10="","",'4 Prod Factureria'!$B10) | D150: ='4 Prod Factureria'!$Q10 | E150: =IF($B150="","",SUMIFS('8 Fudo Ventas'!$B$6:$B$305,'8 Fudo Ventas'!$D$6:$D$305,$B150,'8 Fudo Ventas'!$C$6:$C$305,$A150)) | F150: =IF($B150="","",SUMIFS('8 Fudo Consumos'!$D$6:$D$255,'8 Fudo Consumos'!$B$6:$B$255,$B150,'8 Fudo Consumos'!$C$6:$C$255,$A150)) | G150: ='4 Prod Factureria'!$R10 | H150: =IF($B150="","",SUMIFS('5 Descartes'!$D$6:$D$205,'5 Descartes'!$C$6:$C$205,$B150,'5 Descartes'!$B$6:$B$205,$A150)) | I150: =IF($B150="","",$G150-$H150) | J150: =IF($B150="","",$D150-$E150-$F150-$G150) | K150: =IF(OR($B150="",$D150=0),"",$J150/$D150) | L150: =IF($B150="","",IF($D150=0,"Sin produccion registrada",IF($E150=0,"Sin ventas mapeadas en Fudo",IF(AND($K150<>"",ABS($K150)>Config!$B$48),IF($J150>0,"Salida sin explicar: consumo no registrado o faltante","Se vendio mas de lo elaborado: revisar stock previo"),IF($I150<>0,"Hay descarte sin detallar en la planilla 5","OK"))))) | M150: =IF($K150="","",ABS($K150)+ROW()/1000000)
A151: Facturería | B151: =IF('4 Prod Factureria'!$A11="","",'4 Prod Factureria'!$A11) | C151: =IF('4 Prod Factureria'!$B11="","",'4 Prod Factureria'!$B11) | D151: ='4 Prod Factureria'!$Q11 | E151: =IF($B151="","",SUMIFS('8 Fudo Ventas'!$B$6:$B$305,'8 Fudo Ventas'!$D$6:$D$305,$B151,'8 Fudo Ventas'!$C$6:$C$305,$A151)) | F151: =IF($B151="","",SUMIFS('8 Fudo Consumos'!$D$6:$D$255,'8 Fudo Consumos'!$B$6:$B$255,$B151,'8 Fudo Consumos'!$C$6:$C$255,$A151)) | G151: ='4 Prod Factureria'!$R11 | H151: =IF($B151="","",SUMIFS('5 Descartes'!$D$6:$D$205,'5 Descartes'!$C$6:$C$205,$B151,'5 Descartes'!$B$6:$B$205,$A151)) | I151: =IF($B151="","",$G151-$H151) | J151: =IF($B151="","",$D151-$E151-$F151-$G151) | K151: =IF(OR($B151="",$D151=0),"",$J151/$D151) | L151: =IF($B151="","",IF($D151=0,"Sin produccion registrada",IF($E151=0,"Sin ventas mapeadas en Fudo",IF(AND($K151<>"",ABS($K151)>Config!$B$48),IF($J151>0,"Salida sin explicar: consumo no registrado o faltante","Se vendio mas de lo elaborado: revisar stock previo"),IF($I151<>0,"Hay descarte sin detallar en la planilla 5","OK"))))) | M151: =IF($K151="","",ABS($K151)+ROW()/1000000)
A152: Facturería | B152: =IF('4 Prod Factureria'!$A12="","",'4 Prod Factureria'!$A12) | C152: =IF('4 Prod Factureria'!$B12="","",'4 Prod Factureria'!$B12) | D152: ='4 Prod Factureria'!$Q12 | E152: =IF($B152="","",SUMIFS('8 Fudo Ventas'!$B$6:$B$305,'8 Fudo Ventas'!$D$6:$D$305,$B152,'8 Fudo Ventas'!$C$6:$C$305,$A152)) | F152: =IF($B152="","",SUMIFS('8 Fudo Consumos'!$D$6:$D$255,'8 Fudo Consumos'!$B$6:$B$255,$B152,'8 Fudo Consumos'!$C$6:$C$255,$A152)) | G152: ='4 Prod Factureria'!$R12 | H152: =IF($B152="","",SUMIFS('5 Descartes'!$D$6:$D$205,'5 Descartes'!$C$6:$C$205,$B152,'5 Descartes'!$B$6:$B$205,$A152)) | I152: =IF($B152="","",$G152-$H152) | J152: =IF($B152="","",$D152-$E152-$F152-$G152) | K152: =IF(OR($B152="",$D152=0),"",$J152/$D152) | L152: =IF($B152="","",IF($D152=0,"Sin produccion registrada",IF($E152=0,"Sin ventas mapeadas en Fudo",IF(AND($K152<>"",ABS($K152)>Config!$B$48),IF($J152>0,"Salida sin explicar: consumo no registrado o faltante","Se vendio mas de lo elaborado: revisar stock previo"),IF($I152<>0,"Hay descarte sin detallar en la planilla 5","OK"))))) | M152: =IF($K152="","",ABS($K152)+ROW()/1000000)
A153: Facturería | B153: =IF('4 Prod Factureria'!$A13="","",'4 Prod Factureria'!$A13) | C153: =IF('4 Prod Factureria'!$B13="","",'4 Prod Factureria'!$B13) | D153: ='4 Prod Factureria'!$Q13 | E153: =IF($B153="","",SUMIFS('8 Fudo Ventas'!$B$6:$B$305,'8 Fudo Ventas'!$D$6:$D$305,$B153,'8 Fudo Ventas'!$C$6:$C$305,$A153)) | F153: =IF($B153="","",SUMIFS('8 Fudo Consumos'!$D$6:$D$255,'8 Fudo Consumos'!$B$6:$B$255,$B153,'8 Fudo Consumos'!$C$6:$C$255,$A153)) | G153: ='4 Prod Factureria'!$R13 | H153: =IF($B153="","",SUMIFS('5 Descartes'!$D$6:$D$205,'5 Descartes'!$C$6:$C$205,$B153,'5 Descartes'!$B$6:$B$205,$A153)) | I153: =IF($B153="","",$G153-$H153) | J153: =IF($B153="","",$D153-$E153-$F153-$G153) | K153: =IF(OR($B153="",$D153=0),"",$J153/$D153) | L153: =IF($B153="","",IF($D153=0,"Sin produccion registrada",IF($E153=0,"Sin ventas mapeadas en Fudo",IF(AND($K153<>"",ABS($K153)>Config!$B$48),IF($J153>0,"Salida sin explicar: consumo no registrado o faltante","Se vendio mas de lo elaborado: revisar stock previo"),IF($I153<>0,"Hay descarte sin detallar en la planilla 5","OK"))))) | M153: =IF($K153="","",ABS($K153)+ROW()/1000000)
A154: Facturería | B154: =IF('4 Prod Factureria'!$A14="","",'4 Prod Factureria'!$A14) | C154: =IF('4 Prod Factureria'!$B14="","",'4 Prod Factureria'!$B14) | D154: ='4 Prod Factureria'!$Q14 | E154: =IF($B154="","",SUMIFS('8 Fudo Ventas'!$B$6:$B$305,'8 Fudo Ventas'!$D$6:$D$305,$B154,'8 Fudo Ventas'!$C$6:$C$305,$A154)) | F154: =IF($B154="","",SUMIFS('8 Fudo Consumos'!$D$6:$D$255,'8 Fudo Consumos'!$B$6:$B$255,$B154,'8 Fudo Consumos'!$C$6:$C$255,$A154)) | G154: ='4 Prod Factureria'!$R14 | H154: =IF($B154="","",SUMIFS('5 Descartes'!$D$6:$D$205,'5 Descartes'!$C$6:$C$205,$B154,'5 Descartes'!$B$6:$B$205,$A154)) | I154: =IF($B154="","",$G154-$H154) | J154: =IF($B154="","",$D154-$E154-$F154-$G154) | K154: =IF(OR($B154="",$D154=0),"",$J154/$D154) | L154: =IF($B154="","",IF($D154=0,"Sin produccion registrada",IF($E154=0,"Sin ventas mapeadas en Fudo",IF(AND($K154<>"",ABS($K154)>Config!$B$48),IF($J154>0,"Salida sin explicar: consumo no registrado o faltante","Se vendio mas de lo elaborado: revisar stock previo"),IF($I154<>0,"Hay descarte sin detallar en la planilla 5","OK"))))) | M154: =IF($K154="","",ABS($K154)+ROW()/1000000)
A155: Facturería | B155: =IF('4 Prod Factureria'!$A15="","",'4 Prod Factureria'!$A15) | C155: =IF('4 Prod Factureria'!$B15="","",'4 Prod Factureria'!$B15) | D155: ='4 Prod Factureria'!$Q15 | E155: =IF($B155="","",SUMIFS('8 Fudo Ventas'!$B$6:$B$305,'8 Fudo Ventas'!$D$6:$D$305,$B155,'8 Fudo Ventas'!$C$6:$C$305,$A155)) | F155: =IF($B155="","",SUMIFS('8 Fudo Consumos'!$D$6:$D$255,'8 Fudo Consumos'!$B$6:$B$255,$B155,'8 Fudo Consumos'!$C$6:$C$255,$A155)) | G155: ='4 Prod Factureria'!$R15 | H155: =IF($B155="","",SUMIFS('5 Descartes'!$D$6:$D$205,'5 Descartes'!$C$6:$C$205,$B155,'5 Descartes'!$B$6:$B$205,$A155)) | I155: =IF($B155="","",$G155-$H155) | J155: =IF($B155="","",$D155-$E155-$F155-$G155) | K155: =IF(OR($B155="",$D155=0),"",$J155/$D155) | L155: =IF($B155="","",IF($D155=0,"Sin produccion registrada",IF($E155=0,"Sin ventas mapeadas en Fudo",IF(AND($K155<>"",ABS($K155)>Config!$B$48),IF($J155>0,"Salida sin explicar: consumo no registrado o faltante","Se vendio mas de lo elaborado: revisar stock previo"),IF($I155<>0,"Hay descarte sin detallar en la planilla 5","OK"))))) | M155: =IF($K155="","",ABS($K155)+ROW()/1000000)
A156: Facturería | B156: =IF('4 Prod Factureria'!$A16="","",'4 Prod Factureria'!$A16) | C156: =IF('4 Prod Factureria'!$B16="","",'4 Prod Factureria'!$B16) | D156: ='4 Prod Factureria'!$Q16 | E156: =IF($B156="","",SUMIFS('8 Fudo Ventas'!$B$6:$B$305,'8 Fudo Ventas'!$D$6:$D$305,$B156,'8 Fudo Ventas'!$C$6:$C$305,$A156)) | F156: =IF($B156="","",SUMIFS('8 Fudo Consumos'!$D$6:$D$255,'8 Fudo Consumos'!$B$6:$B$255,$B156,'8 Fudo Consumos'!$C$6:$C$255,$A156)) | G156: ='4 Prod Factureria'!$R16 | H156: =IF($B156="","",SUMIFS('5 Descartes'!$D$6:$D$205,'5 Descartes'!$C$6:$C$205,$B156,'5 Descartes'!$B$6:$B$205,$A156)) | I156: =IF($B156="","",$G156-$H156) | J156: =IF($B156="","",$D156-$E156-$F156-$G156) | K156: =IF(OR($B156="",$D156=0),"",$J156/$D156) | L156: =IF($B156="","",IF($D156=0,"Sin produccion registrada",IF($E156=0,"Sin ventas mapeadas en Fudo",IF(AND($K156<>"",ABS($K156)>Config!$B$48),IF($J156>0,"Salida sin explicar: consumo no registrado o faltante","Se vendio mas de lo elaborado: revisar stock previo"),IF($I156<>0,"Hay descarte sin detallar en la planilla 5","OK"))))) | M156: =IF($K156="","",ABS($K156)+ROW()/1000000)
A157: Facturería | B157: =IF('4 Prod Factureria'!$A17="","",'4 Prod Factureria'!$A17) | C157: =IF('4 Prod Factureria'!$B17="","",'4 Prod Factureria'!$B17) | D157: ='4 Prod Factureria'!$Q17 | E157: =IF($B157="","",SUMIFS('8 Fudo Ventas'!$B$6:$B$305,'8 Fudo Ventas'!$D$6:$D$305,$B157,'8 Fudo Ventas'!$C$6:$C$305,$A157)) | F157: =IF($B157="","",SUMIFS('8 Fudo Consumos'!$D$6:$D$255,'8 Fudo Consumos'!$B$6:$B$255,$B157,'8 Fudo Consumos'!$C$6:$C$255,$A157)) | G157: ='4 Prod Factureria'!$R17 | H157: =IF($B157="","",SUMIFS('5 Descartes'!$D$6:$D$205,'5 Descartes'!$C$6:$C$205,$B157,'5 Descartes'!$B$6:$B$205,$A157)) | I157: =IF($B157="","",$G157-$H157) | J157: =IF($B157="","",$D157-$E157-$F157-$G157) | K157: =IF(OR($B157="",$D157=0),"",$J157/$D157) | L157: =IF($B157="","",IF($D157=0,"Sin produccion registrada",IF($E157=0,"Sin ventas mapeadas en Fudo",IF(AND($K157<>"",ABS($K157)>Config!$B$48),IF($J157>0,"Salida sin explicar: consumo no registrado o faltante","Se vendio mas de lo elaborado: revisar stock previo"),IF($I157<>0,"Hay descarte sin detallar en la planilla 5","OK"))))) | M157: =IF($K157="","",ABS($K157)+ROW()/1000000)
... A169: Facturería | B169: =IF('4 Prod Factureria'!$A29="","",'4 Prod Factureria'!$A29) | C169: =IF('4 Prod Factureria'!$B29="","",'4 Prod Factureria'!$B29) | D169: ='4 Prod Factureria'!$Q29 | E169: =IF($B169="","",SUMIFS('8 Fudo Ventas'!$B$6:$B$305,'8 Fudo Ventas'!$D$6:$D$305,$B169,'8 Fudo Ventas'!$C$6:$C$305,$A169)) | F169: =IF($B169="","",SUMIFS('8 Fudo Consumos'!$D$6:$D$255,'8 Fudo Consumos'!$B$6:$B$255,$B169,'8 Fudo Consumos'!$C$6:$C$255,$A169)) | G169: ='4 Prod Factureria'!$R29 | H169: =IF($B169="","",SUMIFS('5 Descartes'!$D$6:$D$205,'5 Descartes'!$C$6:$C$205,$B169,'5 Descartes'!$B$6:$B$205,$A169)) | I169: =IF($B169="","",$G169-$H169) | J169: =IF($B169="","",$D169-$E169-$F169-$G169) | K169: =IF(OR($B169="",$D169=0),"",$J169/$D169) | L169: =IF($B169="","",IF($D169=0,"Sin produccion registrada",IF($E169=0,"Sin ventas mapeadas en Fudo",IF(AND($K169<>"",ABS($K169)>Config!$B$48),IF($J169>0,"Salida sin explicar: consumo no registrado o faltante","Se vendio mas de lo elaborado: revisar stock previo"),IF($I169<>0,"Hay descarte sin detallar en la planilla 5","OK"))))) | M169: =IF($K169="","",ABS($K169)+ROW()/1000000)
A170: Sandwiches | B170: =IF('4 Prod Sandwiches'!$A6="","",'4 Prod Sandwiches'!$A6) | C170: =IF('4 Prod Sandwiches'!$B6="","",'4 Prod Sandwiches'!$B6) | D170: ='4 Prod Sandwiches'!$Q6 | E170: =IF($B170="","",SUMIFS('8 Fudo Ventas'!$B$6:$B$305,'8 Fudo Ventas'!$D$6:$D$305,$B170,'8 Fudo Ventas'!$C$6:$C$305,$A170)) | F170: =IF($B170="","",SUMIFS('8 Fudo Consumos'!$D$6:$D$255,'8 Fudo Consumos'!$B$6:$B$255,$B170,'8 Fudo Consumos'!$C$6:$C$255,$A170)) | G170: ='4 Prod Sandwiches'!$R6 | H170: =IF($B170="","",SUMIFS('5 Descartes'!$D$6:$D$205,'5 Descartes'!$C$6:$C$205,$B170,'5 Descartes'!$B$6:$B$205,$A170)) | I170: =IF($B170="","",$G170-$H170) | J170: =IF($B170="","",$D170-$E170-$F170-$G170) | K170: =IF(OR($B170="",$D170=0),"",$J170/$D170) | L170: =IF($B170="","",IF($D170=0,"Sin produccion registrada",IF($E170=0,"Sin ventas mapeadas en Fudo",IF(AND($K170<>"",ABS($K170)>Config!$B$48),IF($J170>0,"Salida sin explicar: consumo no registrado o faltante","Se vendio mas de lo elaborado: revisar stock previo"),IF($I170<>0,"Hay descarte sin detallar en la planilla 5","OK"))))) | M170: =IF($K170="","",ABS($K170)+ROW()/1000000)
A171: Sandwiches | B171: =IF('4 Prod Sandwiches'!$A7="","",'4 Prod Sandwiches'!$A7) | C171: =IF('4 Prod Sandwiches'!$B7="","",'4 Prod Sandwiches'!$B7) | D171: ='4 Prod Sandwiches'!$Q7 | E171: =IF($B171="","",SUMIFS('8 Fudo Ventas'!$B$6:$B$305,'8 Fudo Ventas'!$D$6:$D$305,$B171,'8 Fudo Ventas'!$C$6:$C$305,$A171)) | F171: =IF($B171="","",SUMIFS('8 Fudo Consumos'!$D$6:$D$255,'8 Fudo Consumos'!$B$6:$B$255,$B171,'8 Fudo Consumos'!$C$6:$C$255,$A171)) | G171: ='4 Prod Sandwiches'!$R7 | H171: =IF($B171="","",SUMIFS('5 Descartes'!$D$6:$D$205,'5 Descartes'!$C$6:$C$205,$B171,'5 Descartes'!$B$6:$B$205,$A171)) | I171: =IF($B171="","",$G171-$H171) | J171: =IF($B171="","",$D171-$E171-$F171-$G171) | K171: =IF(OR($B171="",$D171=0),"",$J171/$D171) | L171: =IF($B171="","",IF($D171=0,"Sin produccion registrada",IF($E171=0,"Sin ventas mapeadas en Fudo",IF(AND($K171<>"",ABS($K171)>Config!$B$48),IF($J171>0,"Salida sin explicar: consumo no registrado o faltante","Se vendio mas de lo elaborado: revisar stock previo"),IF($I171<>0,"Hay descarte sin detallar en la planilla 5","OK"))))) | M171: =IF($K171="","",ABS($K171)+ROW()/1000000)
A172: Sandwiches | B172: =IF('4 Prod Sandwiches'!$A8="","",'4 Prod Sandwiches'!$A8) | C172: =IF('4 Prod Sandwiches'!$B8="","",'4 Prod Sandwiches'!$B8) | D172: ='4 Prod Sandwiches'!$Q8 | E172: =IF($B172="","",SUMIFS('8 Fudo Ventas'!$B$6:$B$305,'8 Fudo Ventas'!$D$6:$D$305,$B172,'8 Fudo Ventas'!$C$6:$C$305,$A172)) | F172: =IF($B172="","",SUMIFS('8 Fudo Consumos'!$D$6:$D$255,'8 Fudo Consumos'!$B$6:$B$255,$B172,'8 Fudo Consumos'!$C$6:$C$255,$A172)) | G172: ='4 Prod Sandwiches'!$R8 | H172: =IF($B172="","",SUMIFS('5 Descartes'!$D$6:$D$205,'5 Descartes'!$C$6:$C$205,$B172,'5 Descartes'!$B$6:$B$205,$A172)) | I172: =IF($B172="","",$G172-$H172) | J172: =IF($B172="","",$D172-$E172-$F172-$G172) | K172: =IF(OR($B172="",$D172=0),"",$J172/$D172) | L172: =IF($B172="","",IF($D172=0,"Sin produccion registrada",IF($E172=0,"Sin ventas mapeadas en Fudo",IF(AND($K172<>"",ABS($K172)>Config!$B$48),IF($J172>0,"Salida sin explicar: consumo no registrado o faltante","Se vendio mas de lo elaborado: revisar stock previo"),IF($I172<>0,"Hay descarte sin detallar en la planilla 5","OK"))))) | M172: =IF($K172="","",ABS($K172)+ROW()/1000000)
A173: Sandwiches | B173: =IF('4 Prod Sandwiches'!$A9="","",'4 Prod Sandwiches'!$A9) | C173: =IF('4 Prod Sandwiches'!$B9="","",'4 Prod Sandwiches'!$B9) | D173: ='4 Prod Sandwiches'!$Q9 | E173: =IF($B173="","",SUMIFS('8 Fudo Ventas'!$B$6:$B$305,'8 Fudo Ventas'!$D$6:$D$305,$B173,'8 Fudo Ventas'!$C$6:$C$305,$A173)) | F173: =IF($B173="","",SUMIFS('8 Fudo Consumos'!$D$6:$D$255,'8 Fudo Consumos'!$B$6:$B$255,$B173,'8 Fudo Consumos'!$C$6:$C$255,$A173)) | G173: ='4 Prod Sandwiches'!$R9 | H173: =IF($B173="","",SUMIFS('5 Descartes'!$D$6:$D$205,'5 Descartes'!$C$6:$C$205,$B173,'5 Descartes'!$B$6:$B$205,$A173)) | I173: =IF($B173="","",$G173-$H173) | J173: =IF($B173="","",$D173-$E173-$F173-$G173) | K173: =IF(OR($B173="",$D173=0),"",$J173/$D173) | L173: =IF($B173="","",IF($D173=0,"Sin produccion registrada",IF($E173=0,"Sin ventas mapeadas en Fudo",IF(AND($K173<>"",ABS($K173)>Config!$B$48),IF($J173>0,"Salida sin explicar: consumo no registrado o faltante","Se vendio mas de lo elaborado: revisar stock previo"),IF($I173<>0,"Hay descarte sin detallar en la planilla 5","OK"))))) | M173: =IF($K173="","",ABS($K173)+ROW()/1000000)
A174: Sandwiches | B174: =IF('4 Prod Sandwiches'!$A10="","",'4 Prod Sandwiches'!$A10) | C174: =IF('4 Prod Sandwiches'!$B10="","",'4 Prod Sandwiches'!$B10) | D174: ='4 Prod Sandwiches'!$Q10 | E174: =IF($B174="","",SUMIFS('8 Fudo Ventas'!$B$6:$B$305,'8 Fudo Ventas'!$D$6:$D$305,$B174,'8 Fudo Ventas'!$C$6:$C$305,$A174)) | F174: =IF($B174="","",SUMIFS('8 Fudo Consumos'!$D$6:$D$255,'8 Fudo Consumos'!$B$6:$B$255,$B174,'8 Fudo Consumos'!$C$6:$C$255,$A174)) | G174: ='4 Prod Sandwiches'!$R10 | H174: =IF($B174="","",SUMIFS('5 Descartes'!$D$6:$D$205,'5 Descartes'!$C$6:$C$205,$B174,'5 Descartes'!$B$6:$B$205,$A174)) | I174: =IF($B174="","",$G174-$H174) | J174: =IF($B174="","",$D174-$E174-$F174-$G174) | K174: =IF(OR($B174="",$D174=0),"",$J174/$D174) | L174: =IF($B174="","",IF($D174=0,"Sin produccion registrada",IF($E174=0,"Sin ventas mapeadas en Fudo",IF(AND($K174<>"",ABS($K174)>Config!$B$48),IF($J174>0,"Salida sin explicar: consumo no registrado o faltante","Se vendio mas de lo elaborado: revisar stock previo"),IF($I174<>0,"Hay descarte sin detallar en la planilla 5","OK"))))) | M174: =IF($K174="","",ABS($K174)+ROW()/1000000)
A175: Sandwiches | B175: =IF('4 Prod Sandwiches'!$A11="","",'4 Prod Sandwiches'!$A11) | C175: =IF('4 Prod Sandwiches'!$B11="","",'4 Prod Sandwiches'!$B11) | D175: ='4 Prod Sandwiches'!$Q11 | E175: =IF($B175="","",SUMIFS('8 Fudo Ventas'!$B$6:$B$305,'8 Fudo Ventas'!$D$6:$D$305,$B175,'8 Fudo Ventas'!$C$6:$C$305,$A175)) | F175: =IF($B175="","",SUMIFS('8 Fudo Consumos'!$D$6:$D$255,'8 Fudo Consumos'!$B$6:$B$255,$B175,'8 Fudo Consumos'!$C$6:$C$255,$A175)) | G175: ='4 Prod Sandwiches'!$R11 | H175: =IF($B175="","",SUMIFS('5 Descartes'!$D$6:$D$205,'5 Descartes'!$C$6:$C$205,$B175,'5 Descartes'!$B$6:$B$205,$A175)) | I175: =IF($B175="","",$G175-$H175) | J175: =IF($B175="","",$D175-$E175-$F175-$G175) | K175: =IF(OR($B175="",$D175=0),"",$J175/$D175) | L175: =IF($B175="","",IF($D175=0,"Sin produccion registrada",IF($E175=0,"Sin ventas mapeadas en Fudo",IF(AND($K175<>"",ABS($K175)>Config!$B$48),IF($J175>0,"Salida sin explicar: consumo no registrado o faltante","Se vendio mas de lo elaborado: revisar stock previo"),IF($I175<>0,"Hay descarte sin detallar en la planilla 5","OK"))))) | M175: =IF($K175="","",ABS($K175)+ROW()/1000000)
A176: Sandwiches | B176: =IF('4 Prod Sandwiches'!$A12="","",'4 Prod Sandwiches'!$A12) | C176: =IF('4 Prod Sandwiches'!$B12="","",'4 Prod Sandwiches'!$B12) | D176: ='4 Prod Sandwiches'!$Q12 | E176: =IF($B176="","",SUMIFS('8 Fudo Ventas'!$B$6:$B$305,'8 Fudo Ventas'!$D$6:$D$305,$B176,'8 Fudo Ventas'!$C$6:$C$305,$A176)) | F176: =IF($B176="","",SUMIFS('8 Fudo Consumos'!$D$6:$D$255,'8 Fudo Consumos'!$B$6:$B$255,$B176,'8 Fudo Consumos'!$C$6:$C$255,$A176)) | G176: ='4 Prod Sandwiches'!$R12 | H176: =IF($B176="","",SUMIFS('5 Descartes'!$D$6:$D$205,'5 Descartes'!$C$6:$C$205,$B176,'5 Descartes'!$B$6:$B$205,$A176)) | I176: =IF($B176="","",$G176-$H176) | J176: =IF($B176="","",$D176-$E176-$F176-$G176) | K176: =IF(OR($B176="",$D176=0),"",$J176/$D176) | L176: =IF($B176="","",IF($D176=0,"Sin produccion registrada",IF($E176=0,"Sin ventas mapeadas en Fudo",IF(AND($K176<>"",ABS($K176)>Config!$B$48),IF($J176>0,"Salida sin explicar: consumo no registrado o faltante","Se vendio mas de lo elaborado: revisar stock previo"),IF($I176<>0,"Hay descarte sin detallar en la planilla 5","OK"))))) | M176: =IF($K176="","",ABS($K176)+ROW()/1000000)
A177: Sandwiches | B177: =IF('4 Prod Sandwiches'!$A13="","",'4 Prod Sandwiches'!$A13) | C177: =IF('4 Prod Sandwiches'!$B13="","",'4 Prod Sandwiches'!$B13) | D177: ='4 Prod Sandwiches'!$Q13 | E177: =IF($B177="","",SUMIFS('8 Fudo Ventas'!$B$6:$B$305,'8 Fudo Ventas'!$D$6:$D$305,$B177,'8 Fudo Ventas'!$C$6:$C$305,$A177)) | F177: =IF($B177="","",SUMIFS('8 Fudo Consumos'!$D$6:$D$255,'8 Fudo Consumos'!$B$6:$B$255,$B177,'8 Fudo Consumos'!$C$6:$C$255,$A177)) | G177: ='4 Prod Sandwiches'!$R13 | H177: =IF($B177="","",SUMIFS('5 Descartes'!$D$6:$D$205,'5 Descartes'!$C$6:$C$205,$B177,'5 Descartes'!$B$6:$B$205,$A177)) | I177: =IF($B177="","",$G177-$H177) | J177: =IF($B177="","",$D177-$E177-$F177-$G177) | K177: =IF(OR($B177="",$D177=0),"",$J177/$D177) | L177: =IF($B177="","",IF($D177=0,"Sin produccion registrada",IF($E177=0,"Sin ventas mapeadas en Fudo",IF(AND($K177<>"",ABS($K177)>Config!$B$48),IF($J177>0,"Salida sin explicar: consumo no registrado o faltante","Se vendio mas de lo elaborado: revisar stock previo"),IF($I177<>0,"Hay descarte sin detallar en la planilla 5","OK"))))) | M177: =IF($K177="","",ABS($K177)+ROW()/1000000)
A178: Sandwiches | B178: =IF('4 Prod Sandwiches'!$A14="","",'4 Prod Sandwiches'!$A14) | C178: =IF('4 Prod Sandwiches'!$B14="","",'4 Prod Sandwiches'!$B14) | D178: ='4 Prod Sandwiches'!$Q14 | E178: =IF($B178="","",SUMIFS('8 Fudo Ventas'!$B$6:$B$305,'8 Fudo Ventas'!$D$6:$D$305,$B178,'8 Fudo Ventas'!$C$6:$C$305,$A178)) | F178: =IF($B178="","",SUMIFS('8 Fudo Consumos'!$D$6:$D$255,'8 Fudo Consumos'!$B$6:$B$255,$B178,'8 Fudo Consumos'!$C$6:$C$255,$A178)) | G178: ='4 Prod Sandwiches'!$R14 | H178: =IF($B178="","",SUMIFS('5 Descartes'!$D$6:$D$205,'5 Descartes'!$C$6:$C$205,$B178,'5 Descartes'!$B$6:$B$205,$A178)) | I178: =IF($B178="","",$G178-$H178) | J178: =IF($B178="","",$D178-$E178-$F178-$G178) | K178: =IF(OR($B178="",$D178=0),"",$J178/$D178) | L178: =IF($B178="","",IF($D178=0,"Sin produccion registrada",IF($E178=0,"Sin ventas mapeadas en Fudo",IF(AND($K178<>"",ABS($K178)>Config!$B$48),IF($J178>0,"Salida sin explicar: consumo no registrado o faltante","Se vendio mas de lo elaborado: revisar stock previo"),IF($I178<>0,"Hay descarte sin detallar en la planilla 5","OK"))))) | M178: =IF($K178="","",ABS($K178)+ROW()/1000000)
A179: Sandwiches | B179: =IF('4 Prod Sandwiches'!$A15="","",'4 Prod Sandwiches'!$A15) | C179: =IF('4 Prod Sandwiches'!$B15="","",'4 Prod Sandwiches'!$B15) | D179: ='4 Prod Sandwiches'!$Q15 | E179: =IF($B179="","",SUMIFS('8 Fudo Ventas'!$B$6:$B$305,'8 Fudo Ventas'!$D$6:$D$305,$B179,'8 Fudo Ventas'!$C$6:$C$305,$A179)) | F179: =IF($B179="","",SUMIFS('8 Fudo Consumos'!$D$6:$D$255,'8 Fudo Consumos'!$B$6:$B$255,$B179,'8 Fudo Consumos'!$C$6:$C$255,$A179)) | G179: ='4 Prod Sandwiches'!$R15 | H179: =IF($B179="","",SUMIFS('5 Descartes'!$D$6:$D$205,'5 Descartes'!$C$6:$C$205,$B179,'5 Descartes'!$B$6:$B$205,$A179)) | I179: =IF($B179="","",$G179-$H179) | J179: =IF($B179="","",$D179-$E179-$F179-$G179) | K179: =IF(OR($B179="",$D179=0),"",$J179/$D179) | L179: =IF($B179="","",IF($D179=0,"Sin produccion registrada",IF($E179=0,"Sin ventas mapeadas en Fudo",IF(AND($K179<>"",ABS($K179)>Config!$B$48),IF($J179>0,"Salida sin explicar: consumo no registrado o faltante","Se vendio mas de lo elaborado: revisar stock previo"),IF($I179<>0,"Hay descarte sin detallar en la planilla 5","OK"))))) | M179: =IF($K179="","",ABS($K179)+ROW()/1000000)
A180: Sandwiches | B180: =IF('4 Prod Sandwiches'!$A16="","",'4 Prod Sandwiches'!$A16) | C180: =IF('4 Prod Sandwiches'!$B16="","",'4 Prod Sandwiches'!$B16) | D180: ='4 Prod Sandwiches'!$Q16 | E180: =IF($B180="","",SUMIFS('8 Fudo Ventas'!$B$6:$B$305,'8 Fudo Ventas'!$D$6:$D$305,$B180,'8 Fudo Ventas'!$C$6:$C$305,$A180)) | F180: =IF($B180="","",SUMIFS('8 Fudo Consumos'!$D$6:$D$255,'8 Fudo Consumos'!$B$6:$B$255,$B180,'8 Fudo Consumos'!$C$6:$C$255,$A180)) | G180: ='4 Prod Sandwiches'!$R16 | H180: =IF($B180="","",SUMIFS('5 Descartes'!$D$6:$D$205,'5 Descartes'!$C$6:$C$205,$B180,'5 Descartes'!$B$6:$B$205,$A180)) | I180: =IF($B180="","",$G180-$H180) | J180: =IF($B180="","",$D180-$E180-$F180-$G180) | K180: =IF(OR($B180="",$D180=0),"",$J180/$D180) | L180: =IF($B180="","",IF($D180=0,"Sin produccion registrada",IF($E180=0,"Sin ventas mapeadas en Fudo",IF(AND($K180<>"",ABS($K180)>Config!$B$48),IF($J180>0,"Salida sin explicar: consumo no registrado o faltante","Se vendio mas de lo elaborado: revisar stock previo"),IF($I180<>0,"Hay descarte sin detallar en la planilla 5","OK"))))) | M180: =IF($K180="","",ABS($K180)+ROW()/1000000)
A181: Sandwiches | B181: =IF('4 Prod Sandwiches'!$A17="","",'4 Prod Sandwiches'!$A17) | C181: =IF('4 Prod Sandwiches'!$B17="","",'4 Prod Sandwiches'!$B17) | D181: ='4 Prod Sandwiches'!$Q17 | E181: =IF($B181="","",SUMIFS('8 Fudo Ventas'!$B$6:$B$305,'8 Fudo Ventas'!$D$6:$D$305,$B181,'8 Fudo Ventas'!$C$6:$C$305,$A181)) | F181: =IF($B181="","",SUMIFS('8 Fudo Consumos'!$D$6:$D$255,'8 Fudo Consumos'!$B$6:$B$255,$B181,'8 Fudo Consumos'!$C$6:$C$255,$A181)) | G181: ='4 Prod Sandwiches'!$R17 | H181: =IF($B181="","",SUMIFS('5 Descartes'!$D$6:$D$205,'5 Descartes'!$C$6:$C$205,$B181,'5 Descartes'!$B$6:$B$205,$A181)) | I181: =IF($B181="","",$G181-$H181) | J181: =IF($B181="","",$D181-$E181-$F181-$G181) | K181: =IF(OR($B181="",$D181=0),"",$J181/$D181) | L181: =IF($B181="","",IF($D181=0,"Sin produccion registrada",IF($E181=0,"Sin ventas mapeadas en Fudo",IF(AND($K181<>"",ABS($K181)>Config!$B$48),IF($J181>0,"Salida sin explicar: consumo no registrado o faltante","Se vendio mas de lo elaborado: revisar stock previo"),IF($I181<>0,"Hay descarte sin detallar en la planilla 5","OK"))))) | M181: =IF($K181="","",ABS($K181)+ROW()/1000000)
... A186: Sandwiches | B186: =IF('4 Prod Sandwiches'!$A22="","",'4 Prod Sandwiches'!$A22) | C186: =IF('4 Prod Sandwiches'!$B22="","",'4 Prod Sandwiches'!$B22) | D186: ='4 Prod Sandwiches'!$Q22 | E186: =IF($B186="","",SUMIFS('8 Fudo Ventas'!$B$6:$B$305,'8 Fudo Ventas'!$D$6:$D$305,$B186,'8 Fudo Ventas'!$C$6:$C$305,$A186)) | F186: =IF($B186="","",SUMIFS('8 Fudo Consumos'!$D$6:$D$255,'8 Fudo Consumos'!$B$6:$B$255,$B186,'8 Fudo Consumos'!$C$6:$C$255,$A186)) | G186: ='4 Prod Sandwiches'!$R22 | H186: =IF($B186="","",SUMIFS('5 Descartes'!$D$6:$D$205,'5 Descartes'!$C$6:$C$205,$B186,'5 Descartes'!$B$6:$B$205,$A186)) | I186: =IF($B186="","",$G186-$H186) | J186: =IF($B186="","",$D186-$E186-$F186-$G186) | K186: =IF(OR($B186="",$D186=0),"",$J186/$D186) | L186: =IF($B186="","",IF($D186=0,"Sin produccion registrada",IF($E186=0,"Sin ventas mapeadas en Fudo",IF(AND($K186<>"",ABS($K186)>Config!$B$48),IF($J186>0,"Salida sin explicar: consumo no registrado o faltante","Se vendio mas de lo elaborado: revisar stock previo"),IF($I186<>0,"Hay descarte sin detallar en la planilla 5","OK"))))) | M186: =IF($K186="","",ABS($K186)+ROW()/1000000)
A187: Cocina San Luis | B187: =IF('4 Prod Cocina SL'!$A6="","",'4 Prod Cocina SL'!$A6) | C187: =IF('4 Prod Cocina SL'!$B6="","",'4 Prod Cocina SL'!$B6) | D187: ='4 Prod Cocina SL'!$Q6 | E187: =IF($B187="","",SUMIFS('8 Fudo Ventas'!$B$6:$B$305,'8 Fudo Ventas'!$D$6:$D$305,$B187,'8 Fudo Ventas'!$C$6:$C$305,$A187)) | F187: =IF($B187="","",SUMIFS('8 Fudo Consumos'!$D$6:$D$255,'8 Fudo Consumos'!$B$6:$B$255,$B187,'8 Fudo Consumos'!$C$6:$C$255,$A187)) | G187: ='4 Prod Cocina SL'!$R6 | H187: =IF($B187="","",SUMIFS('5 Descartes'!$D$6:$D$205,'5 Descartes'!$C$6:$C$205,$B187,'5 Descartes'!$B$6:$B$205,$A187)) | I187: =IF($B187="","",$G187-$H187) | J187: =IF($B187="","",$D187-$E187-$F187-$G187) | K187: =IF(OR($B187="",$D187=0),"",$J187/$D187) | L187: =IF($B187="","",IF($D187=0,"Sin produccion registrada",IF($E187=0,"Sin ventas mapeadas en Fudo",IF(AND($K187<>"",ABS($K187)>Config!$B$48),IF($J187>0,"Salida sin explicar: consumo no registrado o faltante","Se vendio mas de lo elaborado: revisar stock previo"),IF($I187<>0,"Hay descarte sin detallar en la planilla 5","OK"))))) | M187: =IF($K187="","",ABS($K187)+ROW()/1000000)
A188: Cocina San Luis | B188: =IF('4 Prod Cocina SL'!$A7="","",'4 Prod Cocina SL'!$A7) | C188: =IF('4 Prod Cocina SL'!$B7="","",'4 Prod Cocina SL'!$B7) | D188: ='4 Prod Cocina SL'!$Q7 | E188: =IF($B188="","",SUMIFS('8 Fudo Ventas'!$B$6:$B$305,'8 Fudo Ventas'!$D$6:$D$305,$B188,'8 Fudo Ventas'!$C$6:$C$305,$A188)) | F188: =IF($B188="","",SUMIFS('8 Fudo Consumos'!$D$6:$D$255,'8 Fudo Consumos'!$B$6:$B$255,$B188,'8 Fudo Consumos'!$C$6:$C$255,$A188)) | G188: ='4 Prod Cocina SL'!$R7 | H188: =IF($B188="","",SUMIFS('5 Descartes'!$D$6:$D$205,'5 Descartes'!$C$6:$C$205,$B188,'5 Descartes'!$B$6:$B$205,$A188)) | I188: =IF($B188="","",$G188-$H188) | J188: =IF($B188="","",$D188-$E188-$F188-$G188) | K188: =IF(OR($B188="",$D188=0),"",$J188/$D188) | L188: =IF($B188="","",IF($D188=0,"Sin produccion registrada",IF($E188=0,"Sin ventas mapeadas en Fudo",IF(AND($K188<>"",ABS($K188)>Config!$B$48),IF($J188>0,"Salida sin explicar: consumo no registrado o faltante","Se vendio mas de lo elaborado: revisar stock previo"),IF($I188<>0,"Hay descarte sin detallar en la planilla 5","OK"))))) | M188: =IF($K188="","",ABS($K188)+ROW()/1000000)
A189: Cocina San Luis | B189: =IF('4 Prod Cocina SL'!$A8="","",'4 Prod Cocina SL'!$A8) | C189: =IF('4 Prod Cocina SL'!$B8="","",'4 Prod Cocina SL'!$B8) | D189: ='4 Prod Cocina SL'!$Q8 | E189: =IF($B189="","",SUMIFS('8 Fudo Ventas'!$B$6:$B$305,'8 Fudo Ventas'!$D$6:$D$305,$B189,'8 Fudo Ventas'!$C$6:$C$305,$A189)) | F189: =IF($B189="","",SUMIFS('8 Fudo Consumos'!$D$6:$D$255,'8 Fudo Consumos'!$B$6:$B$255,$B189,'8 Fudo Consumos'!$C$6:$C$255,$A189)) | G189: ='4 Prod Cocina SL'!$R8 | H189: =IF($B189="","",SUMIFS('5 Descartes'!$D$6:$D$205,'5 Descartes'!$C$6:$C$205,$B189,'5 Descartes'!$B$6:$B$205,$A189)) | I189: =IF($B189="","",$G189-$H189) | J189: =IF($B189="","",$D189-$E189-$F189-$G189) | K189: =IF(OR($B189="",$D189=0),"",$J189/$D189) | L189: =IF($B189="","",IF($D189=0,"Sin produccion registrada",IF($E189=0,"Sin ventas mapeadas en Fudo",IF(AND($K189<>"",ABS($K189)>Config!$B$48),IF($J189>0,"Salida sin explicar: consumo no registrado o faltante","Se vendio mas de lo elaborado: revisar stock previo"),IF($I189<>0,"Hay descarte sin detallar en la planilla 5","OK"))))) | M189: =IF($K189="","",ABS($K189)+ROW()/1000000)
A190: Cocina San Luis | B190: =IF('4 Prod Cocina SL'!$A9="","",'4 Prod Cocina SL'!$A9) | C190: =IF('4 Prod Cocina SL'!$B9="","",'4 Prod Cocina SL'!$B9) | D190: ='4 Prod Cocina SL'!$Q9 | E190: =IF($B190="","",SUMIFS('8 Fudo Ventas'!$B$6:$B$305,'8 Fudo Ventas'!$D$6:$D$305,$B190,'8 Fudo Ventas'!$C$6:$C$305,$A190)) | F190: =IF($B190="","",SUMIFS('8 Fudo Consumos'!$D$6:$D$255,'8 Fudo Consumos'!$B$6:$B$255,$B190,'8 Fudo Consumos'!$C$6:$C$255,$A190)) | G190: ='4 Prod Cocina SL'!$R9 | H190: =IF($B190="","",SUMIFS('5 Descartes'!$D$6:$D$205,'5 Descartes'!$C$6:$C$205,$B190,'5 Descartes'!$B$6:$B$205,$A190)) | I190: =IF($B190="","",$G190-$H190) | J190: =IF($B190="","",$D190-$E190-$F190-$G190) | K190: =IF(OR($B190="",$D190=0),"",$J190/$D190) | L190: =IF($B190="","",IF($D190=0,"Sin produccion registrada",IF($E190=0,"Sin ventas mapeadas en Fudo",IF(AND($K190<>"",ABS($K190)>Config!$B$48),IF($J190>0,"Salida sin explicar: consumo no registrado o faltante","Se vendio mas de lo elaborado: revisar stock previo"),IF($I190<>0,"Hay descarte sin detallar en la planilla 5","OK"))))) | M190: =IF($K190="","",ABS($K190)+ROW()/1000000)
A191: Cocina San Luis | B191: =IF('4 Prod Cocina SL'!$A10="","",'4 Prod Cocina SL'!$A10) | C191: =IF('4 Prod Cocina SL'!$B10="","",'4 Prod Cocina SL'!$B10) | D191: ='4 Prod Cocina SL'!$Q10 | E191: =IF($B191="","",SUMIFS('8 Fudo Ventas'!$B$6:$B$305,'8 Fudo Ventas'!$D$6:$D$305,$B191,'8 Fudo Ventas'!$C$6:$C$305,$A191)) | F191: =IF($B191="","",SUMIFS('8 Fudo Consumos'!$D$6:$D$255,'8 Fudo Consumos'!$B$6:$B$255,$B191,'8 Fudo Consumos'!$C$6:$C$255,$A191)) | G191: ='4 Prod Cocina SL'!$R10 | H191: =IF($B191="","",SUMIFS('5 Descartes'!$D$6:$D$205,'5 Descartes'!$C$6:$C$205,$B191,'5 Descartes'!$B$6:$B$205,$A191)) | I191: =IF($B191="","",$G191-$H191) | J191: =IF($B191="","",$D191-$E191-$F191-$G191) | K191: =IF(OR($B191="",$D191=0),"",$J191/$D191) | L191: =IF($B191="","",IF($D191=0,"Sin produccion registrada",IF($E191=0,"Sin ventas mapeadas en Fudo",IF(AND($K191<>"",ABS($K191)>Config!$B$48),IF($J191>0,"Salida sin explicar: consumo no registrado o faltante","Se vendio mas de lo elaborado: revisar stock previo"),IF($I191<>0,"Hay descarte sin detallar en la planilla 5","OK"))))) | M191: =IF($K191="","",ABS($K191)+ROW()/1000000)
A192: Cocina San Luis | B192: =IF('4 Prod Cocina SL'!$A11="","",'4 Prod Cocina SL'!$A11) | C192: =IF('4 Prod Cocina SL'!$B11="","",'4 Prod Cocina SL'!$B11) | D192: ='4 Prod Cocina SL'!$Q11 | E192: =IF($B192="","",SUMIFS('8 Fudo Ventas'!$B$6:$B$305,'8 Fudo Ventas'!$D$6:$D$305,$B192,'8 Fudo Ventas'!$C$6:$C$305,$A192)) | F192: =IF($B192="","",SUMIFS('8 Fudo Consumos'!$D$6:$D$255,'8 Fudo Consumos'!$B$6:$B$255,$B192,'8 Fudo Consumos'!$C$6:$C$255,$A192)) | G192: ='4 Prod Cocina SL'!$R11 | H192: =IF($B192="","",SUMIFS('5 Descartes'!$D$6:$D$205,'5 Descartes'!$C$6:$C$205,$B192,'5 Descartes'!$B$6:$B$205,$A192)) | I192: =IF($B192="","",$G192-$H192) | J192: =IF($B192="","",$D192-$E192-$F192-$G192) | K192: =IF(OR($B192="",$D192=0),"",$J192/$D192) | L192: =IF($B192="","",IF($D192=0,"Sin produccion registrada",IF($E192=0,"Sin ventas mapeadas en Fudo",IF(AND($K192<>"",ABS($K192)>Config!$B$48),IF($J192>0,"Salida sin explicar: consumo no registrado o faltante","Se vendio mas de lo elaborado: revisar stock previo"),IF($I192<>0,"Hay descarte sin detallar en la planilla 5","OK"))))) | M192: =IF($K192="","",ABS($K192)+ROW()/1000000)
A193: Cocina San Luis | B193: =IF('4 Prod Cocina SL'!$A12="","",'4 Prod Cocina SL'!$A12) | C193: =IF('4 Prod Cocina SL'!$B12="","",'4 Prod Cocina SL'!$B12) | D193: ='4 Prod Cocina SL'!$Q12 | E193: =IF($B193="","",SUMIFS('8 Fudo Ventas'!$B$6:$B$305,'8 Fudo Ventas'!$D$6:$D$305,$B193,'8 Fudo Ventas'!$C$6:$C$305,$A193)) | F193: =IF($B193="","",SUMIFS('8 Fudo Consumos'!$D$6:$D$255,'8 Fudo Consumos'!$B$6:$B$255,$B193,'8 Fudo Consumos'!$C$6:$C$255,$A193)) | G193: ='4 Prod Cocina SL'!$R12 | H193: =IF($B193="","",SUMIFS('5 Descartes'!$D$6:$D$205,'5 Descartes'!$C$6:$C$205,$B193,'5 Descartes'!$B$6:$B$205,$A193)) | I193: =IF($B193="","",$G193-$H193) | J193: =IF($B193="","",$D193-$E193-$F193-$G193) | K193: =IF(OR($B193="",$D193=0),"",$J193/$D193) | L193: =IF($B193="","",IF($D193=0,"Sin produccion registrada",IF($E193=0,"Sin ventas mapeadas en Fudo",IF(AND($K193<>"",ABS($K193)>Config!$B$48),IF($J193>0,"Salida sin explicar: consumo no registrado o faltante","Se vendio mas de lo elaborado: revisar stock previo"),IF($I193<>0,"Hay descarte sin detallar en la planilla 5","OK"))))) | M193: =IF($K193="","",ABS($K193)+ROW()/1000000)
A194: Cocina San Luis | B194: =IF('4 Prod Cocina SL'!$A13="","",'4 Prod Cocina SL'!$A13) | C194: =IF('4 Prod Cocina SL'!$B13="","",'4 Prod Cocina SL'!$B13) | D194: ='4 Prod Cocina SL'!$Q13 | E194: =IF($B194="","",SUMIFS('8 Fudo Ventas'!$B$6:$B$305,'8 Fudo Ventas'!$D$6:$D$305,$B194,'8 Fudo Ventas'!$C$6:$C$305,$A194)) | F194: =IF($B194="","",SUMIFS('8 Fudo Consumos'!$D$6:$D$255,'8 Fudo Consumos'!$B$6:$B$255,$B194,'8 Fudo Consumos'!$C$6:$C$255,$A194)) | G194: ='4 Prod Cocina SL'!$R13 | H194: =IF($B194="","",SUMIFS('5 Descartes'!$D$6:$D$205,'5 Descartes'!$C$6:$C$205,$B194,'5 Descartes'!$B$6:$B$205,$A194)) | I194: =IF($B194="","",$G194-$H194) | J194: =IF($B194="","",$D194-$E194-$F194-$G194) | K194: =IF(OR($B194="",$D194=0),"",$J194/$D194) | L194: =IF($B194="","",IF($D194=0,"Sin produccion registrada",IF($E194=0,"Sin ventas mapeadas en Fudo",IF(AND($K194<>"",ABS($K194)>Config!$B$48),IF($J194>0,"Salida sin explicar: consumo no registrado o faltante","Se vendio mas de lo elaborado: revisar stock previo"),IF($I194<>0,"Hay descarte sin detallar en la planilla 5","OK"))))) | M194: =IF($K194="","",ABS($K194)+ROW()/1000000)
A195: Cocina San Luis | B195: =IF('4 Prod Cocina SL'!$A14="","",'4 Prod Cocina SL'!$A14) | C195: =IF('4 Prod Cocina SL'!$B14="","",'4 Prod Cocina SL'!$B14) | D195: ='4 Prod Cocina SL'!$Q14 | E195: =IF($B195="","",SUMIFS('8 Fudo Ventas'!$B$6:$B$305,'8 Fudo Ventas'!$D$6:$D$305,$B195,'8 Fudo Ventas'!$C$6:$C$305,$A195)) | F195: =IF($B195="","",SUMIFS('8 Fudo Consumos'!$D$6:$D$255,'8 Fudo Consumos'!$B$6:$B$255,$B195,'8 Fudo Consumos'!$C$6:$C$255,$A195)) | G195: ='4 Prod Cocina SL'!$R14 | H195: =IF($B195="","",SUMIFS('5 Descartes'!$D$6:$D$205,'5 Descartes'!$C$6:$C$205,$B195,'5 Descartes'!$B$6:$B$205,$A195)) | I195: =IF($B195="","",$G195-$H195) | J195: =IF($B195="","",$D195-$E195-$F195-$G195) | K195: =IF(OR($B195="",$D195=0),"",$J195/$D195) | L195: =IF($B195="","",IF($D195=0,"Sin produccion registrada",IF($E195=0,"Sin ventas mapeadas en Fudo",IF(AND($K195<>"",ABS($K195)>Config!$B$48),IF($J195>0,"Salida sin explicar: consumo no registrado o faltante","Se vendio mas de lo elaborado: revisar stock previo"),IF($I195<>0,"Hay descarte sin detallar en la planilla 5","OK"))))) | M195: =IF($K195="","",ABS($K195)+ROW()/1000000)
A196: Cocina San Luis | B196: =IF('4 Prod Cocina SL'!$A15="","",'4 Prod Cocina SL'!$A15) | C196: =IF('4 Prod Cocina SL'!$B15="","",'4 Prod Cocina SL'!$B15) | D196: ='4 Prod Cocina SL'!$Q15 | E196: =IF($B196="","",SUMIFS('8 Fudo Ventas'!$B$6:$B$305,'8 Fudo Ventas'!$D$6:$D$305,$B196,'8 Fudo Ventas'!$C$6:$C$305,$A196)) | F196: =IF($B196="","",SUMIFS('8 Fudo Consumos'!$D$6:$D$255,'8 Fudo Consumos'!$B$6:$B$255,$B196,'8 Fudo Consumos'!$C$6:$C$255,$A196)) | G196: ='4 Prod Cocina SL'!$R15 | H196: =IF($B196="","",SUMIFS('5 Descartes'!$D$6:$D$205,'5 Descartes'!$C$6:$C$205,$B196,'5 Descartes'!$B$6:$B$205,$A196)) | I196: =IF($B196="","",$G196-$H196) | J196: =IF($B196="","",$D196-$E196-$F196-$G196) | K196: =IF(OR($B196="",$D196=0),"",$J196/$D196) | L196: =IF($B196="","",IF($D196=0,"Sin produccion registrada",IF($E196=0,"Sin ventas mapeadas en Fudo",IF(AND($K196<>"",ABS($K196)>Config!$B$48),IF($J196>0,"Salida sin explicar: consumo no registrado o faltante","Se vendio mas de lo elaborado: revisar stock previo"),IF($I196<>0,"Hay descarte sin detallar en la planilla 5","OK"))))) | M196: =IF($K196="","",ABS($K196)+ROW()/1000000)
A197: Cocina San Luis | B197: =IF('4 Prod Cocina SL'!$A16="","",'4 Prod Cocina SL'!$A16) | C197: =IF('4 Prod Cocina SL'!$B16="","",'4 Prod Cocina SL'!$B16) | D197: ='4 Prod Cocina SL'!$Q16 | E197: =IF($B197="","",SUMIFS('8 Fudo Ventas'!$B$6:$B$305,'8 Fudo Ventas'!$D$6:$D$305,$B197,'8 Fudo Ventas'!$C$6:$C$305,$A197)) | F197: =IF($B197="","",SUMIFS('8 Fudo Consumos'!$D$6:$D$255,'8 Fudo Consumos'!$B$6:$B$255,$B197,'8 Fudo Consumos'!$C$6:$C$255,$A197)) | G197: ='4 Prod Cocina SL'!$R16 | H197: =IF($B197="","",SUMIFS('5 Descartes'!$D$6:$D$205,'5 Descartes'!$C$6:$C$205,$B197,'5 Descartes'!$B$6:$B$205,$A197)) | I197: =IF($B197="","",$G197-$H197) | J197: =IF($B197="","",$D197-$E197-$F197-$G197) | K197: =IF(OR($B197="",$D197=0),"",$J197/$D197) | L197: =IF($B197="","",IF($D197=0,"Sin produccion registrada",IF($E197=0,"Sin ventas mapeadas en Fudo",IF(AND($K197<>"",ABS($K197)>Config!$B$48),IF($J197>0,"Salida sin explicar: consumo no registrado o faltante","Se vendio mas de lo elaborado: revisar stock previo"),IF($I197<>0,"Hay descarte sin detallar en la planilla 5","OK"))))) | M197: =IF($K197="","",ABS($K197)+ROW()/1000000)
A198: Cocina San Luis | B198: =IF('4 Prod Cocina SL'!$A17="","",'4 Prod Cocina SL'!$A17) | C198: =IF('4 Prod Cocina SL'!$B17="","",'4 Prod Cocina SL'!$B17) | D198: ='4 Prod Cocina SL'!$Q17 | E198: =IF($B198="","",SUMIFS('8 Fudo Ventas'!$B$6:$B$305,'8 Fudo Ventas'!$D$6:$D$305,$B198,'8 Fudo Ventas'!$C$6:$C$305,$A198)) | F198: =IF($B198="","",SUMIFS('8 Fudo Consumos'!$D$6:$D$255,'8 Fudo Consumos'!$B$6:$B$255,$B198,'8 Fudo Consumos'!$C$6:$C$255,$A198)) | G198: ='4 Prod Cocina SL'!$R17 | H198: =IF($B198="","",SUMIFS('5 Descartes'!$D$6:$D$205,'5 Descartes'!$C$6:$C$205,$B198,'5 Descartes'!$B$6:$B$205,$A198)) | I198: =IF($B198="","",$G198-$H198) | J198: =IF($B198="","",$D198-$E198-$F198-$G198) | K198: =IF(OR($B198="",$D198=0),"",$J198/$D198) | L198: =IF($B198="","",IF($D198=0,"Sin produccion registrada",IF($E198=0,"Sin ventas mapeadas en Fudo",IF(AND($K198<>"",ABS($K198)>Config!$B$48),IF($J198>0,"Salida sin explicar: consumo no registrado o faltante","Se vendio mas de lo elaborado: revisar stock previo"),IF($I198<>0,"Hay descarte sin detallar en la planilla 5","OK"))))) | M198: =IF($K198="","",ABS($K198)+ROW()/1000000)
... A226: Cocina San Luis | B226: =IF('4 Prod Cocina SL'!$A45="","",'4 Prod Cocina SL'!$A45) | C226: =IF('4 Prod Cocina SL'!$B45="","",'4 Prod Cocina SL'!$B45) | D226: ='4 Prod Cocina SL'!$Q45 | E226: =IF($B226="","",SUMIFS('8 Fudo Ventas'!$B$6:$B$305,'8 Fudo Ventas'!$D$6:$D$305,$B226,'8 Fudo Ventas'!$C$6:$C$305,$A226)) | F226: =IF($B226="","",SUMIFS('8 Fudo Consumos'!$D$6:$D$255,'8 Fudo Consumos'!$B$6:$B$255,$B226,'8 Fudo Consumos'!$C$6:$C$255,$A226)) | G226: ='4 Prod Cocina SL'!$R45 | H226: =IF($B226="","",SUMIFS('5 Descartes'!$D$6:$D$205,'5 Descartes'!$C$6:$C$205,$B226,'5 Descartes'!$B$6:$B$205,$A226)) | I226: =IF($B226="","",$G226-$H226) | J226: =IF($B226="","",$D226-$E226-$F226-$G226) | K226: =IF(OR($B226="",$D226=0),"",$J226/$D226) | L226: =IF($B226="","",IF($D226=0,"Sin produccion registrada",IF($E226=0,"Sin ventas mapeadas en Fudo",IF(AND($K226<>"",ABS($K226)>Config!$B$48),IF($J226>0,"Salida sin explicar: consumo no registrado o faltante","Se vendio mas de lo elaborado: revisar stock previo"),IF($I226<>0,"Hay descarte sin detallar en la planilla 5","OK"))))) | M226: =IF($K226="","",ABS($K226)+ROW()/1000000)
A227: TOTALES | D227: =SUM(D$6:D$226) | E227: =SUM(E$6:E$226) | F227: =SUM(F$6:F$226) | G227: =SUM(G$6:G$226) | H227: =SUM(H$6:H$226) | I227: =SUM(I$6:I$226) | J227: =SUM(J$6:J$226) | K227: =IF($D227=0,"",$J227/$D227) | L227: =COUNTIF($L$6:$L$226,"OK")&" productos OK"

Sheet C Consumo Diario
A1: ANALISIS C · CONSUMO DIA POR DIA DE LOS INSUMOS CRITICOS
A2: Consumo del dia = stock del dia anterior + ingresos de ese dia - stock al cierre del dia. Sale de la planilla 3.
A3: Sirve para ubicar EL DIA exacto del desvio. Un consumo negativo = entro mercaderia que nadie anoto ese dia.
A4: AREA | B4: INSUMO | C4: UNID. | D4: =IF(Config!$B$10="","LUN",UPPER("LUN")&" "&TEXT(Config!$B$10,"dd/mm")) | E4: =IF(Config!$B$11="","MAR",UPPER("MAR")&" "&TEXT(Config!$B$11,"dd/mm")) | F4: =IF(Config!$B$12="","MIE",UPPER("MIE")&" "&TEXT(Config!$B$12,"dd/mm")) | G4: =IF(Config!$B$13="","JUE",UPPER("JUE")&" "&TEXT(Config!$B$13,"dd/mm")) | H4: =IF(Config!$B$14="","VIE",UPPER("VIE")&" "&TEXT(Config!$B$14,"dd/mm")) | I4: =IF(Config!$B$15="","SAB",UPPER("SAB")&" "&TEXT(Config!$B$15,"dd/mm")) | J4: =IF(Config!$B$16="","DOM",UPPER("DOM")&" "&TEXT(Config!$B$16,"dd/mm")) | K4: TOTAL SEMANA | L4: PROMEDIO POR DIA | M4: DIA DE MAYOR CONSUMO | N4: ALERTA
